Workbook
Name \1: #REF!
Name \1: #REF!
Name \1: #REF!
Name \a: #REF!
Name \a: #N/A
Name \a: #REF!
Name \b: #REF!
Name \b: #N/A
Name \b: #REF!
Name \c: #REF!
Name \c: #REF!
Name \d: #REF!
Name \d: #REF!
Name \e: #REF!
Name \e: #REF!
Name \f: #REF!
Name \f: #REF!
Name \g: #REF!
Name \g: #REF!
Name \h: #REF!
Name \h: #REF!
Name \i: #REF!
Name \i: #REF!
Name \j: #REF!
Name \j: #REF!
Name \m: #REF!
Name \m: #REF!
Name \n: #REF!
Name \n: #REF!
Name \p: #REF!
Name \p: #REF!
Name \p: #REF!
Name \q: #REF!
Name \q: #REF!
Name \q: #REF!
Name \r: #REF!
Name \r: #REF!
Name \S: #REF!
Name \s: #REF!
Name \S: #REF!
Name \t: #REF!
Name \t: #REF!
Name \w: #REF!
Name \w: #REF!
Name \w: #REF!
Name \x: #REF!
Name \x: #REF!
Name \y: #REF!
Name \y: #REF!
Name \z: #REF!
Name \z: #REF!
Name _\p: #REF!
Name _\p: #REF!
Name ___________________\a: #REF!
Name ___________________\a: #REF!
Name ___________________\d: #REF!
Name ___________________\d: #REF!
Name ___________________\e: #REF!
Name ___________________\e: #REF!
Name ___________________\i: #REF!

Sheet Cubicacion_General
E1: Sistema de impulsion refino | F1: 3631
E2: Lixiviacion piscina emergencia | F2: 3632 | AK2: Avance Acumulado Fisico | AU2: Avance Cañerias E.D.P
E3: Red Contra Incendio | F3: 6340 | AC3: Según Listado | AD3: MM.CUBICADO | AE3: METROS.CUBICADO | AF3: Avance Fisico | AK3: Acumulado Anterior | AM3: Acumulado Actual | AO3: Acumulado Total | AS3: Avance EDP | AU3: EDP_Acumulado Anterior | AW3: EDP_Acumulado Actual | AY3: EDP_Acumulado Total
AC4: =SUBTOTAL(9,AC6:AC482) -> 8807 | AD4: =SUBTOTAL(9,AD6:AD480) -> 11956815 | AE4: =SUBTOTAL(9,AE6:AE480) -> 11956.815 | AF4: 0.1 | AG4: 0.25 | AH4: 0.55 | AI4: 0.1 | AK4: =SUBTOTAL(9,AK6:AK460) -> 0 | AL4: =SUBTOTAL(9,AL6:AL460) -> 0 | AM4: =SUBTOTAL(9,AM6:AM460) -> 0 | AN4: =SUBTOTAL(9,AN6:AN460) -> 0 | AO4: =SUBTOTAL(9,AO6:AO460) -> 0 | AP4: =SUBTOTAL(9,AP6:AP460) -> 0 | AS4: 0.9 | AT4: 0.1 | AV4: =+SUBTOTAL(9,AV6:AV1269) -> 0 | AZ4: =+SUBTOTAL(9,AZ6:AZ1269) -> 0 | BA4: 3 W L A
B5: N° | C5: Contrato | D5: Item Contrato | E5: Area | F5: Codigo Area | G5: N° P&ID Codelco | H5: Rev | I5: N° Plano | J5: Rev | K5: Nro. Linea | L5: Correlativo | M5: Lamina | N5: DN(inch) | O5: DN(mm) | P5: Clase | Q5: Material | R5: Servicio | S5: Aislación | T5: Desde | U5: Hasta | V5: Densidad del Fluido kg/m3 | W5: Presión | X5: T°C | Y5: Presión Nota (1) | Z5: Temperatura C° | AA5: Fluido de Prueba | AB5: Comentario | AC5: Longitud(mts) | AD5: Longitud mm (Cubicado) | AE5: Longitud Mts (Cubicado) | AF5: Traslado | AG5: Posicionamiento | AH5: Montaje-Pruebas | AI5: Protocolos | AJ5: HH Unitaria | AK5: HH | AL5: Cantidad | AM5: HH | AN5: Cantidad | AO5: HH | AP5: Cantidad | AQ5: Programa Maestro | AR5: N° Protocolo | AS5: Recepcion y Traslado | AT5: Protocolo | AU5: % | AV5: Cantidad | AW5: % | AX5: Cantidad | AY5: % | AZ5: Cantidad | BA5: Recepcion y Traslado | BB5: Fabricacion | BC5: Posicionamiento | BD5: Montaje | BE5: Soportacion | BF5: Protocolo
B6: 1 | C6: CC-403 | E6: Sistema de impulsion refino | F6: =LEFT(K6,4) -> 3631 | G6: 4600027788-03631-201CA-00002 | H6: 0 | K6: 3631-RA-16"-T1-0951-N | L6: 951 | N6: 16" | O6: 400 | P6: T1 | R6: RA | S6: N | T6: Bomba 3631-BVT-001 | U6: 3631-RA-30"-T1-0955-N | V6: 1134 | W6: 5102 | X6: 38 | Y6: 6377.6 | Z6: 20° | AA6: Agua | AC6: 6 | AD6: 7720 | AE6: =AD6/1000 -> 7.72 | AN6: =+AP6-AL6 -> 0 | AP6: =+CONCATENATE(AF6*$AF$4+AG6*$AG$4+AH6*$AH$4+AI6*$AI$4) -> 0 | AQ6: =AP6 -> 0 | AS6: =AH6 -> 0 | AT6: =AI6 -> 0
B7: 2 | C7: CC-403 | E7: Sistema de impulsion refino | F7: =LEFT(K7,4) -> 3631 | G7: 4600027788-03631-201CA-00002 | H7: 0 | K7: 3631-RA-16"-T1-0952-N | L7: 952 | N7: 16" | O7: 400 | P7: T1 | R7: RA | S7: N | T7: Bomba 3631-BVT-002 | U7: 3631-RA-30"-T1-0955-N | V7: 1134 | W7: 5102 | X7: 38 | Y7: 6377.6 | Z7: 20° | AA7: Agua | AC7: 6 | AD7: 7720 | AE7: =AD7/1000 -> 7.72 | AN7: =+AP7-AL7 -> 0 | AP7: =+CONCATENATE(AF7*$AF$4+AG7*$AG$4+AH7*$AH$4+AI7*$AI$4) -> 0 | AQ7: =AP7 -> 0 | AS7: =AH7 -> 0 | AT7: =AI7 -> 0
B8: 3 | C8: CC-403 | E8: Sistema de impulsion refino | F8: =LEFT(K8,4) -> 3631 | G8: 4600027788-03631-201CA-00002 | H8: 0 | K8: 3631-RA-16"-T1-0953-N | L8: 953 | N8: 16" | O8: 400 | P8: T1 | R8: RA | S8: N | T8: Bomba 3631-BVT-003 | U8: 3631-RA-30"-T1-0955-N | V8: 1134 | W8: 5102 | X8: 38 | Y8: 6377.6 | Z8: 20° | AA8: Agua | AC8: 6 | AD8: 7720 | AE8: =AD8/1000 -> 7.72 | AN8: =+AP8-AL8 -> 0 | AP8: =+CONCATENATE(AF8*$AF$4+AG8*$AG$4+AH8*$AH$4+AI8*$AI$4) -> 0 | AQ8: =AP8 -> 0 | AS8: =AH8 -> 0 | AT8: =AI8 -> 0
B9: 4 | C9: CC-403 | E9: Sistema de impulsion refino | F9: =LEFT(K9,4) -> 3631 | G9: 4600027788-03631-201CA-00002 | H9: 0 | K9: 3631-RA-16"-T1-0954-N | L9: 954 | N9: 16" | O9: 400 | P9: T1 | R9: RA | S9: N | T9: Bomba 3631-BVT-004 | U9: 3631-RA-30"-T1-0955-N | V9: 1134 | W9: 5102 | X9: 38 | Y9: 6377.6 | Z9: 20° | AA9: Agua | AC9: 6 | AD9: 7720 | AE9: =AD9/1000 -> 7.72 | AN9: =+AP9-AL9 -> 0 | AP9: =+CONCATENATE(AF9*$AF$4+AG9*$AG$4+AH9*$AH$4+AI9*$AI$4) -> 0 | AQ9: =AP9 -> 0 | AS9: =AH9 -> 0 | AT9: =AI9 -> 0
B10: 5 | C10: CC-403 | E10: Sistema de impulsion refino | F10: =LEFT(K10,4) -> 3631 | G10: 4600027788-03631-201CA-00002 | H10: 0 | I10: 4600027788-03631-502CA-00007 | J10: 0 | K10: 3631-RA-400-H1-0956-N | L10: 956 | M10: 1 | N10: 16" | O10: 400 | P10: H1 | R10: RA | S10: N | T10: 3631-RA-30"-T1-0955-N | U10: Piscina de Reimpulsión OBL | V10: 1134 | W10: 1999 | X10: 20 | Y10: Nota (2) | Z10: 20° | AA10: Agua | AB10: Linea de Drenaje | AC10: 13 | AD10: 11322 | AE10: =AD10/1000 -> 11.322 | AN10: =+AP10-AL10 -> 0 | AP10: =+CONCATENATE(AF10*$AF$4+AG10*$AG$4+AH10*$AH$4+AI10*$AI$4) -> 0 | AQ10: =AP10 -> 0 | AS10: =AH10 -> 0 | AT10: =AI10 -> 0
B11: 6 | C11: CC-403 | E11: Sistema de impulsion refino | F11: =LEFT(K11,4) -> 3631 | G11: 4600027788-03631-201CA-00002 | H11: 0 | K11: 3631-RA-30"-T1-0955-N | L11: 955 | N11: 30" | O11: 760 | P11: T1 | R11: RA | S11: N | T11: Brida Ciega | U11: 3631-RA-710-H1-0956-N | V11: 1134 | W11: 5102 | X11: 38 | Y11: 6377.6 | Z11: 20° | AA11: Agua | AB11: Manifold de Descarga | AC11: 31 | AD11: 15575 | AE11: =AD11/1000 -> 15.575 | AN11: =+AP11-AL11 -> 0 | AP11: =+CONCATENATE(AF11*$AF$4+AG11*$AG$4+AH11*$AH$4+AI11*$AI$4) -> 0 | AQ11: =AP11 -> 0 | AS11: =AH11 -> 0 | AT11: =AI11 -> 0
B12: 7 | C12: CC-403 | E12: Sistema de impulsion refino | F12: =LEFT(K12,4) -> 3631 | G12: 4600027788-03631-201CA-00002 | H12: 0 | K12: 3631-RA-24"-T1-0955-N | L12: 955 | N12: 24" | O12: 630 | P12: T1 | R12: RA | S12: N | T12: Brida Ciega | U12: 3631-RA-710-H1-0956-N | V12: 1134 | W12: 5102 | X12: 38 | Y12: 6377.6 | Z12: 20° | AA12: Agua | AB12: Manifold de Descarga | AC12: - | AD12: 12000 | AE12: =AD12/1000 -> 12 | AN12: =+AP12-AL12 -> 0 | AP12: =+CONCATENATE(AF12*$AF$4+AG12*$AG$4+AH12*$AH$4+AI12*$AI$4) -> 0 | AQ12: =AP12 -> 0 | AS12: =AH12 -> 0 | AT12: =AI12 -> 0
B13: 8 | C13: CC-403 | E13: Sistema de impulsion refino | F13: =LEFT(K13,4) -> 3631 | G13: 4600027788-03631-201CA-00002 | H13: 0 | J13: 0 | K13: 3631-RA-30"-T1-0955-N | L13: 955 | N13: 28" | O13: 710 | P13: T1 | R13: RA | S13: N | T13: Brida Ciega | U13: 3631-RA-710-H1-0956-N | V13: 1134 | W13: 5102 | X13: 38 | Y13: 6377.6 | Z13: 20° | AA13: Agua | AB13: Manifold de Descarga | AC13: - | AD13: 47153 | AE13: =AD13/1000 -> 47.153 | AN13: =+AP13-AL13 -> 0 | AP13: =+CONCATENATE(AF13*$AF$4+AG13*$AG$4+AH13*$AH$4+AI13*$AI$4) -> 0 | AQ13: =AP13 -> 0 | AS13: =AH13 -> 0 | AT13: =AI13 -> 0
B14: 9 | C14: CC-403 | E14: Sistema de impulsion refino | F14: =LEFT(K14,4) -> 3631 | G14: 4600027788-03631-201CA-00002 | H14: 0 | I14: 4600027788-03631-502CA-00003 | J14: 0 | K14: 3631-RA-710-H1-0957-N | L14: 957 | M14: 1 | N14: 28" | O14: 710 | P14: H1 | R14: RA | S14: N | T14: 3631-RA-30"-T1-0955-N | U14: 3631-RA-36"-T1-0958-N Nota (3) | V14: 1134 | W14: 1999 | X14: 20 | Y14: Nota (2) | Z14: 20° | AA14: Agua | AC14: 28 | AD14: 17000 | AE14: =AD14/1000 -> 17 | AN14: =+AP14-AL14 -> 0 | AP14: =+CONCATENATE(AF14*$AF$4+AG14*$AG$4+AH14*$AH$4+AI14*$AI$4) -> 0 | AQ14: =AP14 -> 0 | AS14: =AH14 -> 0 | AT14: =AI14 -> 0
B15: 11 | C15: CC-403 | E15: Sistema de impulsion refino | F15: =LEFT(K15,4) -> 3631 | G15: 4600027788-03631-201CA-00002 | H15: 0 | I15: 4600027788-03631-502CA-00004 | J15: 0 | K15: 3631-RA-710-H1-0957-N | L15: 957 | M15: 2 | N15: 28" | O15: 710 | P15: H1 | R15: RA | S15: N | AD15: 7750 | AE15: =AD15/1000 -> 7.75 | AN15: =+AP15-AL15 -> 0 | AP15: =+CONCATENATE(AF15*$AF$4+AG15*$AG$4+AH15*$AH$4+AI15*$AI$4) -> 0 | AQ15: =AP15 -> 0 | AS15: =AH15 -> 0 | AT15: =AI15 -> 0
B16: 13 | C16: CC-403 | E16: Sistema de impulsion refino | F16: =LEFT(K16,4) -> 3631 | G16: 4600027788-03631-201CA-00002 | H16: 0 | I16: 4600027788-03631-502CA-00005 | J16: 0 | K16: 3631-RA-710-H1-0957-N | L16: 957 | M16: 3 | N16: 24" | O16: 710 | P16: H1 | R16: RA | S16: N | AD16: 3570 | AE16: =AD16/1000 -> 3.57 | AN16: =+AP16-AL16 -> 0 | AP16: =+CONCATENATE(AF16*$AF$4+AG16*$AG$4+AH16*$AH$4+AI16*$AI$4) -> 0 | AQ16: =AP16 -> 0 | AS16: =AH16 -> 0 | AT16: =AI16 -> 0
B17: 15 | C17: CC-403 | E17: Sistema de impulsion refino | F17: =LEFT(K17,4) -> 3631 | I17: 4600027788-03631-502CA-00006 | J17: 0 | K17: 3631-RA-110-H4-0958-N | L17: 958 | M17: 1 | N17: 4" | O17: 110 | P17: H4 | R17: RA | S17: N | AD17: 13149 | AE17: =AD17/1000 -> 13.149 | AN17: =+AP17-AL17 -> 0 | AP17: =+CONCATENATE(AF17*$AF$4+AG17*$AG$4+AH17*$AH$4+AI17*$AI$4) -> 0 | AQ17: =AP17 -> 0 | AS17: =AH17 -> 0 | AT17: =AI17 -> 0
B18: 16 | C18: CC-403 | E18: Sistema de impulsion refino | F18: =LEFT(K18,4) -> 3631 | K18: 3631-RA-500-H3-0958-N | L18: 958 | N18: 20" | O18: 500 | P18: H3 | R18: RA | S18: N | AD18: 550000 | AE18: =AD18/1000 -> 550 | AN18: =+AP18-AL18 -> 0 | AP18: =+CONCATENATE(AF18*$AF$4+AG18*$AG$4+AH18*$AH$4+AI18*$AI$4) -> 0 | AQ18: =AP18 -> 0 | AS18: =AH18 -> 0 | AT18: =AI18 -> 0
B19: 17 | C19: CC-403 | E19: Sistema de impulsion refino | F19: =LEFT(K19,4) -> 3631 | K19: 3631-RA-630-H3-0958-N | L19: 958 | N19: 24" | O19: 630 | P19: H3 | R19: RA | S19: N | AD19: 510000 | AE19: =AD19/1000 -> 510 | AN19: =+AP19-AL19 -> 0 | AP19: =+CONCATENATE(AF19*$AF$4+AG19*$AG$4+AH19*$AH$4+AI19*$AI$4) -> 0 | AQ19: =AP19 -> 0 | AS19: =AH19 -> 0 | AT19: =AI19 -> 0
B20: 18 | C20: CC-403 | E20: Sistema de impulsion refino | F20: =LEFT(K20,4) -> 3631 | K20: 3631-RA-710-H3-0958-N | L20: 958 | N20: 28" | O20: 710 | P20: H3 | R20: RA | S20: N | AD20: 255000 | AE20: =AD20/1000 -> 255 | AN20: =+AP20-AL20 -> 0 | AP20: =+CONCATENATE(AF20*$AF$4+AG20*$AG$4+AH20*$AH$4+AI20*$AI$4) -> 0 | AQ20: =AP20 -> 0 | AS20: =AH20 -> 0 | AT20: =AI20 -> 0
B21: 19 | C21: CC-403 | E21: Sistema de impulsion refino | F21: =LEFT(K21,4) -> 3631 | G21: 4600027788-03631-201CA-00002 | H21: 0 | I21: 4600027788-03631-201CA-00002 | K21: 3631-RA-900-H3-0958-N | L21: 958 | N21: 36" | O21: 900 | P21: H3 | R21: RA | S21: N | T21: Brida Ciega | U21: Brida Ciega | V21: 1134 | W21: 1586 | X21: 25 | Y21: Nota (2) | Z21: 20° | AA21: Agua | AB21: Nota (4) | AC21: 5056 | AD21: 3950000 | AE21: =AD21/1000 -> 3950 | AN21: =+AP21-AL21 -> 0 | AP21: =+CONCATENATE(AF21*$AF$4+AG21*$AG$4+AH21*$AH$4+AI21*$AI$4) -> 0 | AQ21: =AP21 -> 0 | AS21: =AH21 -> 0 | AT21: =AI21 -> 0
B22: 20 | C22: CC-403 | E22: Sistema de impulsion refino | F22: =LEFT(K22,4) -> 3631 | G22: 4600027788-03631-201CA-00002 | H22: 0 | K22: 3631-RA-315-H3-0959-N | L22: 959 | N22: 12" | O22: 315 | P22: H3 | R22: RA | S22: N | T22: 3631-RA-900-H3-0958-N Nota (4) | U22: Sistema de Riego (Fuera del alcance del Proyecto) | V22: 1134 | W22: 1586 | X22: 25 | Y22: Nota (2) | Z22: 20° | AA22: Agua | AC22: 111 | AD22: 111950 | AE22: =AD22/1000 -> 111.95 | AN22: =+AP22-AL22 -> 0 | AP22: =+CONCATENATE(AF22*$AF$4+AG22*$AG$4+AH22*$AH$4+AI22*$AI$4) -> 0 | AQ22: =AP22 -> 0 | AS22: =AH22 -> 0 | AT22: =AI22 -> 0
B23: 21 | C23: CC-403 | E23: Sistema de impulsion refino | F23: =LEFT(K23,4) -> 3631 | G23: 4600027788-03631-201CA-00002 | H23: 0 | K23: 3631-RA-315-H3-0905-N | L23: 905 | N23: 12" | O23: 315 | P23: H3 | R23: RA | S23: N | T23: 3631-RA-710-H3-0958-N Nota (4) | U23: Sistema de Riego (Fuera del alcance del Proyecto) | V23: 1134 | W23: 1586 | X23: 25 | Y23: Nota (2) | Z23: 20° | AA23: Agua | AC23: 192 | AD23: 192050 | AE23: =AD23/1000 -> 192.05 | AN23: =+AP23-AL23 -> 0 | AP23: =+CONCATENATE(AF23*$AF$4+AG23*$AG$4+AH23*$AH$4+AI23*$AI$4) -> 0 | AQ23: =AP23 -> 0 | AS23: =AH23 -> 0 | AT23: =AI23 -> 0
B24: 22 | C24: CC-403 | E24: Sistema de impulsion refino | F24: =LEFT(K24,4) -> 3631 | G24: 4600027788-03631-201CA-00002 | H24: 0 | K24: 3631-RA-315-H3-0906-N | L24: 906 | N24: 12" | O24: 315 | P24: H3 | R24: RA | S24: N | T24: 3631-RA-710-H3-0958-N Nota (4) | U24: Sistema de Riego (Fuera del alcance del Proyecto) | V24: 1134 | W24: 1586 | X24: 25 | Y24: Nota (2) | Z24: 20° | AA24: Agua | AC24: 274 | AD24: 274200 | AE24: =AD24/1000 -> 274.2 | AN24: =+AP24-AL24 -> 0 | AP24: =+CONCATENATE(AF24*$AF$4+AG24*$AG$4+AH24*$AH$4+AI24*$AI$4) -> 0 | AQ24: =AP24 -> 0 | AS24: =AH24 -> 0 | AT24: =AI24 -> 0
B25: 23 | C25: CC-403 | E25: Sistema de impulsion refino | F25: =LEFT(K25,4) -> 3631 | G25: 4600027788-03631-201CA-00002 | H25: 0 | K25: 3631-RA-315-H3-0907-N | L25: 907 | N25: 12" | O25: 315 | P25: H3 | R25: RA | S25: N | T25: 3631-RA-710-H3-0958-N Nota (4) | U25: Sistema de Riego (Fuera del alcance del Proyecto) | V25: 1134 | W25: 1586 | X25: 25 | Y25: Nota (2) | Z25: 20° | AA25: Agua | AC25: 358 | AD25: 361650 | AE25: =AD25/1000 -> 361.65 | AN25: =+AP25-AL25 -> 0 | AP25: =+CONCATENATE(AF25*$AF$4+AG25*$AG$4+AH25*$AH$4+AI25*$AI$4) -> 0 | AQ25: =AP25 -> 0 | AS25: =AH25 -> 0 | AT25: =AI25 -> 0
B26: 24 | C26: CC-403 | E26: Sistema de impulsion refino | F26: =LEFT(K26,4) -> 3631 | G26: 4600027788-03631-201CA-00002 | H26: 0 | K26: 3631-RA-315-H3-0908-N | L26: 908 | N26: 12" | O26: 315 | P26: H3 | R26: RA | S26: N | T26: 3631-RA-630-H3-0958-N Nota (4) | U26: Sistema de Riego (Fuera del alcance del Proyecto) | V26: 1134 | W26: 1586 | X26: 25 | Y26: Nota (2) | Z26: 20° | AA26: Agua | AC26: 440 | AD26: 445100 | AE26: =AD26/1000 -> 445.1 | AN26: =+AP26-AL26 -> 0 | AP26: =+CONCATENATE(AF26*$AF$4+AG26*$AG$4+AH26*$AH$4+AI26*$AI$4) -> 0 | AQ26: =AP26 -> 0 | AS26: =AH26 -> 0 | AT26: =AI26 -> 0
B27: 25 | C27: CC-403 | E27: Sistema de impulsion refino | F27: =LEFT(K27,4) -> 3631 | G27: 4600027788-03631-201CA-00002 | H27: 0 | K27: 3631-RA-315-H3-0909-N | L27: 909 | N27: 12" | O27: 315 | P27: H3 | R27: RA | S27: N | T27: 3631-RA-630-H3-0958-N Nota (4) | U27: Sistema de Riego (Fuera del alcance del Proyecto) | V27: 1134 | W27: 1586 | X27: 25 | Y27: Nota (2) | Z27: 20° | AA27: Agua | AC27: 525 | AD27: 528850 | AE27: =AD27/1000 -> 528.85 | AN27: =+AP27-AL27 -> 0 | AP27: =+CONCATENATE(AF27*$AF$4+AG27*$AG$4+AH27*$AH$4+AI27*$AI$4) -> 0 | AQ27: =AP27 -> 0 | AS27: =AH27 -> 0 | AT27: =AI27 -> 0
B28: 26 | C28: CC-403 | E28: Sistema de impulsion refino | F28: =LEFT(K28,4) -> 3631 | G28: 4600027788-03631-201CA-00002 | H28: 0 | K28: 3631-RA-315-H3-0910-N | L28: 910 | N28: 12" | O28: 315 | P28: H3 | R28: RA | S28: N | T28: 3631-RA-630-H3-0958-N Nota (4) | U28: Sistema de Riego (Fuera del alcance del Proyecto) | V28: 1134 | W28: 1586 | X28: 25 | Y28: Nota (2) | Z28: 20° | AA28: Agua | AC28: 611 | AD28: 612550 | AE28: =AD28/1000 -> 612.55 | AN28: =+AP28-AL28 -> 0 | AP28: =+CONCATENATE(AF28*$AF$4+AG28*$AG$4+AH28*$AH$4+AI28*$AI$4) -> 0 | AQ28: =AP28 -> 0 | AS28: =AH28 -> 0 | AT28: =AI28 -> 0
B29: 27 | C29: CC-403 | E29: Sistema de impulsion refino | F29: =LEFT(K29,4) -> 3631 | G29: 4600027788-03631-201CA-00002 | H29: 0 | K29: 3631-RA-315-H3-0911-N | L29: 911 | N29: 12" | O29: 315 | P29: H3 | R29: RA | S29: N | T29: 3631-RA-500-H3-0958-N Nota (4) | U29: Sistema de Riego (Fuerda del alcance del Proyecto) | V29: 1134 | W29: 1586 | X29: 25 | Y29: Nota (2) | Z29: 20° | AA29: Agua | AC29: 637 | AD29: 697100 | AE29: =AD29/1000 -> 697.1 | AN29: =+AP29-AL29 -> 0 | AP29: =+CONCATENATE(AF29*$AF$4+AG29*$AG$4+AH29*$AH$4+AI29*$AI$4) -> 0 | AQ29: =AP29 -> 0 | AS29: =AH29 -> 0 | AT29: =AI29 -> 0
B30: 28 | C30: CC-403 | E30: Sistema de impulsion refino | F30: =LEFT(K30,4) -> 3631 | G30: 4600027788-03631-201CA-00002 | H30: 0 | K30: 3631-RA-315-H3-0912-N | L30: 912 | N30: 12" | O30: 315 | P30: H3 | R30: RA | S30: N | T30: 3631-RA-500-H3-0958-N Nota (4) | U30: Sistema de Riego (Fuera del alcance del Proyecto) | V30: 1134 | W30: 1586 | X30: 25 | Y30: Nota (2) | Z30: 20° | AA30: Agua | AC30: 507 | AD30: 674150 | AE30: =AD30/1000 -> 674.15 | AN30: =+AP30-AL30 -> 0 | AP30: =+CONCATENATE(AF30*$AF$4+AG30*$AG$4+AH30*$AH$4+AI30*$AI$4) -> 0 | AQ30: =AP30 -> 0 | AS30: =AH30 -> 0 | AT30: =AI30 -> 0
B31: 29 | C31: CC-403 | E31: Lixiviacion piscina emergencia | F31: =LEFT(K31,4) -> 3632 | I31: 4600027788-03632-502CA-00001 | J31: 0 | K31: 3632-RA-14"-T2-0931-N | L31: 931 | M31: 1 | N31: 14" | O31: 355 | P31: T2 | R31: RA | S31: N | AD31: 1275 | AE31: =AD31/1000 -> 1.275 | AN31: =+AP31-AL31 -> 0 | AP31: =+CONCATENATE(AF31*$AF$4+AG31*$AG$4+AH31*$AH$4+AI31*$AI$4) -> 0 | AQ31: =AP31 -> 0 | AS31: =AH31 -> 0 | AT31: =AI31 -> 0
B32: 30 | C32: CC-403 | E32: Lixiviacion piscina emergencia | F32: =LEFT(K32,4) -> 3632 | I32: 4600027788-03632-502CA-00003 | J32: 0 | K32: 3632-RA-14"-T2-0932-N | L32: 932 | M32: 1 | N32: 14" | O32: 355 | P32: T2 | R32: RA | S32: N | AD32: 1275 | AE32: =AD32/1000 -> 1.275 | AN32: =+AP32-AL32 -> 0 | AP32: =+CONCATENATE(AF32*$AF$4+AG32*$AG$4+AH32*$AH$4+AI32*$AI$4) -> 0 | AQ32: =AP32 -> 0 | AS32: =AH32 -> 0 | AT32: =AI32 -> 0
B33: 31 | C33: CC-403 | E33: Lixiviacion piscina emergencia | F33: =LEFT(K33,4) -> 3632 | I33: 4600027788-03632-102CA-00002/00004/00005 | J33: 0 | K33: 3632-RA-355-H4-0933-N | L33: 933 | N33: 14" | O33: 355 | P33: H4 | AD33: 350000 | AE33: =AD33/1000 -> 350 | AN33: =+AP33-AL33 -> 0 | AP33: =+CONCATENATE(AF33*$AF$4+AG33*$AG$4+AH33*$AH$4+AI33*$AI$4) -> 0 | AQ33: =AP33 -> 0 | AS33: =AH33 -> 0 | AT33: =AI33 -> 0
B34: 32 | C34: CC-403 | E34: Lixiviacion piscina emergencia | F34: =LEFT(K34,4) -> 3632 | I34: 4600027788-03632-502CA-00002 | J34: 0 | K34: 3632-RA-355-H4-0933-N | L34: 933 | M34: 1 | N34: 14" | O34: 355 | P34: H4 | R34: RA | S34: N | AD34: 2658 | AE34: =AD34/1000 -> 2.658 | AN34: =+AP34-AL34 -> 0 | AP34: =+CONCATENATE(AF34*$AF$4+AG34*$AG$4+AH34*$AH$4+AI34*$AI$4) -> 0 | AQ34: =AP34 -> 0 | AS34: =AH34 -> 0 | AT34: =AI34 -> 0
B35: 33 | C35: CC-403 | E35: Lixiviacion piscina emergencia | F35: =LEFT(K35,4) -> 3632 | I35: 4600027788-03632-502CA-00004 | J35: 0 | K35: 3632-RA-355-H4-0933-N | L35: 933 | M35: 2 | N35: 14" | O35: 355 | P35: H4 | R35: RA | S35: N | AD35: 2658 | AE35: =AD35/1000 -> 2.658 | AN35: =+AP35-AL35 -> 0 | AP35: =+CONCATENATE(AF35*$AF$4+AG35*$AG$4+AH35*$AH$4+AI35*$AI$4) -> 0 | AQ35: =AP35 -> 0 | AS35: =AH35 -> 0 | AT35: =AI35 -> 0
B36: 34 | C36: CC-403 | E36: Lixiviacion piscina emergencia | F36: =LEFT(K36,4) -> 3632 | I36: 4600027788-03632-502CA-00005 | J36: 0 | K36: 3632-RA-355-H4-0933-N | L36: 933 | M36: 3 | N36: 14" | O36: 355 | P36: H4 | R36: RA | S36: N | AD36: 3758 | AE36: =AD36/1000 -> 3.758 | AN36: =+AP36-AL36 -> 0 | AP36: =+CONCATENATE(AF36*$AF$4+AG36*$AG$4+AH36*$AH$4+AI36*$AI$4) -> 0 | AQ36: =AP36 -> 0 | AS36: =AH36 -> 0 | AT36: =AI36 -> 0
B37: 35 | C37: CC-403 | E37: Lixiviacion piscina emergencia | F37: =LEFT(K37,4) -> 3632 | I37: 4600027788-03632-502CA-00006 | J37: 0 | K37: 3632-RA-355-H4-0933-N | L37: 933 | M37: 4 | N37: 14" | O37: 355 | P37: H4 | R37: RA | S37: N | AD37: 6500 | AE37: =AD37/1000 -> 6.5 | AN37: =+AP37-AL37 -> 0 | AP37: =+CONCATENATE(AF37*$AF$4+AG37*$AG$4+AH37*$AH$4+AI37*$AI$4) -> 0 | AQ37: =AP37 -> 0 | AS37: =AH37 -> 0 | AT37: =AI37 -> 0
B38: 36 | C38: CC-403 | E38: Lixiviacion piscina emergencia | F38: =LEFT(K38,4) -> 3632 | I38: 4600027788-03632-502CA-00007 | J38: 0 | K38: 3632-RA-355-H4-0933-N | L38: 933 | M38: 5 | N38: 14" | O38: 355 | P38: H4 | R38: RA | S38: N | AD38: 1795 | AE38: =AD38/1000 -> 1.795 | AN38: =+AP38-AL38 -> 0 | AP38: =+CONCATENATE(AF38*$AF$4+AG38*$AG$4+AH38*$AH$4+AI38*$AI$4) -> 0 | AQ38: =AP38 -> 0 | AS38: =AH38 -> 0 | AT38: =AI38 -> 0
B39: 37 | C39: CC-403 | E39: Lixiviacion piscina emergencia | F39: =LEFT(K39,4) -> 3632 | I39: 4600027788-03632-502CA-00008 | J39: 0 | K39: 3632-RA-355-H4-0935-N | L39: 935 | M39: 1 | N39: 14" | O39: 355 | P39: H4 | R39: RA | S39: N | AD39: 8058 | AE39: =AD39/1000 -> 8.058 | AN39: =+AP39-AL39 -> 0 | AP39: =+CONCATENATE(AF39*$AF$4+AG39*$AG$4+AH39*$AH$4+AI39*$AI$4) -> 0 | AQ39: =AP39 -> 0 | AS39: =AH39 -> 0 | AT39: =AI39 -> 0
B40: 38 | C40: CC-403 | E40: Lixiviacion piscina emergencia | F40: =LEFT(K40,4) -> 3632 | I40: 4600027788-03632-300CA-00003 | K40: 3632-RA-800-H4-0938-N | L40: 938 | N40: 32" | O40: 800 | P40: H4 | R40: RA | S40: N | AD40: 15375 | AE40: =AD40/1000 -> 15.375 | AN40: =+AP40-AL40 -> 0 | AP40: =+CONCATENATE(AF40*$AF$4+AG40*$AG$4+AH40*$AH$4+AI40*$AI$4) -> 0 | AQ40: =AP40 -> 0 | AS40: =AH40 -> 0 | AT40: =AI40 -> 0
B41: 39 | C41: CC-403 | E41: Lixiviacion piscina emergencia | F41: =LEFT(K41,4) -> 3632 | I41: 4600027788-03632-201CI-00008 | K41: 3632-RA-900-H4-0939-N | L41: 939 | N41: 36" | O41: 900 | P41: H4 | R41: RA | S41: N | AD41: 300000 | AE41: =AD41/1000 -> 300 | AN41: =+AP41-AL41 -> 0 | AP41: =+CONCATENATE(AF41*$AF$4+AG41*$AG$4+AH41*$AH$4+AI41*$AI$4) -> 0 | AQ41: =AP41 -> 0 | AS41: =AH41 -> 0 | AT41: =AI41 -> 0
B42: 40 | C42: CC-403 | E42: Lixiviacion piscina emergencia | F42: =LEFT(K42,4) -> 3632 | I42: 4600027788-03632-300CA-00003 | K42: 3632-RA-800-H4-0939-N | L42: 939 | N42: 32" | O42: 800 | P42: H4 | R42: RA | S42: N | AD42: 14160 | AE42: =AD42/1000 -> 14.16 | AN42: =+AP42-AL42 -> 0 | AP42: =+CONCATENATE(AF42*$AF$4+AG42*$AG$4+AH42*$AH$4+AI42*$AI$4) -> 0 | AQ42: =AP42 -> 0 | AS42: =AH42 -> 0 | AT42: =AI42 -> 0
B43: 41 | C43: CC-403 | E43: Red de Incendio | F43: =LEFT(K43,4) -> 6340 | G43: 4600027788-06340-201CA-00001 | K43: 6340-FP-200-H1-0960-N | L43: 960 | N43: 8" | O43: 200 | P43: H1 | Q43: CAÑERÍA, HDPE PE100 PN20 - ISO 4427 -2, EXTREMOS PARA TERMOFUSIÓN | R43: FP | S43: N | T43: Línea 500mm diámetro (Existente) | U43: Línea 6340-FP-200-H6-0961-N | W43: 190 | AE43: =AD43/1000 -> 0 | AN43: =+AP43-AL43 -> 0 | AP43: =+CONCATENATE(AF43*$AF$4+AG43*$AG$4+AH43*$AH$4+AI43*$AI$4) -> 0 | AQ43: =AP43 -> 0 | AS43: =AH43 -> 0 | AT43: =AI43 -> 0
B44: 42 | C44: CC-403 | E44: Red de Incendio | F44: =LEFT(K44,4) -> 6340 | G44: 4600027788-06340-201CA-00001 | K44: 6340-FP-200-H6-0961-N | L44: 961 | N44: 8" | O44: 200 | P44: H6 | Q44: CAÑERÍA, HDPE PE100 PN10 - ISO 4427 -2, EXTREMOS PARA TERMOFUSIÓN | R44: FP | S44: N | T44: Línea 6340-FP-200-H1-0960-N | U44: Línea 6340-FP-8"-C2-0969-N | W44: 102 | AE44: =AD44/1000 -> 0 | AN44: =+AP44-AL44 -> 0 | AP44: =+CONCATENATE(AF44*$AF$4+AG44*$AG$4+AH44*$AH$4+AI44*$AI$4) -> 0 | AQ44: =AP44 -> 0 | AS44: =AH44 -> 0 | AT44: =AI44 -> 0
B45: 43 | C45: CC-403 | E45: Red de Incendio | F45: =LEFT(K45,4) -> 6340 | G45: 4600027788-06340-201CA-00001 | I45: 4600027788-06340-502CA-00002 | J45: 0 | K45: 6340-FP-10"-C2-0962-HC | L45: 962 | M45: 1 | N45: 10" | O45: 250 | P45: C2 | Q45: CAÑERÍA, ACERO CARBONO, ASTM A53-B Gr B, SCH STD, EWR, TIPO E, EXTREMOS RANURADOS, ASME B36.10 | R45: FP | S45: HC | T45: Descarga TK 6340-EST-001 | U45: Succión manifold estación bombeo | W45: 11 | AC45: Pendiente | AD45: 3330 | AE45: =AD45/1000 -> 3.33 | AN45: =+AP45-AL45 -> 0 | AP45: =+CONCATENATE(AF45*$AF$4+AG45*$AG$4+AH45*$AH$4+AI45*$AI$4) -> 0 | AQ45: =AP45 -> 0 | AS45: =AH45 -> 0 | AT45: =AI45 -> 0
B46: 44 | C46: CC-403 | E46: Red de Incendio | F46: =LEFT(K46,4) -> 6340 | G46: 4600027788-06340-201CA-00001 | I46: 4600027788-06340-502CA-00003 | J46: 1 | K46: 6340-FP-14"-C3-0963-HC | L46: 963 | M46: 1 | N46: 14" | O46: 355 | P46: C3 | Q46: CAÑERÍA DE ACERO CARBONO, ASTM A53 GR. B ERW, SCH 40, EXTREMOS RANURADOS, ASME B36.10M | R46: FP | S46: HC | T46: Línea 6340-FP-10"-C3-1514-N | U46: Línea 6340-FP-14"-C5-0964-N | W46: 208 | AC46: Pendiente | AD46: 2877 | AE46: =AD46/1000 -> 2.877 | AN46: =+AP46-AL46 -> 0 | AP46: =+CONCATENATE(AF46*$AF$4+AG46*$AG$4+AH46*$AH$4+AI46*$AI$4) -> 0 | AQ46: =AP46 -> 0 | AS46: =AH46 -> 0 | AT46: =AI46 -> 0
B47: 45 | C47: CC-403 | E47: Red de Incendio | F47: =LEFT(K47,4) -> 6340 | G47: 4600027788-06340-201CA-00001 | K47: 6340-FP-14"-C5-0964-N | L47: 964 | N47: 14" | O47: 355 | P47: C5 | Q47: CAÑERÍA, ACERO CARBONO, ASTM A53-B Gr B, SCH STD, EWR, TIPO E, EXTREMOS BISELADO, ASME B36.10 | R47: FP | S47: N | T47: Línea 6340-FP-10"-C3-0963-N | U47: Línea 6340-FP-14”-C5-0965-N | W47: 219 | AE47: =AD47/1000 -> 0 | AN47: =+AP47-AL47 -> 0 | AP47: =+CONCATENATE(AF47*$AF$4+AG47*$AG$4+AH47*$AH$4+AI47*$AI$4) -> 0 | AQ47: =AP47 -> 0 | AS47: =AH47 -> 0 | AT47: =AI47 -> 0
B48: 46 | C48: CC-403 | E48: Red de Incendio | F48: =LEFT(K48,4) -> 6340 | G48: 4600027788-06340-201CA-00002 | K48: 6340-FP-12"-C5-0965-N | L48: 965 | N48: 12" | O48: 315 | P48: C5 | Q48: CAÑERÍA, ACERO CARBONO, ASTM A53-B Gr B, SCH STD, EWR, TIPO E, EXTREMOS BISELADO, ASME B36.10 | R48: FP | S48: N | T48: Línea 6340-FP-14"-C5-0964-N | U48: Línea 6340-FP-12"-C3-0966-HC | W48: 219 | AE48: =AD48/1000 -> 0 | AN48: =+AP48-AL48 -> 0 | AP48: =+CONCATENATE(AF48*$AF$4+AG48*$AG$4+AH48*$AH$4+AI48*$AI$4) -> 0 | AQ48: =AP48 -> 0 | AS48: =AH48 -> 0 | AT48: =AI48 -> 0
B49: 47 | C49: CC-403 | E49: Red de Incendio | F49: =LEFT(K49,4) -> 6340 | G49: 4600027788-06340-201CA-00002 | I49: 4600027788-06340-502CA-00079 | J49: 0 | K49: 6340-FP-12"-C3-0966-HC | L49: 966 | M49: 1 | N49: 12" | O49: 315 | P49: C3 | Q49: CAÑERÍA DE ACERO CARBONO, ASTM A53 GR. B ERW, SCH 40, EXTREMOS RANURADOS, ASME B36.10M | R49: FP | S49: HC | T49: Línea 6340-FP-14”-C5-0965-N | U49: Protección Cola Correa 220-CV-205 | W49: 170 | AD49: 9315 | AE49: =AD49/1000 -> 9.315 | AN49: =+AP49-AL49 -> 0 | AP49: =+CONCATENATE(AF49*$AF$4+AG49*$AG$4+AH49*$AH$4+AI49*$AI$4) -> 0 | AQ49: =AP49 -> 0 | AS49: =AH49 -> 0 | AT49: =AI49 -> 0
B50: 48 | C50: CC-403 | E50: Red de Incendio | F50: =LEFT(K50,4) -> 6340 | G50: 4600027788-06340-201CA-00002 | I50: 4600027788-06340-502CA-00079 | J50: 0 | K50: 6340-FP-12"-C3-0966-HC | L50: 966 | M50: 2 | N50: 12" | O50: 315 | P50: C3 | Q50: CAÑERÍA DE ACERO CARBONO, ASTM A53 GR. B ERW, SCH 40, EXTREMOS RANURADOS, ASME B36.10M | R50: FP | S50: HC | AD50: 25391 | AE50: =AD50/1000 -> 25.391 | AN50: =+AP50-AL50 -> 0 | AP50: =+CONCATENATE(AF50*$AF$4+AG50*$AG$4+AH50*$AH$4+AI50*$AI$4) -> 0 | AQ50: =AP50 -> 0 | AS50: =AH50 -> 0 | AT50: =AI50 -> 0
B51: 49 | C51: CC-403 | E51: Red de Incendio | F51: =LEFT(K51,4) -> 6340 | G51: 4600027788-06340-201CA-00002 | I51: 4600027788-06340-502CA-00079 | K51: 6340-FP-12"-C3-0966-HC | L51: 966 | M51: 3 | N51: 12" | O51: 315 | P51: C3 | Q51: CAÑERÍA DE ACERO CARBONO, ASTM A53 GR. B ERW, SCH 40, EXTREMOS RANURADOS, ASME B36.10M | R51: FP | S51: HC | AE51: =AD51/1000 -> 0 | AN51: =+AP51-AL51 -> 0 | AP51: =+CONCATENATE(AF51*$AF$4+AG51*$AG$4+AH51*$AH$4+AI51*$AI$4) -> 0 | AQ51: =AP51 -> 0 | AS51: =AH51 -> 0 | AT51: =AI51 -> 0
B52: 50 | C52: CC-403 | E52: Red de Incendio | F52: =LEFT(K52,4) -> 6340 | G52: 4600027788-06340-201CA-00004 | K52: 6340-FP-4"-C5-0967-N | L52: 967 | N52: 4" | O52: 110 | P52: C5 | Q52: CAÑERÍA, ACERO CARBONO, ASTM A53-B Gr B, SCH STD, EWR, TIPO E, EXTREMOS BISELADO, ASME B36.10 | R52: FP | S52: N | T52: Línea 6340-FP-12"-C5-0965-N | U52: Línea 6340-FP-3"-C3-0976-HC | W52: 207 | AE52: =AD52/1000 -> 0 | AN52: =+AP52-AL52 -> 0 | AP52: =+CONCATENATE(AF52*$AF$4+AG52*$AG$4+AH52*$AH$4+AI52*$AI$4) -> 0 | AQ52: =AP52 -> 0 | AS52: =AH52 -> 0 | AT52: =AI52 -> 0
B53: 51 | C53: CC-403 | E53: Red de Incendio | F53: =LEFT(K53,4) -> 6340 | G53: 4600027788-06340-201CA-00004 | I53: 4600027788-06340-502CA-00034 | J53: 0 | K53: 6340-FP-3"-C3-0968-N | L53: 968 | M53: 1 | N53: 3" | O53: 90 | P53: C3 | Q53: CAÑERÍA DE ACERO CARBONO, ASTM A53 GR. B ERW, SCH 40, EXTREMOS RANURADOS, ASME B36.10M | R53: FP | S53: N | AC53: Pendiente | AD53: 4456 | AE53: =AD53/1000 -> 4.456 | AN53: =+AP53-AL53 -> 0 | AP53: =+CONCATENATE(AF53*$AF$4+AG53*$AG$4+AH53*$AH$4+AI53*$AI$4) -> 0 | AQ53: =AP53 -> 0 | AS53: =AH53 -> 0 | AT53: =AI53 -> 0
B54: 52 | C54: CC-403 | E54: Red de Incendio | F54: =LEFT(K54,4) -> 6340 | G54: 4600027788-06340-201CA-00004 | I54: 4600027788-06340-502CA-00034 | J54: 0 | K54: 6340-FP-3"-C3-0968-N | L54: 968 | M54: 2 | N54: 3" | O54: 90 | P54: C3 | Q54: CAÑERÍA DE ACERO CARBONO, ASTM A53 GR. B ERW, SCH 40, EXTREMOS RANURADOS, ASME B36.10M | R54: FP | S54: N | T54: Línea 6340-FP-4"-C3-0967-N | U54: Protección Sistema Motriz Cabeza 220-CV-205 | W54: 30 | AC54: Pendiente | AD54: 10038 | AE54: =AD54/1000 -> 10.038 | AN54: =+AP54-AL54 -> 0 | AP54: =+CONCATENATE(AF54*$AF$4+AG54*$AG$4+AH54*$AH$4+AI54*$AI$4) -> 0 | AQ54: =AP54 -> 0 | AS54: =AH54 -> 0 | AT54: =AI54 -> 0
B55: 53 | C55: CC-403 | E55: Red de Incendio | F55: =LEFT(K55,4) -> 6340 | I55: 4600027788-06340-502CA-00031 | J55: 0 | K55: 6340-FP-3"-C3-0968-HC | L55: 968 | M55: 1 | N55: 3" | O55: 90 | P55: C3 | Q55: CAÑERÍA DE ACERO CARBONO, ASTM A53 GR. B ERW, SCH 40, EXTREMOS RANURADOS, ASME B36.10M | R55: FP | S55: HC | AC55: Pendiente | AD55: 2997 | AE55: =AD55/1000 -> 2.997 | AN55: =+AP55-AL55 -> 0 | AP55: =+CONCATENATE(AF55*$AF$4+AG55*$AG$4+AH55*$AH$4+AI55*$AI$4) -> 0 | AQ55: =AP55 -> 0 | AS55: =AH55 -> 0 | AT55: =AI55 -> 0
B56: 54 | C56: CC-403 | E56: Red de Incendio | F56: =LEFT(K56,4) -> 6340 | G56: 4600027788-06340-201CA-00001 | K56: 6340-FP-8"-C2-0969-N | L56: 969 | N56: 8" | O56: 200 | P56: C2 | R56: FP | S56: N | T56: Línea 6340-FP-200-H6-0961-N | U56: Línea 6340-FP-8"-H6-0970-N | W56: 102 | AE56: =AD56/1000 -> 0 | AN56: =+AP56-AL56 -> 0 | AP56: =+CONCATENATE(AF56*$AF$4+AG56*$AG$4+AH56*$AH$4+AI56*$AI$4) -> 0 | AQ56: =AP56 -> 0 | AS56: =AH56 -> 0 | AT56: =AI56 -> 0
B57: 55 | C57: CC-403 | E57: Red de Incendio | F57: =LEFT(K57,4) -> 6340 | G57: 4600027788-06340-201CA-00001 | K57: 6340-FP-8"-H6-0970-N | L57: 970 | N57: 8" | O57: 200 | P57: H6 | Q57: CAÑERÍA, HDPE PE100 PN10 - ISO 4427 -2, EXTREMOS PARA TERMOFUSIÓN | R57: FP | S57: N | T57: Línea 6340-FP-8"-C2-0969-N | U57: Línea 6340-FP-8"-C2-0971-N | W57: 102 | AE57: =AD57/1000 -> 0 | AN57: =+AP57-AL57 -> 0 | AP57: =+CONCATENATE(AF57*$AF$4+AG57*$AG$4+AH57*$AH$4+AI57*$AI$4) -> 0 | AQ57: =AP57 -> 0 | AS57: =AH57 -> 0 | AT57: =AI57 -> 0
B58: 56 | C58: CC-403 | E58: Red de Incendio | F58: =LEFT(K58,4) -> 6340 | G58: 4600027788-06340-201CA-00001 | I58: 4600027788-06340-502CA-00010 | J58: 0 | K58: 6340-FP-6"-C2-0971-HC | L58: 971 | M58: 1 | N58: 6" | O58: 180 | P58: C2 | Q58: CAÑERÍA ACERO CARBONO, ASTM A53-B Gr B, SCH STD, EWR, TIPO E, EXTREMOS RANURADOS, ASME B36.10 | R58: FP | S58: HC | AD58: 1750 | AE58: =AD58/1000 -> 1.75 | AN58: =+AP58-AL58 -> 0 | AP58: =+CONCATENATE(AF58*$AF$4+AG58*$AG$4+AH58*$AH$4+AI58*$AI$4) -> 0 | AQ58: =AP58 -> 0 | AS58: =AH58 -> 0 | AT58: =AI58 -> 0
B59: 57 | C59: CC-403 | E59: Red de Incendio | F59: =LEFT(K59,4) -> 6340 | G59: 4600027788-06340-201CA-00001 | I59: 4600027788-06340-502CA-00010 | J59: 0 | K59: 6340-FP-6"-C2-0971-HC | L59: 971 | M59: 2 | N59: 6" | O59: 180 | P59: C2 | Q59: CAÑERÍA ACERO CARBONO, ASTM A53-B Gr B, SCH STD, EWR, TIPO E, EXTREMOS RANURADOS, ASME B36.10 | R59: FP | S59: HC | AD59: 2163 | AE59: =AD59/1000 -> 2.163 | AN59: =+AP59-AL59 -> 0 | AP59: =+CONCATENATE(AF59*$AF$4+AG59*$AG$4+AH59*$AH$4+AI59*$AI$4) -> 0 | AQ59: =AP59 -> 0 | AS59: =AH59 -> 0 | AT59: =AI59 -> 0
B60: 58 | C60: CC-403 | E60: Red de Incendio | F60: =LEFT(K60,4) -> 6340 | G60: 4600027788-06340-201CA-00001 | I60: 4600027788-06340-502CA-00010 | J60: 0 | K60: 6340-FP-6"-C2-0971-HC | L60: 971 | M60: 3 | N60: 6" | O60: 180 | P60: C2 | Q60: CAÑERÍA ACERO CARBONO, ASTM A53-B Gr B, SCH STD, EWR, TIPO E, EXTREMOS RANURADOS, ASME B36.10 | R60: FP | S60: HC | AD60: 5890 | AE60: =AD60/1000 -> 5.89 | AN60: =+AP60-AL60 -> 0 | AP60: =+CONCATENATE(AF60*$AF$4+AG60*$AG$4+AH60*$AH$4+AI60*$AI$4) -> 0 | AQ60: =AP60 -> 0 | AS60: =AH60 -> 0 | AT60: =AI60 -> 0
B61: 59 | C61: CC-403 | E61: Red de Incendio | F61: =LEFT(K61,4) -> 6340 | G61: 4600027788-06340-201CA-00001 | I61: 4600027788-06340-502CA-00010 | J61: 0 | K61: 6340-FP-6"-C2-0971-HC | L61: 971 | M61: 4 | N61: 6" | O61: 180 | P61: C2 | Q61: CAÑERÍA ACERO CARBONO, ASTM A53-B Gr B, SCH STD, EWR, TIPO E, EXTREMOS RANURADOS, ASME B36.10 | R61: FP | S61: HC | T61: Línea 6340-FP-8"-H6-0970-N | U61: Estanque Red de Incendio 6340- EST-001 | W61: 102 | AC61: Pendiente | AD61: 13139 | AE61: =AD61/1000 -> 13.139 | AN61: =+AP61-AL61 -> 0 | AP61: =+CONCATENATE(AF61*$AF$4+AG61*$AG$4+AH61*$AH$4+AI61*$AI$4) -> 0 | AQ61: =AP61 -> 0 | AS61: =AH61 -> 0 | AT61: =AI61 -> 0
B62: 60 | C62: CC-403 | E62: Red de Incendio | F62: =LEFT(K62,4) -> 6340 | G62: 4600027788-06340-201CA-00004 | K62: 6340-FP-4"-C5-0972-N | L62: 972 | N62: 4" | O62: 110 | P62: C5 | Q62: CAÑERÍA, ACERO CARBONO, ASTM A53-B Gr B, SCH STD, EWR, TIPO E, EXTREMOS BISELADO, ASME B36.10 | R62: FP | S62: N | T62: Línea 6340-FP-12"-C5-0965-N | U62: Línea 6340-FP-3"-C3-0974-HC | W62: 206 | AE62: =AD62/1000 -> 0 | AN62: =+AP62-AL62 -> 0 | AP62: =+CONCATENATE(AF62*$AF$4+AG62*$AG$4+AH62*$AH$4+AI62*$AI$4) -> 0 | AQ62: =AP62 -> 0 | AS62: =AH62 -> 0 | AT62: =AI62 -> 0
B63: 61 | C63: CC-403 | E63: Red de Incendio | F63: =LEFT(K63,4) -> 6340 | G63: 4600027788-06340-201CA-00004 | I63: 4600027788-06340-502CA-00039 | J63: 0 | K63: 6340-FP-3"-C3-0973-N | L63: 973 | M63: 1 | N63: 3" | O63: 90 | P63: C3 | Q63: CAÑERÍA DE ACERO CARBONO, ASTM A53 GR. B ERW, SCH 40, EXTREMOS RANURADOS, ASME B36.10M | R63: FP | S63: N | AC63: Pendiente | AD63: 3919 | AE63: =AD63/1000 -> 3.919 | AN63: =+AP63-AL63 -> 0 | AP63: =+CONCATENATE(AF63*$AF$4+AG63*$AG$4+AH63*$AH$4+AI63*$AI$4) -> 0 | AQ63: =AP63 -> 0 | AS63: =AH63 -> 0 | AT63: =AI63 -> 0
B64: 62 | C64: CC-403 | E64: Red de Incendio | F64: =LEFT(K64,4) -> 6340 | G64: 4600027788-06340-201CA-00004 | I64: 4600027788-06340-502CA-00039 | J64: 0 | K64: 6340-FP-3"-C3-0973-N | L64: 973 | M64: 2 | N64: 3" | O64: 90 | P64: C3 | Q64: CAÑERÍA DE ACERO CARBONO, ASTM A53 GR. B ERW, SCH 40, EXTREMOS RANURADOS, ASME B36.10M | R64: FP | S64: N | AC64: Pendiente | AD64: 8050 | AE64: =AD64/1000 -> 8.05 | AN64: =+AP64-AL64 -> 0 | AP64: =+CONCATENATE(AF64*$AF$4+AG64*$AG$4+AH64*$AH$4+AI64*$AI$4) -> 0 | AQ64: =AP64 -> 0 | AS64: =AH64 -> 0 | AT64: =AI64 -> 0
B65: 63 | C65: CC-403 | E65: Red de Incendio | F65: =LEFT(K65,4) -> 6340 | G65: 4600027788-06340-201CA-00004 | I65: 4600027788-06340-502CA-00040 | J65: 0 | K65: 6340-FP-3"-C3-0973-N | L65: 973 | M65: 1 | N65: 3" | O65: 90 | P65: C3 | Q65: CAÑERÍA DE ACERO CARBONO, ASTM A53 GR. B ERW, SCH 40, EXTREMOS RANURADOS, ASME B36.10M | R65: FP | S65: N | AD65: 4027 | AE65: =AD65/1000 -> 4.027 | AN65: =+AP65-AL65 -> 0 | AP65: =+CONCATENATE(AF65*$AF$4+AG65*$AG$4+AH65*$AH$4+AI65*$AI$4) -> 0 | AQ65: =AP65 -> 0 | AS65: =AH65 -> 0 | AT65: =AI65 -> 0
B66: 64 | C66: CC-403 | E66: Red de Incendio | F66: =LEFT(K66,4) -> 6340 | G66: 4600027788-06340-201CA-00004 | I66: 4600027788-06340-502CA-00040 | J66: 0 | K66: 6340-FP-3"-C3-0973-N | L66: 973 | M66: 2 | N66: 3" | O66: 90 | P66: C3 | Q66: CAÑERÍA DE ACERO CARBONO, ASTM A53 GR. B ERW, SCH 40, EXTREMOS RANURADOS, ASME B36.10M | R66: FP | S66: N | AD66: 6951 | AE66: =AD66/1000 -> 6.951 | AN66: =+AP66-AL66 -> 0 | AP66: =+CONCATENATE(AF66*$AF$4+AG66*$AG$4+AH66*$AH$4+AI66*$AI$4) -> 0 | AQ66: =AP66 -> 0 | AS66: =AH66 -> 0 | AT66: =AI66 -> 0
B67: 65 | C67: CC-403 | E67: Red de Incendio | F67: =LEFT(K67,4) -> 6340 | I67: 4600027788-06340-502CA-00029 | J67: 0 | K67: 6340-FP-3"-C3-0973-HC | L67: 973 | M67: 1 | N67: 3" | O67: 90 | P67: C3 | Q67: CAÑERÍA DE ACERO CARBONO, ASTM A53 GR. B ERW, SCH 40, EXTREMOS RANURADOS, ASME B36.10M | R67: FP | S67: HC | AC67: Pendiente | AD67: 2987 | AE67: =AD67/1000 -> 2.987 | AN67: =+AP67-AL67 -> 0 | AP67: =+CONCATENATE(AF67*$AF$4+AG67*$AG$4+AH67*$AH$4+AI67*$AI$4) -> 0 | AQ67: =AP67 -> 0 | AS67: =AH67 -> 0 | AT67: =AI67 -> 0
B68: 66 | C68: CC-403 | E68: Red de Incendio | F68: =LEFT(K68,4) -> 6340 | G68: 4600027788-06340-201CA-00004 | I68: 4600027788-06340-502CA-00035 | J68: 0 | K68: 6340-FP-3"-C3-0974-N | L68: 974 | M68: 1 | N68: 3" | O68: 90 | P68: C3 | Q68: CAÑERÍA DE ACERO CARBONO, ASTM A53 GR. B ERW, SCH 40, EXTREMOS RANURADOS, ASME B36.10M | R68: FP | S68: N | T68: Línea 6340-FP-4"-C3-0972-N | U68: Protección Correa 220-CV-205 | W68: 120 | AC68: Pendiente | AD68: 4469 | AE68: =AD68/1000 -> 4.469 | AN68: =+AP68-AL68 -> 0 | AP68: =+CONCATENATE(AF68*$AF$4+AG68*$AG$4+AH68*$AH$4+AI68*$AI$4) -> 0 | AQ68: =AP68 -> 0 | AS68: =AH68 -> 0 | AT68: =AI68 -> 0
B69: 67 | C69: CC-403 | E69: Red de Incendio | F69: =LEFT(K69,4) -> 6340 | G69: 4600027788-06340-201CA-00004 | I69: 4600027788-06340-502CA-00035 | J69: 0 | K69: 6340-FP-3"-C3-0974-N | L69: 974 | M69: 2 | N69: 3" | O69: 90 | P69: C3 | Q69: CAÑERÍA DE ACERO CARBONO, ASTM A53 GR. B ERW, SCH 40, EXTREMOS RANURADOS, ASME B36.10M | R69: FP | S69: N | AD69: 8047 | AE69: =AD69/1000 -> 8.047 | AN69: =+AP69-AL69 -> 0 | AP69: =+CONCATENATE(AF69*$AF$4+AG69*$AG$4+AH69*$AH$4+AI69*$AI$4) -> 0 | AQ69: =AP69 -> 0 | AS69: =AH69 -> 0 | AT69: =AI69 -> 0
B70: 68 | C70: CC-403 | E70: Red de Incendio | F70: =LEFT(K70,4) -> 6340 | G70: 4600027788-06340-201CA-00004 | I70: 4600027788-06340-502CA-00036 | J70: 0 | K70: 6340-FP-3"-C3-0974-N | L70: 974 | M70: 1 | N70: 3" | O70: 90 | P70: C3 | Q70: CAÑERÍA DE ACERO CARBONO, ASTM A53 GR. B ERW, SCH 40, EXTREMOS RANURADOS, ASME B36.10M | R70: FP | S70: N | AD70: 4027 | AE70: =AD70/1000 -> 4.027 | AN70: =+AP70-AL70 -> 0 | AP70: =+CONCATENATE(AF70*$AF$4+AG70*$AG$4+AH70*$AH$4+AI70*$AI$4) -> 0 | AQ70: =AP70 -> 0 | AS70: =AH70 -> 0 | AT70: =AI70 -> 0
B71: 69 | C71: CC-403 | E71: Red de Incendio | F71: =LEFT(K71,4) -> 6340 | G71: 4600027788-06340-201CA-00004 | I71: 4600027788-06340-502CA-00036 | J71: 0 | K71: 6340-FP-3"-C3-0974-N | L71: 974 | M71: 2 | N71: 3" | O71: 90 | P71: C3 | Q71: CAÑERÍA DE ACERO CARBONO, ASTM A53 GR. B ERW, SCH 40, EXTREMOS RANURADOS, ASME B36.10M | R71: FP | S71: N | AD71: 6972 | AE71: =AD71/1000 -> 6.972 | AN71: =+AP71-AL71 -> 0 | AP71: =+CONCATENATE(AF71*$AF$4+AG71*$AG$4+AH71*$AH$4+AI71*$AI$4) -> 0 | AQ71: =AP71 -> 0 | AS71: =AH71 -> 0 | AT71: =AI71 -> 0
B72: 70 | C72: CC-403 | E72: Red de Incendio | F72: =LEFT(K72,4) -> 6340 | I72: 4600027788-06340-502CA-00028 | J72: 0 | K72: 6340-FP-3"-C3-0974-HC | L72: 974 | M72: 1 | N72: 3" | O72: 90 | P72: C3 | Q72: CAÑERÍA DE ACERO CARBONO, ASTM A53 GR. B ERW, SCH 40, EXTREMOS RANURADOS, ASME B36.10M | R72: FP | S72: HC | AC72: Pendiente | AD72: 2890 | AE72: =AD72/1000 -> 2.89 | AN72: =+AP72-AL72 -> 0 | AP72: =+CONCATENATE(AF72*$AF$4+AG72*$AG$4+AH72*$AH$4+AI72*$AI$4) -> 0 | AQ72: =AP72 -> 0 | AS72: =AH72 -> 0 | AT72: =AI72 -> 0
B73: 71 | C73: CC-403 | E73: Red de Incendio | F73: =LEFT(K73,4) -> 6340 | G73: 4600027788-06340-201CA-00004 | I73: 4600027788-06340-502CA-00033 | J73: 0 | K73: 6340-FP-3"-C3-0976-N | L73: 976 | M73: 1 | N73: 3" | O73: 90 | P73: C3 | Q73: CAÑERÍA DE ACERO CARBONO, ASTM A53 GR. B ERW, SCH 40, EXTREMOS RANURADOS, ASME B36.10M | R73: FP | S73: N | T73: Línea 6340-FP-4"-C3-0967-N | U73: Protección sistema tensor 220-CV- 205 | W73: 30 | AC73: Pendiente | AD73: 8057 | AE73: =AD73/1000 -> 8.057 | AN73: =+AP73-AL73 -> 0 | AP73: =+CONCATENATE(AF73*$AF$4+AG73*$AG$4+AH73*$AH$4+AI73*$AI$4) -> 0 | AQ73: =AP73 -> 0 | AS73: =AH73 -> 0 | AT73: =AI73 -> 0
B74: 72 | C74: CC-403 | E74: Red de Incendio | F74: =LEFT(K74,4) -> 6340 | I74: 4600027788-06340-502CA-00030 | J74: 0 | K74: 6340-FP-3"-C3-0976-HC | L74: 976 | M74: 1 | N74: 3" | O74: 90 | P74: C3 | Q74: CAÑERÍA DE ACERO CARBONO, ASTM A53 GR. B ERW, SCH 40, EXTREMOS RANURADOS, ASME B36.10M | R74: FP | S74: HC | AC74: Pendiente | AD74: 3000 | AE74: =AD74/1000 -> 3 | AN74: =+AP74-AL74 -> 0 | AP74: =+CONCATENATE(AF74*$AF$4+AG74*$AG$4+AH74*$AH$4+AI74*$AI$4) -> 0 | AQ74: =AP74 -> 0 | AS74: =AH74 -> 0 | AT74: =AI74 -> 0
B75: 73 | C75: CC-403 | E75: Red de Incendio | F75: =LEFT(K75,4) -> 6340 | G75: 4600027788-06340-201CA-00004 | K75: 6340-FP-12"-C5-0977-N | L75: 977 | N75: 12" | O75: 315 | P75: C5 | Q75: CAÑERÍA, ACERO CARBONO, ASTM A53-B Gr B, SCH STD, EWR, TIPO E, EXTREMOS BISELADO, ASME B36.10 | R75: FP | S75: N | T75: Línea 6340-FP-12"-C3-0974-HC | U75: Línea 6340-FP-12"-C3-0978-HC | W75: 170 | AE75: =AD75/1000 -> 0 | AN75: =+AP75-AL75 -> 0 | AP75: =+CONCATENATE(AF75*$AF$4+AG75*$AG$4+AH75*$AH$4+AI75*$AI$4) -> 0 | AQ75: =AP75 -> 0 | AS75: =AH75 -> 0 | AT75: =AI75 -> 0
B76: 74 | C76: CC-403 | E76: Red de Incendio | F76: =LEFT(K76,4) -> 6340 | G76: 4600027788-06340-201CA-00004 | I76: 4600027788-06340-502CA-00080 | J76: 0 | K76: 6340-FP-12"-C3-0978-HC | L76: 978 | M76: 1 | N76: 12" | O76: 315 | P76: C3 | Q76: CAÑERÍA DE ACERO CARBONO, ASTM A53 GR. B ERW, SCH 40, EXTREMOS RANURADOS, ASME B36.10M | R76: FP | S76: HC | T76: Línea 6340-FP-12"-C5-0977-N | U76: Línea 6340-FP-12"-C5-0979-N | W76: 170 | AD76: 21621 | AE76: =AD76/1000 -> 21.621 | AN76: =+AP76-AL76 -> 0 | AP76: =+CONCATENATE(AF76*$AF$4+AG76*$AG$4+AH76*$AH$4+AI76*$AI$4) -> 0 | AQ76: =AP76 -> 0 | AS76: =AH76 -> 0 | AT76: =AI76 -> 0
B77: 75 | C77: CC-403 | E77: Red de Incendio | F77: =LEFT(K77,4) -> 6340 | G77: 4600027788-06340-201CA-00004 | I77: 4600027788-06340-502CA-00080 | J77: 0 | K77: 6340-FP-12"-C3-0978-HC | L77: 978 | M77: 2 | N77: 12" | O77: 315 | P77: C3 | Q77: CAÑERÍA DE ACERO CARBONO, ASTM A53 GR. B ERW, SCH 40, EXTREMOS RANURADOS, ASME B36.10M | R77: FP | S77: HC | AD77: 34121 | AE77: =AD77/1000 -> 34.121 | AN77: =+AP77-AL77 -> 0 | AP77: =+CONCATENATE(AF77*$AF$4+AG77*$AG$4+AH77*$AH$4+AI77*$AI$4) -> 0 | AQ77: =AP77 -> 0 | AS77: =AH77 -> 0 | AT77: =AI77 -> 0
B78: 76 | C78: CC-403 | E78: Red de Incendio | F78: =LEFT(K78,4) -> 6340 | G78: 4600027788-06340-201CA-00004 | I78: 4600027788-06340-502CA-00080 | J78: 0 | K78: 6340-FP-12"-C3-0978-HC | L78: 978 | M78: 3 | N78: 12" | O78: 315 | P78: C3 | Q78: CAÑERÍA DE ACERO CARBONO, ASTM A53 GR. B ERW, SCH 40, EXTREMOS RANURADOS, ASME B36.10M | R78: FP | S78: HC | AD78: 17103 | AE78: =AD78/1000 -> 17.103 | AN78: =+AP78-AL78 -> 0 | AP78: =+CONCATENATE(AF78*$AF$4+AG78*$AG$4+AH78*$AH$4+AI78*$AI$4) -> 0 | AQ78: =AP78 -> 0 | AS78: =AH78 -> 0 | AT78: =AI78 -> 0
B79: 77 | C79: CC-403 | E79: Red de Incendio | F79: =LEFT(K79,4) -> 6340 | G79: 4600027788-06340-201CA-00004 | K79: 6340-FP-12"-C5-0979-N | L79: 979 | N79: 12" | O79: 315 | P79: C5 | Q79: CAÑERÍA, ACERO CARBONO, ASTM A53-B Gr B, SCH STD, EWR, TIPO E, EXTREMOS BISELADO, ASME B36.10 | R79: FP | S79: N | T79: Línea 6340-FP-12"-C3-0978-HC | U79: Línea 6340-FP-12"-C3-0980-HC | W79: 170 | AE79: =AD79/1000 -> 0 | AN79: =+AP79-AL79 -> 0 | AP79: =+CONCATENATE(AF79*$AF$4+AG79*$AG$4+AH79*$AH$4+AI79*$AI$4) -> 0 | AQ79: =AP79 -> 0 | AS79: =AH79 -> 0 | AT79: =AI79 -> 0
B80: 78 | C80: CC-403 | E80: Red de Incendio | F80: =LEFT(K80,4) -> 6340 | G80: 4600027788-06340-201CA-00005 | I80: 4600027788-06340-502CA-00081 | K80: 6340-FP-12"-C3-0980-HC | L80: 980 | M80: 1 | N80: 12" | O80: 315 | P80: C3 | Q80: CAÑERÍA DE ACERO CARBONO, ASTM A53 GR. B ERW, SCH 40, EXTREMOS RANURADOS, ASME B36.10M | R80: FP | S80: HC | T80: Línea 6340-FP-12"-C5-0979-N | U80: Línea 6340-FP-12"-C5-0982-N | W80: 170 | AD80: 16692 | AE80: =AD80/1000 -> 16.692 | AN80: =+AP80-AL80 -> 0 | AP80: =+CONCATENATE(AF80*$AF$4+AG80*$AG$4+AH80*$AH$4+AI80*$AI$4) -> 0 | AQ80: =AP80 -> 0 | AS80: =AH80 -> 0 | AT80: =AI80 -> 0
B81: 79 | C81: CC-403 | E81: Red de Incendio | F81: =LEFT(K81,4) -> 6340 | G81: 4600027788-06340-201CA-00005 | I81: 4600027788-06340-502CA-00081 | K81: 6340-FP-12"-C3-0980-HC | L81: 980 | M81: 2 | N81: 12" | O81: 315 | P81: C3 | Q81: CAÑERÍA DE ACERO CARBONO, ASTM A53 GR. B ERW, SCH 40, EXTREMOS RANURADOS, ASME B36.10M | R81: FP | S81: HC | AD81: 19441 | AE81: =AD81/1000 -> 19.441 | AN81: =+AP81-AL81 -> 0 | AP81: =+CONCATENATE(AF81*$AF$4+AG81*$AG$4+AH81*$AH$4+AI81*$AI$4) -> 0 | AQ81: =AP81 -> 0 | AS81: =AH81 -> 0 | AT81: =AI81 -> 0
B82: 80 | C82: CC-403 | E82: Red de Incendio | F82: =LEFT(K82,4) -> 6340 | G82: 4600027788-06340-201CA-00004 | K82: 6340-FP-3"-C3-0981-HC | L82: 981 | N82: 3" | O82: 90 | P82: C3 | Q82: CAÑERÍA DE ACERO CARBONO, ASTM A53 GR. B ERW, SCH 40, EXTREMOS RANURADOS, ASME B36.10M | R82: FP | S82: HC | T82: Línea 6340-FP-12"-C5-0965-N | U82: Línea 6340-FP-3"-C3-0983-HC | W82: 170 | AE82: =AD82/1000 -> 0 | AN82: =+AP82-AL82 -> 0 | AP82: =+CONCATENATE(AF82*$AF$4+AG82*$AG$4+AH82*$AH$4+AI82*$AI$4) -> 0 | AQ82: =AP82 -> 0 | AS82: =AH82 -> 0 | AT82: =AI82 -> 0
B83: 81 | C83: CC-403 | E83: Red de Incendio | F83: =LEFT(K83,4) -> 6340 | G83: 4600027788-06340-201CA-00005 | K83: 6340-FP-12"-C5-0982-N | L83: 982 | N83: 12" | O83: 315 | P83: C5 | Q83: CAÑERÍA, ACERO CARBONO, ASTM A53-B Gr B, SCH STD, EWR, TIPO E, EXTREMOS BISELADO, ASME B36.10 | R83: FP | S83: N | T83: Línea 6340-FP-12"-C3-0980-HC | U83: Línea 6340-FP-12"-C3-0986-HC | W83: 170 | AE83: =AD83/1000 -> 0 | AN83: =+AP83-AL83 -> 0 | AP83: =+CONCATENATE(AF83*$AF$4+AG83*$AG$4+AH83*$AH$4+AI83*$AI$4) -> 0 | AQ83: =AP83 -> 0 | AS83: =AH83 -> 0 | AT83: =AI83 -> 0
B84: 82 | C84: CC-403 | E84: Red de Incendio | F84: =LEFT(K84,4) -> 6340 | G84: 4600027788-06340-201CA-00004 | I84: 4600027788-06340-502CA-00058 | J84: 0 | K84: 6340-FP-3"-C3-0983-N | L84: 983 | M84: 1 | N84: 3" | O84: 90 | P84: C3 | Q84: CAÑERÍA DE ACERO CARBONO, ASTM A53 GR. B ERW, SCH 40, EXTREMOS RANURADOS, ASME B36.10M | R84: FP | S84: N | T84: Línea 6340-FP-4"-C3-0981-N | U84: Protección Túnel N°1 | W84: 30 | AC84: Pendiente | AD84: 9453 | AE84: =AD84/1000 -> 9.453 | AN84: =+AP84-AL84 -> 0 | AP84: =+CONCATENATE(AF84*$AF$4+AG84*$AG$4+AH84*$AH$4+AI84*$AI$4) -> 0 | AQ84: =AP84 -> 0 | AS84: =AH84 -> 0 | AT84: =AI84 -> 0
B85: 83 | C85: CC-403 | E85: Red de Incendio | F85: =LEFT(K85,4) -> 6340 | G85: 4600027788-06340-201CA-00004 | I85: 4600027788-06340-502CA-00058 | J85: 0 | K85: 6340-FP-3"-C3-0983-N | L85: 983 | M85: 2 | N85: 3" | O85: 90 | P85: C3 | Q85: CAÑERÍA DE ACERO CARBONO, ASTM A53 GR. B ERW, SCH 40, EXTREMOS RANURADOS, ASME B36.10M | R85: FP | S85: N | AD85: 6757 | AE85: =AD85/1000 -> 6.757 | AN85: =+AP85-AL85 -> 0 | AP85: =+CONCATENATE(AF85*$AF$4+AG85*$AG$4+AH85*$AH$4+AI85*$AI$4) -> 0 | AQ85: =AP85 -> 0 | AS85: =AH85 -> 0 | AT85: =AI85 -> 0
B86: 84 | C86: CC-403 | E86: Red de Incendio | F86: =LEFT(K86,4) -> 6340 | G86: 4600027788-06340-201CA-00004 | I86: 4600027788-06340-502CA-00058 | J86: 0 | K86: 6340-FP-3"-C3-0983-N | L86: 983 | M86: 3 | N86: 3" | O86: 90 | P86: C3 | Q86: CAÑERÍA DE ACERO CARBONO, ASTM A53 GR. B ERW, SCH 40, EXTREMOS RANURADOS, ASME B36.10M | R86: FP | S86: N | AD86: 12667 | AE86: =AD86/1000 -> 12.667 | AN86: =+AP86-AL86 -> 0 | AP86: =+CONCATENATE(AF86*$AF$4+AG86*$AG$4+AH86*$AH$4+AI86*$AI$4) -> 0 | AQ86: =AP86 -> 0 | AS86: =AH86 -> 0 | AT86: =AI86 -> 0
B87: 85 | C87: CC-403 | E87: Red de Incendio | F87: =LEFT(K87,4) -> 6340 | I87: 4600027788-06340-502CA-00057 | J87: 0 | K87: 6340-FP-3"-C3-0983-HC | L87: 983 | M87: 1 | N87: 3" | O87: 90 | P87: C3 | Q87: CAÑERÍA DE ACERO CARBONO, ASTM A53 GR. B ERW, SCH 40, EXTREMOS RANURADOS, ASME B36.10M | R87: FP | S87: HC | AC87: Pendiente | AD87: 2619 | AE87: =AD87/1000 -> 2.619 | AN87: =+AP87-AL87 -> 0 | AP87: =+CONCATENATE(AF87*$AF$4+AG87*$AG$4+AH87*$AH$4+AI87*$AI$4) -> 0 | AQ87: =AP87 -> 0 | AS87: =AH87 -> 0 | AT87: =AI87 -> 0
B88: 86 | C88: CC-403 | E88: Red de Incendio | F88: =LEFT(K88,4) -> 6340 | G88: 4600027788-06340-201CA-00004 | K88: 6340-FP-3"-C5-0984-N | L88: 984 | N88: 3" | O88: 90 | P88: C5 | Q88: CAÑERÍA, ACERO CARBONO, ASTM A53-B Gr B, SCH STD, EWR, TIPO E, EXTREMOS BISELADO, ASME B36.10 | R88: FP | S88: N | T88: Línea 6340-FP-12"-C5-0977-N | U88: Línea 6340-FP-3"-C3-0985-HC | W88: 170 | AE88: =AD88/1000 -> 0 | AN88: =+AP88-AL88 -> 0 | AP88: =+CONCATENATE(AF88*$AF$4+AG88*$AG$4+AH88*$AH$4+AI88*$AI$4) -> 0 | AQ88: =AP88 -> 0 | AS88: =AH88 -> 0 | AT88: =AI88 -> 0
B89: 87 | C89: CC-403 | E89: Red de Incendio | F89: =LEFT(K89,4) -> 6340 | G89: 4600027788-06340-201CA-00004 | I89: 4600027788-06340-502CA-00060 | J89: 0 | K89: 6340-FP-3"-C3-0985-N | L89: 985 | M89: 1 | N89: 3" | O89: 90 | P89: C3 | Q89: CAÑERÍA DE ACERO CARBONO, ASTM A53 GR. B ERW, SCH 40, EXTREMOS RANURADOS, ASME B36.10M | R89: FP | S89: N | T89: Línea 6340-FP-3"-C5-0984-N | U89: Protección Túnel N°1 | W89: 30 | AC89: Pendiente | AD89: 5374 | AE89: =AD89/1000 -> 5.374 | AN89: =+AP89-AL89 -> 0 | AP89: =+CONCATENATE(AF89*$AF$4+AG89*$AG$4+AH89*$AH$4+AI89*$AI$4) -> 0 | AQ89: =AP89 -> 0 | AS89: =AH89 -> 0 | AT89: =AI89 -> 0
B90: 88 | C90: CC-403 | E90: Red de Incendio | F90: =LEFT(K90,4) -> 6340 | G90: 4600027788-06340-201CA-00004 | I90: 4600027788-06340-502CA-00060 | J90: 0 | K90: 6340-FP-3"-C3-0985-N | L90: 985 | M90: 2 | N90: 3" | O90: 90 | P90: C3 | Q90: CAÑERÍA DE ACERO CARBONO, ASTM A53 GR. B ERW, SCH 40, EXTREMOS RANURADOS, ASME B36.10M | R90: FP | S90: N | AD90: 7017 | AE90: =AD90/1000 -> 7.017 | AN90: =+AP90-AL90 -> 0 | AP90: =+CONCATENATE(AF90*$AF$4+AG90*$AG$4+AH90*$AH$4+AI90*$AI$4) -> 0 | AQ90: =AP90 -> 0 | AS90: =AH90 -> 0 | AT90: =AI90 -> 0
B91: 89 | C91: CC-403 | E91: Red de Incendio | F91: =LEFT(K91,4) -> 6340 | G91: 4600027788-06340-201CA-00004 | I91: 4600027788-06340-502CA-00060 | J91: 0 | K91: 6340-FP-3"-C3-0985-N | L91: 985 | M91: 3 | N91: 3" | O91: 90 | P91: C3 | Q91: CAÑERÍA DE ACERO CARBONO, ASTM A53 GR. B ERW, SCH 40, EXTREMOS RANURADOS, ASME B36.10M | R91: FP | S91: N | AD91: 10947 | AE91: =AD91/1000 -> 10.947 | AN91: =+AP91-AL91 -> 0 | AP91: =+CONCATENATE(AF91*$AF$4+AG91*$AG$4+AH91*$AH$4+AI91*$AI$4) -> 0 | AQ91: =AP91 -> 0 | AS91: =AH91 -> 0 | AT91: =AI91 -> 0
B92: 90 | C92: CC-403 | E92: Red de Incendio | F92: =LEFT(K92,4) -> 6340 | I92: 4600027788-06340-502CA-00059 | J92: 0 | K92: 6340-FP-3"-C3-0985-HC | L92: 985 | M92: 1 | N92: 3" | O92: 90 | P92: C3 | Q92: CAÑERÍA DE ACERO CARBONO, ASTM A53 GR. B ERW, SCH 40, EXTREMOS RANURADOS, ASME B36.10M | R92: FP | S92: HC | AC92: Pendiente | AD92: 3055 | AE92: =AD92/1000 -> 3.055 | AN92: =+AP92-AL92 -> 0 | AP92: =+CONCATENATE(AF92*$AF$4+AG92*$AG$4+AH92*$AH$4+AI92*$AI$4) -> 0 | AQ92: =AP92 -> 0 | AS92: =AH92 -> 0 | AT92: =AI92 -> 0
B93: 91 | C93: CC-403 | E93: Red de Incendio | F93: =LEFT(K93,4) -> 6340 | G93: 4600027788-06340-201CA-00005 | I93: 4600027788-06340-502CA-00082 | J93: 0 | K93: 6340-FP-12"-C3-0986-HC | L93: 986 | M93: 1 | N93: 12" | O93: 315 | P93: C3 | Q93: CAÑERÍA DE ACERO CARBONO, ASTM A53 GR. B ERW, SCH 40, EXTREMOS RANURADOS, ASME B36.10M | R93: FP | S93: HC | T93: Línea 6340-FP-12"-C5-0982-N | U93: Línea 6340-FP-12"-C5-0987-N | W93: 170 | AD93: 13820 | AE93: =AD93/1000 -> 13.82 | AN93: =+AP93-AL93 -> 0 | AP93: =+CONCATENATE(AF93*$AF$4+AG93*$AG$4+AH93*$AH$4+AI93*$AI$4) -> 0 | AQ93: =AP93 -> 0 | AS93: =AH93 -> 0 | AT93: =AI93 -> 0
B94: 92 | C94: CC-403 | E94: Red de Incendio | F94: =LEFT(K94,4) -> 6340 | G94: 4600027788-06340-201CA-00005 | I94: 4600027788-06340-502CA-00082 | J94: 0 | K94: 6340-FP-12"-C3-0986-HC | L94: 986 | M94: 2 | N94: 12" | O94: 315 | P94: C3 | Q94: CAÑERÍA DE ACERO CARBONO, ASTM A53 GR. B ERW, SCH 40, EXTREMOS RANURADOS, ASME B36.10M | R94: FP | S94: HC | AD94: 23665 | AE94: =AD94/1000 -> 23.665 | AN94: =+AP94-AL94 -> 0 | AP94: =+CONCATENATE(AF94*$AF$4+AG94*$AG$4+AH94*$AH$4+AI94*$AI$4) -> 0 | AQ94: =AP94 -> 0 | AS94: =AH94 -> 0 | AT94: =AI94 -> 0
B95: 93 | C95: CC-403 | E95: Red de Incendio | F95: =LEFT(K95,4) -> 6340 | G95: 4600027788-06340-201CA-00005 | K95: 6340-FP-12"-C5-0987-N | L95: 987 | N95: 12" | O95: 315 | P95: C5 | Q95: CAÑERÍA, ACERO CARBONO, ASTM A53-B Gr B, SCH STD, EWR, TIPO E, EXTREMOS BISELADO, ASME B36.10 | R95: FP | S95: N | T95: Línea 6340-FP-12"-C3-0986-HC | U95: Línea 6340-FP-12"-C3-0988-HC | W95: 170 | AE95: =AD95/1000 -> 0 | AN95: =+AP95-AL95 -> 0 | AP95: =+CONCATENATE(AF95*$AF$4+AG95*$AG$4+AH95*$AH$4+AI95*$AI$4) -> 0 | AQ95: =AP95 -> 0 | AS95: =AH95 -> 0 | AT95: =AI95 -> 0
B96: 94 | C96: CC-403 | E96: Red de Incendio | F96: =LEFT(K96,4) -> 6340 | G96: 4600027788-06340-201CA-00005 | I96: 4600027788-06340-502CA-00083 | J96: 0 | K96: 6340-FP-12"-C3-0988-HC | L96: 988 | M96: 1 | N96: 12" | O96: 315 | P96: C3 | Q96: CAÑERÍA DE ACERO CARBONO, ASTM A53 GR. B ERW, SCH 40, EXTREMOS RANURADOS, ASME B36.10M | R96: FP | S96: HC | T96: Línea 6340-FP-12"-C5-0987-N | U96: Línea 6340-FP-12"-C5-0989-N | W96: 170 | AD96: 19919 | AE96: =AD96/1000 -> 19.919 | AN96: =+AP96-AL96 -> 0 | AP96: =+CONCATENATE(AF96*$AF$4+AG96*$AG$4+AH96*$AH$4+AI96*$AI$4) -> 0 | AQ96: =AP96 -> 0 | AS96: =AH96 -> 0 | AT96: =AI96 -> 0
B97: 95 | C97: CC-403 | E97: Red de Incendio | F97: =LEFT(K97,4) -> 6340 | G97: 4600027788-06340-201CA-00005 | I97: 4600027788-06340-502CA-00083 | J97: 0 | K97: 6340-FP-12"-C3-0988-HC | L97: 988 | M97: 2 | N97: 12" | O97: 315 | P97: C3 | Q97: CAÑERÍA DE ACERO CARBONO, ASTM A53 GR. B ERW, SCH 40, EXTREMOS RANURADOS, ASME B36.10M | R97: FP | S97: HC | AD97: 17402 | AE97: =AD97/1000 -> 17.402 | AN97: =+AP97-AL97 -> 0 | AP97: =+CONCATENATE(AF97*$AF$4+AG97*$AG$4+AH97*$AH$4+AI97*$AI$4) -> 0 | AQ97: =AP97 -> 0 | AS97: =AH97 -> 0 | AT97: =AI97 -> 0
B98: 96 | C98: CC-403 | E98: Red de Incendio | F98: =LEFT(K98,4) -> 6340 | G98: 4600027788-06340-201CA-00005 | K98: 6340-FP-12"-C5-0989-N | L98: 989 | N98: 12" | O98: 315 | P98: C5 | Q98: CAÑERÍA, ACERO CARBONO, ASTM A53-B Gr B, SCH STD, EWR, TIPO E, EXTREMOS BISELADO, ASME B36.10 | R98: FP | S98: N | T98: Línea 6340-FP-12"-C3-0988-HC | U98: Línea 6340-FP-12"-C3-0991-HC | W98: 170 | AE98: =AD98/1000 -> 0 | AN98: =+AP98-AL98 -> 0 | AP98: =+CONCATENATE(AF98*$AF$4+AG98*$AG$4+AH98*$AH$4+AI98*$AI$4) -> 0 | AQ98: =AP98 -> 0 | AS98: =AH98 -> 0 | AT98: =AI98 -> 0
B99: 97 | C99: CC-403 | E99: Red de Incendio | F99: =LEFT(K99,4) -> 6340 | G99: 4600027788-06340-201CA-00004 | K99: 6340-FP-3"-C5-0990-N | L99: 990 | N99: 3" | O99: 90 | P99: C5 | Q99: CAÑERÍA, ACERO CARBONO, ASTM A53-B Gr B, SCH STD, EWR, TIPO E, EXTREMOS BISELADO, ASME B36.10 | R99: FP | S99: N | T99: Línea 6340-FP-12"-C5-0977-N | U99: Línea 6340-FP-3"-C3-0992-HC | W99: 170 | AE99: =AD99/1000 -> 0 | AN99: =+AP99-AL99 -> 0 | AP99: =+CONCATENATE(AF99*$AF$4+AG99*$AG$4+AH99*$AH$4+AI99*$AI$4) -> 0 | AQ99: =AP99 -> 0 | AS99: =AH99 -> 0 | AT99: =AI99 -> 0
B100: 98 | C100: CC-403 | E100: Red de Incendio | F100: =LEFT(K100,4) -> 6340 | G100: 4600027788-06340-201CA-00005 | I100: 4600027788-06340-502CA-00084 | J100: 0 | K100: 6340-FP-12"-C3-0991-HC | L100: 991 | M100: 1 | N100: 12" | O100: 315 | P100: C3 | Q100: CAÑERÍA DE ACERO CARBONO, ASTM A53 GR. B ERW, SCH 40, EXTREMOS RANURADOS, ASME B36.10M | R100: FP | S100: HC | T100: Línea 6340-FP-12"-C5-0989-N | U100: Línea 6340-FP-12"-C5-0995-N | W100: 170 | AD100: 12869 | AE100: =AD100/1000 -> 12.869 | AN100: =+AP100-AL100 -> 0 | AP100: =+CONCATENATE(AF100*$AF$4+AG100*$AG$4+AH100*$AH$4+AI100*$AI$4) -> 0 | AQ100: =AP100 -> 0 | AS100: =AH100 -> 0 | AT100: =AI100 -> 0
...

Sheet Soportes General
C2: LISTADO DE SOPORTES | O2: Pulgadas | P2: Suma de Cant.
O3: 0.75 | P3: 2
O4: 1 | P4: 506
B5: CENTINA | O5: 1.25 | P5: 3
B6: ITEM | C6: Clase | D6: Tag Soporte | E6: Dn Ø " | F6: Cant. | G6: Unidad | H6: Peso Unitario/kg | I6: Peso Total kg | J6: Estandar Soportes | K6: Rev | L6: Comentario | M6: Estatus Solicitud | O6: 1.5 | P6: 204
B7: 1 | C7: SA01 | D7: 3631-SA01-30" | E7: 30 | F7: 1 | G7: c/u | H7: 870 | I7: =H7*F7 -> 870 | J7: 4600027788-03630-000CA-00003 | K7: 3 | L7: El Gap Largo/Ancho y espesor dependera de material de cañeria | O7: 2 | P7: 292
B8: 2 | C8: SA07 | D8: 3631-SA07-12" | E8: 12 | F8: 4 | G8: c/u | H8: 189 | I8: =H8*F8 -> 756 | J8: 4600027788-03630-000CA-00004 | K8: 3 | L8: El Gap Largo/Ancho y espesor dependera de material de cañeria | O8: 3 | P8: 828
B9: 3 | C9: SA08 | D9: 3631-SA08-28" | E9: 28 | F9: 1 | G9: c/u | H9: 661 | I9: =H9*F9 -> 661 | J9: 4600027788-03630-000CA-00004 | K9: 3 | L9: El Gap Largo/Ancho y espesor dependera de material de cañeria | O9: 4 | P9: 75
B10: 4 | C10: SA09 | D10: 3631-SA09-24" | E10: 24 | F10: 1 | G10: c/u | H10: 417 | I10: =H10*F10 -> 417 | J10: 4600027788-03630-000CA-00005 | K10: 2 | L10: El Gap Largo/Ancho y espesor dependera de material de cañeria | O10: 6 | P10: 29
B11: 5 | C11: SA40 | D11: 3631-SA40-36" | E11: 26 | F11: 1 | G11: c/u | H11: 413 | I11: =H11*F11 -> 413 | J11: 4600027788-03630-000CA-00005 | K11: 2 | L11: El Gap Largo/Ancho y espesor dependera de material de cañeria | O11: 8 | P11: 39
B12: 6 | C12: SS02 | D12: 3631-SS02-16" | E12: 16 | F12: 9 | G12: c/u | H12: 48 | I12: =H12*F12 -> 432 | J12: 4600027788-03630-000CA-00003 | K12: 3 | L12: El Gap Largo/Ancho y espesor dependera de material de cañeria | O12: 10 | P12: 31
B13: 7 | C13: SS02 | D13: 3631-SS02-24" | E13: 24 | F13: 3 | G13: c/u | H13: 137 | I13: =H13*F13 -> 411 | J13: 4600027788-03630-000CA-00003 | K13: 3 | L13: El Gap Largo/Ancho y espesor dependera de material de cañeria | O13: 12 | P13: 306
B14: 8 | C14: SS02 | D14: 3631-SS02-30" | E14: 30 | F14: 4 | G14: c/u | H14: 227 | I14: =H14*F14 -> 908 | J14: 4600027788-03630-000CA-00003 | K14: 3 | L14: El Gap Largo/Ancho y espesor dependera de material de cañeria | O14: 14 | P14: 75
B15: 9 | C15: SS02 | D15: 3631-SS02-36" | E15: 36 | F15: 1 | G15: c/u | H15: 170 | I15: =H15*F15 -> 170 | J15: 4600027788-03630-000CA-00003 | K15: 3 | L15: El Gap Largo/Ancho y espesor dependera de material de cañeria | O15: Total general | P15: 2390
B16: 10 | C16: SS04 | D16: 3631-SS04-16" | E16: 16 | F16: 3 | G16: c/u | H16: 112 | I16: =H16*F16 -> 336 | J16: 4600027788-03630-000CA-00003 | K16: 3 | L16: El Gap Largo/Ancho y espesor dependera de material de cañeria
B17: 11 | C17: SS04 | D17: 3631-SS04-24" | E17: 24 | F17: 2 | G17: c/u | H17: 225 | I17: =H17*F17 -> 450 | J17: 4600027788-03630-000CA-00003 | K17: 3 | L17: El Gap Largo/Ancho y espesor dependera de material de cañeria
B18: 12 | C18: SS04 | D18: 3631-SS04-28" | E18: 28 | F18: 9 | G18: c/u | H18: 238 | I18: =H18*F18 -> 2142 | J18: 4600027788-03630-000CA-00003 | K18: 3 | L18: El Gap Largo/Ancho y espesor dependera de material de cañeria
B19: 13 | C19: SS04 | D19: 3631-SS04-36" | E19: 36 | F19: 15 | G19: c/u | H19: 451 | I19: =H19*F19 -> 6765 | J19: 4600027788-03630-000CA-00003 | K19: 3 | L19: El Gap Largo/Ancho y espesor dependera de material de cañeria
E21: Total | F21: =+SUM(F7:F20) -> 54 | G21: - | H21: - | I21: =SUM(I7:I20) -> 14731
B23: RED CONTRA INCENDIO
B24: ITEM | C24: Clase | D24: Tag Soporte | E24: Dn Ø" | F24: Cant. | G24: Unidad | H24: Peso Unitario/kg | I24: Peso Total kg | J24: Tag Linea | K24: Materialidad | L24: Planos de Soporte | M24: Estatus Solicitud
B25: 1 | C25: PU01 | D25: 6340-PU01-015 | E25: 1.5 | F25: 2 | G25: c/u | H25: 0.1 | I25: =F25*H25 -> 0.2 | J25: 6340-FP-1 1/2"-C3-0968-N | K25: Acero Carbono ASTM A36 o superior | L25: 4600027788-03630-000CA-00001 / 00002 / 00006
B26: 2 | C26: PU01 | D26: 6340-PU01-015 | E26: 1.5 | F26: 3 | G26: c/u | H26: 0.1 | I26: =F26*H26 -> 0.3 | J26: 6340-FP-1 1/2"-C3-0972-HC | K26: Acero Carbono ASTM A36 o superior | L26: 4600027788-03630-000CA-00001 / 00002 / 00006
B27: 3 | C27: SP22 | D27: 6340-SP22-001 | E27: 1.5 | F27: 3 | G27: c/u | H27: 2 | I27: =F27*H27 -> 6 | J27: 6340-FP-1 1/2"-C3-0972-HC | K27: Acero Carbono ASTM A36 o superior | L27: 4600027788-03630-000CA-00001 / 00002 / 00006
B28: 4 | C28: PU01 | D28: 6340-PU01-015 | E28: 1.5 | F28: 2 | G28: c/u | H28: 0.1 | I28: =F28*H28 -> 0.2 | J28: 6340-FP-1 1/2"-C3-0974-N | K28: Acero Carbono ASTM A36 o superior | L28: 4600027788-03630-000CA-00001 / 00002 / 00006
B29: 5 | C29: PU01 | D29: 6340-PU01-015 | E29: 1.5 | F29: 2 | G29: c/u | H29: 0.1 | I29: =F29*H29 -> 0.2 | J29: 6340-FP-1 1/2"-C3-0981-HC | K29: Acero Carbono ASTM A36 o superior | L29: 4600027788-03630-000CA-00001 / 00002 / 00006
B30: 6 | C30: SP22 | D30: 6340-SP22-001 | E30: 1.5 | F30: 2 | G30: c/u | H30: 2 | I30: =F30*H30 -> 4 | J30: 6340-FP-1 1/2"-C3-0981-HC | K30: Acero Carbono ASTM A36 o superior | L30: 4600027788-03630-000CA-00001 / 00002 / 00006
B31: 7 | C31: PU01 | D31: 6340-PU01-015 | E31: 1.5 | F31: 3 | G31: c/u | H31: 0.1 | I31: =F31*H31 -> 0.3 | J31: 6340-FP-1 1/2"-C3-0990-HC | K31: Acero Carbono ASTM A36 o superior | L31: 4600027788-03630-000CA-00001 / 00002 / 00006
B32: 8 | C32: SP22 | D32: 6340-SP22-001 | E32: 1.5 | F32: 3 | G32: c/u | H32: 2 | I32: =F32*H32 -> 6 | J32: 6340-FP-1 1/2"-C3-0990-HC | K32: Acero Carbono ASTM A36 o superior | L32: 4600027788-03630-000CA-00001 / 00002 / 00006
B33: 9 | C33: PU01 | D33: 6340-PU01-015 | E33: 1.5 | F33: 3 | G33: c/u | H33: 0.1 | I33: =F33*H33 -> 0.3 | J33: 6340-FP-1 1/2"-C3-0997-HC | K33: Acero Carbono ASTM A36 o superior | L33: 4600027788-03630-000CA-00001 / 00002 / 00006
B34: 10 | C34: SP22 | D34: 6340-SP22-001 | E34: 1.5 | F34: 3 | G34: c/u | H34: 2 | I34: =F34*H34 -> 6 | J34: 6340-FP-1 1/2"-C3-0997-HC | K34: Acero Carbono ASTM A36 o superior | L34: 4600027788-03630-000CA-00001 / 00002 / 00006
B35: 11 | C35: PU01 | D35: 6340-PU01-030 | E35: 3 | F35: 1 | G35: c/u | H35: 0.4 | I35: =F35*H35 -> 0.4 | J35: 6340-FP-1 1/2"-C3-0997-HC | K35: Acero Carbono ASTM A36 o superior | L35: 4600027788-03630-000CA-00001 / 00002 / 00006
B36: 12 | C36: SP39 | D36: 6340-SP39-001 | E36: 3 | F36: 1 | G36: c/u | H36: 5.6 | I36: =F36*H36 -> 5.6 | J36: 6340-FP-1 1/2"-C3-0997-HC | K36: Acero Carbono ASTM A36 o superior | L36: 4600027788-03630-000CA-00001 / 00002 / 00006
... B167: 143 | C167: SG01 | D167: 6340-SG01-120 | E167: 12 | F167: 9 | G167: c/u | H167: 6.3 | I167: =F167*H167 -> 56.7 | J167: 6340-FP-12"-C3-0966-HC | K167: Acero Carbono ASTM A36 o superior | L167: 4600027788-03630-000CA-00001 / 00002 / 00006
B168: 144 | C168: SL01 | D168: 6340-SL01-120 | E168: 12 | F168: 2 | G168: c/u | H168: 15.7 | I168: =F168*H168 -> 31.4 | J168: 6340-FP-12"-C3-0966-HC | K168: Acero Carbono ASTM A36 o superior | L168: 4600027788-03630-000CA-00001 / 00002 / 00006 | W168: 3" | X168: 12" | Y168: 14" | Z168: totales
B169: 145 | C169: SP01 | D169: 6340-SP01-402 | E169: 12 | F169: 9 | G169: c/u | H169: 17 | I169: =F169*H169 -> 153 | J169: 6340-FP-12"-C3-0966-HC | K169: Acero Carbono ASTM A36 o superior | L169: 4600027788-03630-000CA-00001 / 00002 / 00006 | V169: SP 42 | W169: - | X169: 64 | Y169: 20 | Z169: =+X169+Y169 -> 84
B170: 146 | C170: SS12 | D170: 6340-SS12-120 | E170: 12 | F170: 5 | G170: c/u | H170: 20 | I170: =F170*H170 -> 100 | J170: 6340-FP-12"-C3-0966-HC | K170: Acero Carbono ASTM A36 o superior | L170: 4600027788-03630-000CA-00001 / 00002 / 00006 | V170: SP 43 | W170: 132 | X170: - | Y170: - | Z170: 132
B171: 147 | C171: SZ02 | D171: 6340-SZ02-120 | E171: 12 | F171: 9 | G171: c/u | H171: 8.4 | I171: =F171*H171 -> 75.6 | J171: 6340-FP-12"-C3-0966-HC | K171: Acero Carbono ASTM A36 o superior | L171: 4600027788-03630-000CA-00001 / 00002 / 00006
B172: 148 | C172: SP26 | D172: 3640-SP26-502 | E172: 12 | F172: 2 | G172: c/u | H172: 205 | I172: =F172*H172 -> 410 | J172: 6340-FP-12"-C3-0978-HC | K172: Acero Carbono ASTM A36 o superior | L172: 4600027788-03630-000CA-00001 / 00002 / 00006
B173: 149 | C173: SP33 | D173: 3640-SP33-002 | E173: 12 | F173: 2 | G173: c/u | H173: 41 | I173: =F173*H173 -> 82 | J173: 6340-FP-12"-C3-0978-HC | K173: Acero Carbono ASTM A36 o superior | L173: 4600027788-03630-000CA-00001 / 00002 / 00006
B174: 150 | C174: SG01 | D174: 6340-SG01-120 | E174: 12 | F174: 8 | G174: c/u | H174: 6.3 | I174: =F174*H174 -> 50.4 | J174: 6340-FP-12"-C3-0978-HC | K174: Acero Carbono ASTM A36 o superior | L174: 4600027788-03630-000CA-00001 / 00002 / 00006
B175: 151 | C175: SL01 | D175: 6340-SL01-120 | E175: 12 | F175: 3 | G175: c/u | H175: 15.7 | I175: =F175*H175 -> 47.1 | J175: 6340-FP-12"-C3-0978-HC | K175: Acero Carbono ASTM A36 o superior | L175: 4600027788-03630-000CA-00001 / 00002 / 00006
B176: 152 | C176: SP01 | D176: 6340-SP01-403 | E176: 12 | F176: 5 | G176: c/u | H176: 20.3 | I176: =F176*H176 -> 101.5 | J176: 6340-FP-12"-C3-0978-HC | K176: Acero Carbono ASTM A36 o superior | L176: 4600027788-03630-000CA-00001 / 00002 / 00006
B177: 153 | C177: SP42 | D177: 6340-SP42-001 | E177: 12 | F177: 11 | G177: c/u | H177: 22 | I177: =F177*H177 -> 242 | J177: 6340-FP-12"-C3-0978-HC | K177: Acero Carbono ASTM A36 o superior | L177: 4600027788-03630-000CA-00001 / 00002 / 00006
B178: 154 | C178: SS12 | D178: 6340-SS12-120 | E178: 12 | F178: 12 | G178: c/u | H178: 20 | I178: =F178*H178 -> 240 | J178: 6340-FP-12"-C3-0978-HC | K178: Acero Carbono ASTM A36 o superior | L178: 4600027788-03630-000CA-00001 / 00002 / 00006
B179: 155 | C179: SZ02 | D179: 6340-SZ02-120 | E179: 12 | F179: 8 | G179: c/u | H179: 8.4 | I179: =F179*H179 -> 67.2 | J179: 6340-FP-12"-C3-0978-HC | K179: Acero Carbono ASTM A36 o superior | L179: 4600027788-03630-000CA-00001 / 00002 / 00006
B180: 156 | C180: SP26 | D180: 3640-SP26-502 | E180: 12 | F180: 2 | G180: c/u | H180: 205 | I180: =F180*H180 -> 410 | J180: 6340-FP-12"-C3-0980-HC | K180: Acero Carbono ASTM A36 o superior | L180: 4600027788-03630-000CA-00001 / 00002 / 00006
B181: 157 | C181: SP33 | D181: 3640-SP33-002 | E181: 12 | F181: 2 | G181: c/u | H181: 41 | I181: =F181*H181 -> 82 | J181: 6340-FP-12"-C3-0980-HC | K181: Acero Carbono ASTM A36 o superior | L181: 4600027788-03630-000CA-00001 / 00002 / 00006
B182: 158 | C182: SG01 | D182: 6340-SG01-120 | E182: 12 | F182: 8 | G182: c/u | H182: 6.3 | I182: =F182*H182 -> 50.4 | J182: 6340-FP-12"-C3-0980-HC | K182: Acero Carbono ASTM A36 o superior | L182: 4600027788-03630-000CA-00001 / 00002 / 00006
... B623: 599 | C623: PU01 | D623: 6340-PU01-015 | E623: 1.5 | F623: 1 | G623: c/u | H623: 0.1 | I623: =F623*H623 -> 0.1 | J623: 6340-FP-4"-C5-1170-N | K623: Acero Carbono ASTM A36 o superior | L623: 4600027788-03630-000CA-00001 / 00002 / 00006
E624: Total | F624: =+SUM(F25:F623) -> 2390 | G624: - | H624: - | I624: =SUM(I25:I623) -> 18640.35

Sheet Valvulas_General
B2: Listado Valvulas Manuales
B4: N° | C4: Ø | D4: Codigo | E4: Correlativo | F4: Tag | G4: Tipo de Valvula | H4: Descripcion | I4: Servicio | J4: Clase ASME/ Rating | K4: Presión de Diseño (kPa) | L4: Accionamiento | M4: N° de Línea | N4: N° P&ID Codelco | O4: Rev | P4: Comentario | S4: Resumen Sentina
B5: 1 | C5: 4" | D5: VBB | E5: 901 | F5: 4"-VBB-901 | G5: Válvula de Bola | H5: VÁLVULA DE BOLA CLASE 300 SEGÚN B16.34, FLANGES SEGÚN B16.5, OPERACIÓN MANUAL, CUERPO TITANIO ASTM B367 GR2, BOLA TITANIO ASTM B367 GR2, TRIM TITANIO ASTM B367 GR2, ASIENTO VITON C. | I5: Refino | J5: CL 300 | K5: 5.102 | L5: Manual con Palanca | M5: 3631-RA-16"-T1-0951-N | N5: 4600027788-03631-201CA-00002 | O5: 0 | R5: Cuenta de Codigo | S5: Etiquetas de columna
B6: 2 | C6: 4" | D6: VVT | E6: 901 | F6: 4"-VVT-901 | G6: Válvula de Venteo | H6: VÁLVULA DE VENTEO DE DOBLE / TRIPLE EFECTO, CLASE 300 SEGÚN AWWA C512, FLANGES SEGÚN B16.5, FLG, CUERPO PVDF, FLOTADOR EN ESPUMA DE POLIETILENO, TRIM TITANIO ASTM B367 GR2, ASIENTO VITON C. | I6: Refino | J6: CL 300 | K6: 5.102 | L6: N/A | M6: 3631-RA-16"-T1-0951-N | N6: 4600027788-03631-201CA-00002 | O6: 0 | R6: Etiquetas de fila | S6: 12" | T6: 16" | U6: 2" | V6: 24" | W6: 36" | X6: 4" | Y6: 6" | Z6: 8" | AA6: Total general
B7: 3 | C7: 2" | D7: VBB | E7: 903B | F7: 2"-VBB-903B | G7: Válvula de Bola | H7: VÁLVULA DE BOLA CLASE 300 SEGÚN B16.34, FLANGES SEGÚN B16.5, OPERACIÓN MANUAL, CUERPO TITANIO ASTM B367 GR2, BOLA TITANIO ASTM B367 GR2, TRIM TITANIO ASTM B367 GR2, ASIENTO VITON C. | I7: Refino | J7: CL 300 | K7: 5.102 | L7: Manual con Palanca | M7: 3631-RA-16"-T1-0951-N | N7: 4600027788-03631-201CA-00002 | O7: 0 | R7: Válvula de Bola | U7: 24 | X7: 5 | Y7: 4 | Z7: 3 | AA7: 36
B8: 4 | C8: 2" | D8: VBB | E8: 904B | F8: 2"-VBB-904B | G8: Válvula de Bola | H8: VÁLVULA DE BOLA CLASE 300 SEGÚN B16.34, FLANGES SEGÚN B16.5, OPERACIÓN MANUAL, CUERPO TITANIO ASTM B367 GR2, BOLA TITANIO ASTM B367 GR2, TRIM TITANIO ASTM B367 GR2, ASIENTO VITON C. | I8: Refino | J8: CL 300 | K8: 5.102 | L8: Manual con Palanca | M8: 3631-RA-16"-T1-0951-N | N8: 4600027788-03631-201CA-00002 | O8: 0 | R8: Valvula de Retención | T8: 4 | AA8: 4
B9: 5 | C9: 2" | D9: VBB | E9: 903 | F9: 2"-VBB-903 | G9: Válvula de Bola | H9: VÁLVULA DE BOLA CLASE 300 SEGÚN B16.34, FLANGES SEGÚN B16.5, OPERACIÓN MANUAL, CUERPO TITANIO ASTM B367 GR2, BOLA TITANIO ASTM B367 GR2, TRIM TITANIO ASTM B367 GR2, ASIENTO VITON C. | I9: Refino | J9: CL 300 | K9: 5.102 | L9: Manual con Palanca | M9: 3631-RA-16"-T1-0951-N | N9: 4600027788-03631-201CA-00002 | O9: 0 | R9: Válvula de Venteo | X9: 5 | Y9: 4 | Z9: 3 | AA9: 12
B10: 6 | C10: 2" | D10: VBB | E10: 904 | F10: 2"-VBB-904 | G10: Válvula de Bola | H10: VÁLVULA DE BOLA CLASE 300 SEGÚN B16.34, FLANGES SEGÚN B16.5, OPERACIÓN MANUAL, CUERPO TITANIO ASTM B367 GR2, BOLA TITANIO ASTM B367 GR2, TRIM TITANIO ASTM B367 GR2, ASIENTO VITON C. | I10: Refino | J10: CL 300 | K10: 5.102 | L10: Manual con Palanca | M10: 3631-RA-16"-T1-0951-N | N10: 4600027788-03631-201CA-00002 | O10: 0 | R10: Válvula Mariposa | S10: 9 | T10: 5 | V10: 1 | W10: 1 | AA10: 16
B11: 7 | C11: 16" | D11: VRC | E11: 901 | F11: 16"-VRC-901 | G11: Valvula de Retención | H11: VÁLVULA DE RETENCIÓN TIPO DUO CHECK ASME B16.34, CL 300 WAFER, PARA FLANGES ASME B16.5, CUERPO Y TRIM TITANIO ASTM B367 GR C2. | I11: Refino | J11: CL 300 | K11: 5.102 | L11: N/A | M11: 3631-RA-16"-T1-0951-N | N11: 4600027788-03631-201CA-00002 | O11: 0 | R11: Total general | S11: 9 | T11: 9 | U11: 24 | V11: 1 | W11: 1 | X11: 10 | Y11: 8 | Z11: 6 | AA11: 68
B12: 8 | C12: 2" | D12: VBB | E12: 925 | F12: 2"-VBB-925 | G12: Válvula de Bola | H12: VÁLVULA DE BOLA CLASE 300 SEGÚN B16.34, FLANGES SEGÚN B16.5, OPERACIÓN MANUAL, CUERPO TITANIO ASTM B367 GR2, BOLA TITANIO ASTM B367 GR2, TRIM TITANIO ASTM B367 GR2, ASIENTO VITON C. | I12: Refino | J12: CL 300 | K12: 5.102 | L12: Manual con Palanca | M12: 3631-RA-16"-T1-0951-N | N12: 4600027788-03631-201CA-00002 | O12: 0
B13: 9 | C13: 16" | D13: VMP | E13: 901 | F13: 16"-VMP-901 | G13: Válvula Mariposa | H13: VÁLVULA DE MARIPOSA HIGH PERFOMANCE CLASE 300 SEGÚN B16.34, FLANGES SEGÚN B16.5, LUG, OPERADA POR ENGRANAJE, CUERPO TITANIO ASTM B367 GR C2, DISCO TITANIO ASTM B367 GR2, ASIENTO VITON C. | I13: Refino | J13: CL 300 | K13: 5.102 | L13: Manual con Reductor | M13: 3631-RA-16"-T1-0951-N | N13: 4600027788-03631-201CA-00002 | O13: 0
B14: 10 | C14: 4" | D14: VBB | E14: 902 | F14: 4"-VBB-902 | G14: Válvula de Bola | H14: VÁLVULA DE BOLA CLASE 300 SEGÚN B16.34, FLANGES SEGÚN B16.5, OPERACIÓN MANUAL, CUERPO TITANIO ASTM B367 GR2, BOLA TITANIO ASTM B367 GR2, TRIM TITANIO ASTM B367 GR2, ASIENTO VITON C. | I14: Refino | J14: CL 300 | K14: 5.102 | L14: Manual con Palanca | M14: 3631-RA-16"-T1-0952-N | N14: 4600027788-03631-201CA-00002 | O14: 0
B15: 11 | C15: 4" | D15: VVT | E15: 902 | F15: 4"-VVT-902 | G15: Válvula de Venteo | H15: VÁLVULA DE VENTEO DE DOBLE / TRIPLE EFECTO, CLASE 300 SEGÚN AWWA C512, FLANGES SEGÚN B16.5, FLG, CUERPO PVDF, FLOTADOR EN ESPUMA DE POLIETILENO, TRIM TITANIO ASTM B367 GR2, ASIENTO VITON C. | I15: Refino | J15: CL 300 | K15: 5.102 | L15: N/A | M15: 3631-RA-16"-T1-0952-N | N15: 4600027788-03631-201CA-00002 | O15: 0
B16: 12 | C16: 2" | D16: VBB | E16: 907B | F16: 2"-VBB-907B | G16: Válvula de Bola | H16: VÁLVULA DE BOLA CLASE 300 SEGÚN B16.34, FLANGES SEGÚN B16.5, OPERACIÓN MANUAL, CUERPO TITANIO ASTM B367 GR2, BOLA TITANIO ASTM B367 GR2, TRIM TITANIO ASTM B367 GR2, ASIENTO VITON C. | I16: Refino | J16: CL 300 | K16: 5.102 | L16: Manual con Palanca | M16: 3631-RA-16"-T1-0952-N | N16: 4600027788-03631-201CA-00002 | O16: 0
B17: 13 | C17: 2" | D17: VBB | E17: 908B | F17: 2"-VBB-908B | G17: Válvula de Bola | H17: VÁLVULA DE BOLA CLASE 300 SEGÚN B16.34, FLANGES SEGÚN B16.5, OPERACIÓN MANUAL, CUERPO TITANIO ASTM B367 GR2, BOLA TITANIO ASTM B367 GR2, TRIM TITANIO ASTM B367 GR2, ASIENTO VITON C. | I17: Refino | J17: CL 300 | K17: 5.102 | L17: Manual con Palanca | M17: 3631-RA-16"-T1-0952-N | N17: 4600027788-03631-201CA-00002 | O17: 0
B18: 14 | C18: 2" | D18: VBB | E18: 907 | F18: 2"-VBB-907 | G18: Válvula de Bola | H18: VÁLVULA DE BOLA CLASE 300 SEGÚN B16.34, FLANGES SEGÚN B16.5, OPERACIÓN MANUAL, CUERPO TITANIO ASTM B367 GR2, BOLA TITANIO ASTM B367 GR2, TRIM TITANIO ASTM B367 GR2, ASIENTO VITON C. | I18: Refino | J18: CL 300 | K18: 5.102 | L18: Manual con Palanca | M18: 3631-RA-16"-T1-0952-N | N18: 4600027788-03631-201CA-00002 | O18: 0
B19: 15 | C19: 2" | D19: VBB | E19: 908 | F19: 2"-VBB-908 | G19: Válvula de Bola | H19: VÁLVULA DE BOLA CLASE 300 SEGÚN B16.34, FLANGES SEGÚN B16.5, OPERACIÓN MANUAL, CUERPO TITANIO ASTM B367 GR2, BOLA TITANIO ASTM B367 GR2, TRIM TITANIO ASTM B367 GR2, ASIENTO VITON C. | I19: Refino | J19: CL 300 | K19: 5.102 | L19: Manual con Palanca | M19: 3631-RA-16"-T1-0952-N | N19: 4600027788-03631-201CA-00002 | O19: 0
B20: 16 | C20: 16" | D20: VRC | E20: 902 | F20: 16"-VRC-902 | G20: Valvula de Retención | H20: VÁLVULA DE RETENCIÓN TIPO DUO CHECK ASME B16.34, CL 300 WAFER, PARA FLANGES ASME B16.5, CUERPO Y TRIM TITANIO ASTM B367 GR C2. | I20: Refino | J20: CL 300 | K20: 5.102 | L20: N/A | M20: 3631-RA-16"-T1-0952-N | N20: 4600027788-03631-201CA-00002 | O20: 0
B21: 17 | C21: 2" | D21: VBB | E21: 926 | F21: 2"-VBB-926 | G21: Válvula de Bola | H21: VÁLVULA DE BOLA CLASE 300 SEGÚN B16.34, FLANGES SEGÚN B16.5, OPERACIÓN MANUAL, CUERPO TITANIO ASTM B367 GR2, BOLA TITANIO ASTM B367 GR2, TRIM TITANIO ASTM B367 GR2, ASIENTO VITON C. | I21: Refino | J21: CL 300 | K21: 5.102 | L21: Manual con Palanca | M21: 3631-RA-16"-T1-0952-N | N21: 4600027788-03631-201CA-00002 | O21: 0
B22: 18 | C22: 16" | D22: VMP | E22: 902 | F22: 16"-VMP-902 | G22: Válvula Mariposa | H22: VÁLVULA DE MARIPOSA HIGH PERFOMANCE CLASE 300 SEGÚN B16.34, FLANGES SEGÚN B16.5, LUG, OPERADA POR ENGRANAJE, CUERPO TITANIO ASTM B367 GR C2, DISCO TITANIO ASTM B367 GR2, ASIENTO VITON C. | I22: Refino | J22: CL 300 | K22: 5.102 | L22: Manual con Reductor | M22: 3631-RA-16"-T1-0952-N | N22: 4600027788-03631-201CA-00002 | O22: 0
B23: 19 | C23: 4" | D23: VBB | E23: 903 | F23: 4"-VBB-903 | G23: Válvula de Bola | H23: VÁLVULA DE BOLA CLASE 300 SEGÚN B16.34, FLANGES SEGÚN B16.5, OPERACIÓN MANUAL, CUERPO TITANIO ASTM B367 GR2, BOLA TITANIO ASTM B367 GR2, TRIM TITANIO ASTM B367 GR2, ASIENTO VITON C. | I23: Refino | J23: CL 300 | K23: 5.102 | L23: Manual con Palanca | M23: 3631-RA-16"-T1-0953-N | N23: 4600027788-03631-201CA-00002 | O23: 0
B24: 20 | C24: 4" | D24: VVT | E24: 903 | F24: 4"-VVT-903 | G24: Válvula de Venteo | H24: VÁLVULA DE VENTEO DE DOBLE / TRIPLE EFECTO, CLASE 300 SEGÚN AWWA C512, FLANGES SEGÚN B16.5, FLG, CUERPO PVDF, FLOTADOR EN ESPUMA DE POLIETILENO, TRIM TITANIO ASTM B367 GR2, ASIENTO VITON C. | I24: Refino | J24: CL 300 | K24: 5.102 | L24: N/A | M24: 3631-RA-16"-T1-0953-N | N24: 4600027788-03631-201CA-00002 | O24: 0
B25: 21 | C25: 2" | D25: VBB | E25: 911B | F25: 2"-VBB-911B | G25: Válvula de Bola | H25: VÁLVULA DE BOLA CLASE 300 SEGÚN B16.34, FLANGES SEGÚN B16.5, OPERACIÓN MANUAL, CUERPO TITANIO ASTM B367 GR2, BOLA TITANIO ASTM B367 GR2, TRIM TITANIO ASTM B367 GR2, ASIENTO VITON C. | I25: Refino | J25: CL 300 | K25: 5.102 | L25: Manual con Palanca | M25: 3631-RA-16"-T1-0953-N | N25: 4600027788-03631-201CA-00002 | O25: 0
B26: 22 | C26: 2" | D26: VBB | E26: 912B | F26: 2"-VBB-912B | G26: Válvula de Bola | H26: VÁLVULA DE BOLA CLASE 300 SEGÚN B16.34, FLANGES SEGÚN B16.5, OPERACIÓN MANUAL, CUERPO TITANIO ASTM B367 GR2, BOLA TITANIO ASTM B367 GR2, TRIM TITANIO ASTM B367 GR2, ASIENTO VITON C. | I26: Refino | J26: CL 300 | K26: 5.102 | L26: Manual con Palanca | M26: 3631-RA-16"-T1-0953-N | N26: 4600027788-03631-201CA-00002 | O26: 0
B27: 23 | C27: 2" | D27: VBB | E27: 911 | F27: 2"-VBB-911 | G27: Válvula de Bola | H27: VÁLVULA DE BOLA CLASE 300 SEGÚN B16.34, FLANGES SEGÚN B16.5, OPERACIÓN MANUAL, CUERPO TITANIO ASTM B367 GR2, BOLA TITANIO ASTM B367 GR2, TRIM TITANIO ASTM B367 GR2, ASIENTO VITON C. | I27: Refino | J27: CL 300 | K27: 5.102 | L27: Manual con Palanca | M27: 3631-RA-16"-T1-0953-N | N27: 4600027788-03631-201CA-00002 | O27: 0
B28: 24 | C28: 2" | D28: VBB | E28: 912 | F28: 2"-VBB-912 | G28: Válvula de Bola | H28: VÁLVULA DE BOLA CLASE 300 SEGÚN B16.34, FLANGES SEGÚN B16.5, OPERACIÓN MANUAL, CUERPO TITANIO ASTM B367 GR2, BOLA TITANIO ASTM B367 GR2, TRIM TITANIO ASTM B367 GR2, ASIENTO VITON C. | I28: Refino | J28: CL 300 | K28: 5.102 | L28: Manual con Palanca | M28: 3631-RA-16"-T1-0953-N | N28: 4600027788-03631-201CA-00002 | O28: 0
B29: 25 | C29: 16" | D29: VRC | E29: 903 | F29: 16"-VRC-903 | G29: Valvula de Retención | H29: VÁLVULA DE RETENCIÓN TIPO DUO CHECK ASME B16.34, CL 300 WAFER, PARA FLANGES ASME B16.5, CUERPO Y TRIM TITANIO ASTM B367 GR C2. | I29: Refino | J29: CL 300 | K29: 5.102 | L29: N/A | M29: 3631-RA-16"-T1-0953-N | N29: 4600027788-03631-201CA-00002 | O29: 0
B30: 26 | C30: 2" | D30: VBB | E30: 927 | F30: 2"-VBB-927 | G30: Válvula de Bola | H30: VÁLVULA DE BOLA CLASE 300 SEGÚN B16.34, FLANGES SEGÚN B16.5, OPERACIÓN MANUAL, CUERPO TITANIO ASTM B367 GR2, BOLA TITANIO ASTM B367 GR2, TRIM TITANIO ASTM B367 GR2, ASIENTO VITON C. | I30: Refino | J30: CL 300 | K30: 5.102 | L30: Manual con Palanca | M30: 3631-RA-16"-T1-0953-N | N30: 4600027788-03631-201CA-00002 | O30: 0
B31: 27 | C31: 16" | D31: VMP | E31: 903 | F31: 16"-VMP-903 | G31: Válvula Mariposa | H31: VÁLVULA DE MARIPOSA HIGH PERFOMANCE CLASE 300 SEGÚN B16.34, FLANGES SEGÚN B16.5, LUG, OPERADA POR ENGRANAJE, CUERPO TITANIO ASTM B367 GR C2, DISCO TITANIO ASTM B367 GR2, ASIENTO VITON C. | I31: Refino | J31: CL 300 | K31: 5.102 | L31: Manual con Reductor | M31: 3631-RA-16"-T1-0953-N | N31: 4600027788-03631-201CA-00002 | O31: 0
B32: 28 | C32: 4" | D32: VBB | E32: 904 | F32: 4"-VBB-904 | G32: Válvula de Bola | H32: VÁLVULA DE BOLA CLASE 300 SEGÚN B16.34, FLANGES SEGÚN B16.5, OPERACIÓN MANUAL, CUERPO TITANIO ASTM B367 GR2, BOLA TITANIO ASTM B367 GR2, TRIM TITANIO ASTM B367 GR2, ASIENTO VITON C. | I32: Refino | J32: CL 300 | K32: 5.102 | L32: Manual con Palanca | M32: 3631-RA-16"-T1-0954-N | N32: 4600027788-03631-201CA-00002 | O32: 0
B33: 29 | C33: 4" | D33: VVT | E33: 904 | F33: 4"-VVT-904 | G33: Válvula de Venteo | H33: VÁLVULA DE VENTEO DE DOBLE / TRIPLE EFECTO, CLASE 300 SEGÚN AWWA C512, FLANGES SEGÚN B16.5, FLG, CUERPO PVDF, FLOTADOR EN ESPUMA DE POLIETILENO, TRIM TITANIO ASTM B367 GR2, ASIENTO VITON C. | I33: Refino | J33: CL 300 | K33: 5.102 | L33: N/A | M33: 3631-RA-16"-T1-0954-N | N33: 4600027788-03631-201CA-00002 | O33: 0
B34: 30 | C34: 2" | D34: VBB | E34: 915B | F34: 2"-VBB-915B | G34: Válvula de Bola | H34: VÁLVULA DE BOLA CLASE 300 SEGÚN B16.34, FLANGES SEGÚN B16.5, OPERACIÓN MANUAL, CUERPO TITANIO ASTM B367 GR2, BOLA TITANIO ASTM B367 GR2, TRIM TITANIO ASTM B367 GR2, ASIENTO VITON C. | I34: Refino | J34: CL 300 | K34: 5.102 | L34: Manual con Palanca | M34: 3631-RA-16"-T1-0954-N | N34: 4600027788-03631-201CA-00002 | O34: 0
B35: 31 | C35: 2" | D35: VBB | E35: 916B | F35: 2"-VBB-916B | G35: Válvula de Bola | H35: VÁLVULA DE BOLA CLASE 300 SEGÚN B16.34, FLANGES SEGÚN B16.5, OPERACIÓN MANUAL, CUERPO TITANIO ASTM B367 GR2, BOLA TITANIO ASTM B367 GR2, TRIM TITANIO ASTM B367 GR2, ASIENTO VITON C. | I35: Refino | J35: CL 300 | K35: 5.102 | L35: Manual con Palanca | M35: 3631-RA-16"-T1-0954-N | N35: 4600027788-03631-201CA-00002 | O35: 0
B36: 32 | C36: 2" | D36: VBB | E36: 915 | F36: 2"-VBB-915 | G36: Válvula de Bola | H36: VÁLVULA DE BOLA CLASE 300 SEGÚN B16.34, FLANGES SEGÚN B16.5, OPERACIÓN MANUAL, CUERPO TITANIO ASTM B367 GR2, BOLA TITANIO ASTM B367 GR2, TRIM TITANIO ASTM B367 GR2, ASIENTO VITON C. | I36: Refino | J36: CL 300 | K36: 5.102 | L36: Manual con Palanca | M36: 3631-RA-16"-T1-0954-N | N36: 4600027788-03631-201CA-00002 | O36: 0
B37: 33 | C37: 2" | D37: VBB | E37: 916 | F37: 2"-VBB-916 | G37: Válvula de Bola | H37: VÁLVULA DE BOLA CLASE 300 SEGÚN B16.34, FLANGES SEGÚN B16.5, OPERACIÓN MANUAL, CUERPO TITANIO ASTM B367 GR2, BOLA TITANIO ASTM B367 GR2, TRIM TITANIO ASTM B367 GR2, ASIENTO VITON C. | I37: Refino | J37: CL 300 | K37: 5.102 | L37: Manual con Palanca | M37: 3631-RA-16"-T1-0954-N | N37: 4600027788-03631-201CA-00002 | O37: 0
B38: 34 | C38: 16" | D38: VRC | E38: 904 | F38: 16"-VRC-904 | G38: Valvula de Retención | H38: VÁLVULA DE RETENCIÓN TIPO DUO CHECK ASME B16.34, CL 300 WAFER, PARA FLANGES ASME B16.5, CUERPO Y TRIM TITANIO ASTM B367 GR C2. | I38: Refino | J38: CL 300 | K38: 5.102 | L38: N/A | M38: 3631-RA-16"-T1-0954-N | N38: 4600027788-03631-201CA-00002 | O38: 0
B39: 35 | C39: 2" | D39: VBB | E39: 928 | F39: 2"-VBB-928 | G39: Válvula de Bola | H39: VÁLVULA DE BOLA CLASE 300 SEGÚN B16.34, FLANGES SEGÚN B16.5, OPERACIÓN MANUAL, CUERPO TITANIO ASTM B367 GR2, BOLA TITANIO ASTM B367 GR2, TRIM TITANIO ASTM B367 GR2, ASIENTO VITON C. | I39: Refino | J39: CL 300 | K39: 5.102 | L39: Manual con Palanca | M39: 3631-RA-16"-T1-0954-N | N39: 4600027788-03631-201CA-00002 | O39: 0
B40: 36 | C40: 16" | D40: VMP | E40: 904 | F40: 16"-VMP-904 | G40: Válvula Mariposa | H40: VÁLVULA DE MARIPOSA HIGH PERFOMANCE CLASE 300 SEGÚN B16.34, FLANGES SEGÚN B16.5, LUG, OPERADA POR ENGRANAJE, CUERPO TITANIO ASTM B367 GR C2, DISCO TITANIO ASTM B367 GR2, ASIENTO VITON C. | I40: Refino | J40: CL 300 | K40: 5.102 | L40: Manual con Reductor | M40: 3631-RA-16"-T1-0954-N | N40: 4600027788-03631-201CA-00002 | O40: 0
B41: 37 | C41: 16" | D41: VMP | E41: 901 | F41: 16"-VMP-901 | G41: Válvula Mariposa | H41: VÁLVULA DE MARIPOSA HIGH PERFOMANCE CLASE 150 SEGÚN B16.34, FLANGES SEGÚN B16.5, LUG, OPERADA POR ENGRANAJE, CUERPO TITANIO ASTM B367 GR C2, DISCO TITANIO ASTM B367 GR2, ASIENTO VITON C. | I41: Refino | J41: CL 150 | K41: 1.999 | L41: Manual con Reductor | M41: 3631-RA-400-H1-0956-N | N41: 4600027788-03631-201CA-00002 | O41: 0
B42: 38 | C42: 2" | D42: VBB | E42: 929 | F42: 2"-VBB-929 | G42: Válvula de Bola | H42: VÁLVULA DE BOLA CLASE 300 SEGÚN B16.34, FLANGES SEGÚN B16.5, OPERACIÓN MANUAL, CUERPO TITANIO ASTM B367 GR2, BOLA TITANIO ASTM B367 GR2, TRIM TITANIO ASTM B367 GR2, ASIENTO VITON C. | I42: Refino | J42: CL 300 | K42: 5.102 | L42: Manual con Palanca | M42: 3631-RA-30"-T1-0955-N | N42: 4600027788-03631-201CA-00002 | O42: 0
B43: 39 | C43: 2" | D43: VBB | E43: 930 | F43: 2"-VBB-930 | G43: Válvula de Bola | H43: VÁLVULA DE BOLA CLASE 300 SEGÚN B16.34, FLANGES SEGÚN B16.5, OPERACIÓN MANUAL, CUERPO TITANIO ASTM B367 GR2, BOLA TITANIO ASTM B367 GR2, TRIM TITANIO ASTM B367 GR2, ASIENTO VITON C. | I43: Refino | J43: CL 300 | K43: 5.102 | L43: Manual con Palanca | M43: 3631-RA-30"-T1-0955-N | N43: 4600027788-03631-201CA-00002 | O43: 0
B44: 40 | C44: 24" | D44: VMP | E44: 903 | F44: 24"-VMP-903 | G44: Válvula Mariposa | H44: VÁLVULA DE MARIPOSA HIGH PERFOMANCE CLASE 150 SEGÚN B16.34, FLANGES SEGÚN B16.5, LUG, OPERADA POR ENGRANAJE, CUERPO TITANIO ASTM B367 GR C2, DISCO TITANIO ASTM B367 GR2, ASIENTO VITON C. | I44: Refino | J44: CL 150 | K44: 1.999 | L44: Manual con Reductor | M44: 3631-RA-710-H1-0957-N | N44: 4600027788-03631-201CA-00002 | O44: 0
B45: 41 | C45: 36" | D45: VMP | E45: 901 | F45: 36"-VMP-901 | G45: Válvula Mariposa | H45: VÁLVULA DE MARIPOSA HIGH PERFOMANCE CLASE 150 SEGÚN B16.34, FLANGES SEGÚN B16.47, LUG, OPERADA POR ENGRANAJE, CUERPO TITANIO ASTM B367 GR C2, DISCO TITANIO ASTM B367 GR2, ASIENTO VITON C. | I45: Refino | J45: CL 150 | K45: 1.586 | L45: Manual con Reductor | M45: 3631-RA-900-H3-0958-N | N45: 4600027788-03631-201CA-00002 | O45: 0
B46: 42 | C46: 8" | D46: VBB | E46: 51 | F46: 8"-VBB-051 | G46: Válvula de Bola | H46: VÁLVULA DE BOLA CLASE 150, LUG, SEGÚN B16.34, FLANGES SEGÚN B16.5, OPERACIÓN MANUAL, CUERPO PVDF, BOLA PVDF, ASIENTO VITON, SELLO PTFE, VÁSTAGO TITANIO ASTM B367 GR. 2 | I46: Refino | J46: CL 150 | K46: 1.965 | L46: Manual con Palanca | M46: 3631-RA-900-H3-0958-N | N46: 4600027788-03631-201CA-00002 | O46: 0
B47: 43 | C47: 8" | D47: VVT | E47: 51 | F47: 8" -VVT-051 | G47: Válvula de Venteo | H47: VÁLVULA DE VENTEO DE DOBLE / TRIPLE EFECTO, CLASE 150 SEGÚN AWWA C512, FLANGES SEGÚN B16.5, FLG, CUERPO PVDF, FLOTADOR EN ESPUMA DE POLIETILENO, TRIM TITANIO ASTM B367 GR2, ASIENTO VITON C. | I47: Refino | J47: CL 150 | K47: 1.965 | L47: N/A | M47: 3631-RA-900-H3-0958-N | N47: 4600027788-03631-201CA-00002 | O47: 0
... B72: 68 | C72: 12" | D72: VMP | E72: 908 | F72: 12"-VMP-908 | G72: Válvula Mariposa | H72: VÁLVULA DE MARIPOSA HIGH PERFOMANCE CLASE 150 SEGÚN B16.34, FLANGES SEGÚN B16.5, LUG, OPERADA POR ENGRANAJE, CUERPO TITANIO ASTM B367 GR C2, DISCO TITANIO ASTM B367 GR2, ASIENTO VITON C. | I72: Refino | J72: CL 150 | K72: 1.586 | L72: Manual con Reductor | M72: 3631-RA-315-H3-0912-N | N72: 4600027788-03631-201CA-00003 | O72: 0
B74: Listado Valvulas RCI
S75: Resumen RCI
B76: Item | C76: Ø | D76: Codigo | E76: Correlativo | F76: Tag | G76: Tipo de Valvula | H76: Descripcion | I76: Servicio | J76: Clase ASME/ Rating | K76: Presión de Diseño (kPa) | L76: Accionamiento | M76: N° de Línea | N76: N° P&ID Codelco | O76: Rev | P76: Comentario | R76: Cuenta de Codigo | S76: Etiquetas de columna
B77: 1 | C77: 8" | D77: VGI | E77: 901 | F77: 8"-VGI-901 | G77: Válvula de Compuerta | I77: Agua Contra Incendio (FP) | L77: Manual | M77: 6340-FP-200-H1-0960-N | N77: 4600027788-06340-201CA-00001 | R77: Etiquetas de fila | S77: 1" | T77: 1.1/2" | U77: 10" | V77: 14" | W77: 2" | X77: 2.1/2" | Y77: 3" | Z77: 3/4" | AA77: 4" | AB77: 4” | AC77: 6" | AD77: 8" | AE77: FCV | AF77: PCV | AG77: Total general
B78: 2 | C78: 1.1/2" | D78: VBB | E78: 911 | F78: 1.1/2"-VBB-911 | G78: Válvula de Bola | I78: Agua Contra Incendio (FP) | L78: Manual | M78: 6340-FP-200-H1-0960-N | N78: 4600027788-06340-201CA-00001 | R78: Válvula Angular de Bola | X78: 6 | AG78: 6
B79: 3 | C79: 1.1/2" | D79: VBB | E79: 912 | F79: 1.1/2"-VBB-912 | G79: Válvula de Bola | I79: Agua Contra Incendio (FP) | L79: Manual | M79: 6340-FP-200-H1-0960-N | N79: 4600027788-06340-201CA-00001 | R79: Válvula de Alivio | Z79: 2 | AC79: 2 | AG79: 4
B80: 4 | C80: 1" | D80: VBB | E80: 909 | F80: 1"-VBB-909 | G80: Válvula de Bola | I80: Agua Contra Incendio (FP) | L80: Manual | M80: 6340-FP-200-H6-0961-N | N80: 4600027788-06340-201CA-00001 | R80: Válvula de Bola | S80: 111 | T80: 114 | W80: 2 | AD80: 3 | AG80: 230
B81: 5 | C81: 2" | D81: VBB | E81: 910 | F81: 2"-VBB-910 | G81: Válvula de Bola | I81: Agua Contra Incendio (FP) | L81: Manual | M81: 6340-FP-200-H6-0961-N | N81: 4600027788-06340-201CA-00001 | R81: Válvula de Compuerta | U81: 5 | W81: 1 | Y81: 3 | AC81: 3 | AD81: 1 | AG81: 13
B82: 6 | C82: 8" | D82: VMP | E82: 908 | F82: 8"-VMP-908 | G82: Válvula de Mariposa | I82: Agua Contra Incendio (FP) | L82: Manual | M82: 6340-FP-200-H6-0961-N | N82: 4600027788-06340-201CA-00001 | R82: Válvula de Flotador | AC82: 1 | AG82: 1
B83: 7 | C83: 6" | D83: VDF | E83: 1 | F83: 6"-VDF-001 | G83: Válvula de Flotador | I83: Agua Contra Incendio (FP) | L83: Pilotada | M83: 6340-FP-8"-C2-0971-HC | N83: 4600027788-06340-201CA-00001 | R83: Válvula de Mariposa | T83: 1 | X83: 110 | Y83: 18 | AA83: 6 | AB83: 1 | AD83: 10 | AG83: 146
B84: 8 | C84: 10" | D84: VGI | E84: 902 | F84: 10"-VGI-902 | G84: Válvula de Compuerta | I84: Agua Contra Incendio (FP) | L84: Manual | M84: 6340-FP-10"-C2-0962-N | N84: 4600027788-06340-201CA-00001 | R84: Válvula de Poste | V84: 2 | AC84: 51 | AG84: 53
B85: 9 | C85: 10" | D85: VGI | E85: 1501 | F85: 10"-VGI-1501 | G85: Válvula de Compuerta | I85: Agua Contra Incendio (FP) | L85: Manual | M85: 6340-FP-10"-C2-1501-N | N85: 4600027788-06340-201CA-00001 | R85: Válvula de Retención | AD85: 4 | AG85: 4
B86: 10 | C86: 1.1/2" | D86: VBB | E86: 1501 | F86: 1.1/2"-VBB-1501 | G86: Válvula de Bola | I86: Agua Contra Incendio (FP) | L86: Manual | M86: 6340-FP-10"-C2-1501-N | N86: 4600027788-06340-201CA-00001 | R86: Válvula de Venteo | T86: 26 | AG86: 26
B87: 11 | C87: 1.1/2" | D87: VBB | E87: 1505 | F87: 1.1/2"-VBB-1505 | G87: Válvula de Bola | I87: Agua Contra Incendio (FP) | L87: Manual | M87: 6340-FP-8"-C3-1505-N | N87: 4600027788-06340-201CA-00001 | R87: Válvula Diluvio | AE87: 29 | AF87: 1 | AG87: 30
B88: 12 | C88: 8" | D88: VRC | E88: 1501 | F88: 8"-VRC-1501 | G88: Válvula de Retención | I88: Agua Contra Incendio (FP) | L88: Manual | M88: 6340-FP-8"-C3-1505-N | N88: 4600027788-06340-201CA-00001 | R88: Válvula Reductora de Presión | AF88: 24 | AG88: 24
B89: 13 | C89: 8" | D89: VMP | E89: 1501 | F89: 8"-VMP-1501 | G89: Válvula de Mariposa | I89: Agua Contra Incendio (FP) | L89: Manual | M89: 6340-FP-8"-C3-1505-N | N89: 4600027788-06340-201CA-00001 | R89: Total general | S89: 111 | T89: 141 | U89: 5 | V89: 2 | W89: 3 | X89: 116 | Y89: 21 | Z89: 2 | AA89: 6 | AB89: 1 | AC89: 57 | AD89: 18 | AE89: 29 | AF89: 25 | AG89: 537
B90: 14 | C90: 8" | D90: VMP | E90: 1505 | F90: 8"-VMP-1505 | G90: Válvula de Mariposa | I90: Agua Contra Incendio (FP) | L90: Manual | M90: 6340-FP-8"-C3-1509-N | N90: 4600027788-06340-201CA-00001
B91: 15 | C91: 3/4" | D91: PRV | E91: 1501 | F91: 3/4"-PRV-1501 | G91: Válvula de Alivio | I91: Agua Contra Incendio (FP) | L91: Manual | M91: 6340-FP-8"-C3-1505-N | N91: 4600027788-06340-201CA-00001
B92: 16 | C92: 10" | D92: VGI | E92: 1502 | F92: 10"-VGI-1502 | G92: Válvula de Compuerta | I92: Agua Contra Incendio (FP) | L92: Manual | M92: 6340-FP-10"-C2-1502-N | N92: 4600027788-06340-201CA-00001
B93: 17 | C93: 1.1/2" | D93: VBB | E93: 1502 | F93: 1.1/2"-VBB-1502 | G93: Válvula de Bola | I93: Agua Contra Incendio (FP) | L93: Manual | M93: 6340-FP-10"-C2-1502-N | N93: 4600027788-06340-201CA-00001
B94: 18 | C94: 1.1/2" | D94: VBB | E94: 1506 | F94: 1.1/2"-VBB-1506 | G94: Válvula de Bola | I94: Agua Contra Incendio (FP) | L94: Manual | M94: 6340-FP-8"-C3-1506-N | N94: 4600027788-06340-201CA-00001
B95: 19 | C95: 8" | D95: VRC | E95: 1502 | F95: 8"-VRC-1502 | G95: Válvula de Retención | I95: Agua Contra Incendio (FP) | L95: Manual | M95: 6340-FP-8"-C3-1506-N | N95: 4600027788-06340-201CA-00001
B96: 20 | C96: 8" | D96: VMP | E96: 1502 | F96: 8"-VMP-1502 | G96: Válvula de Mariposa | I96: Agua Contra Incendio (FP) | L96: Manual | M96: 6340-FP-8"-C3-1506-N | N96: 4600027788-06340-201CA-00001
B97: 21 | C97: 8" | D97: VMP | E97: 1506 | F97: 8"-VMP-1506 | G97: Válvula de Mariposa | I97: Agua Contra Incendio (FP) | L97: Manual | M97: 6340-FP-8"-C3-1510-N | N97: 4600027788-06340-201CA-00001
B98: 22 | C98: 6" | D98: PRV | E98: 1502 | F98: 6"-PRV-1502 | G98: Válvula de Alivio | I98: Agua Contra Incendio (FP) | L98: Manual | M98: 6340-FP-8"-C3-1512-N | N98: 4600027788-06340-201CA-00001
B99: 23 | C99: 10" | D99: VGI | E99: 1504 | F99: 10"-VGI-1504 | G99: Válvula de Compuerta | I99: Agua Contra Incendio (FP) | L99: Manual | M99: 6340-FP-2"-C2-1504-N | N99: 4600027788-06340-201CA-00001
B100: 24 | C100: 1.1/2" | D100: VBB | E100: 1504 | F100: 1.1/2"-VBB-1504 | G100: Válvula de Bola | I100: Agua Contra Incendio (FP) | L100: Manual | M100: 6340-FP-2"-C2-1504-N | N100: 4600027788-06340-201CA-00001
B101: 25 | C101: 1.1/2" | D101: VBB | E101: 1508 | F101: 1.1/2"-VBB-1508 | G101: Válvula de Bola | I101: Agua Contra Incendio (FP) | L101: Manual | M101: 6340-FP-1.1/2"-C2-1508-N | N101: 4600027788-06340-201CA-00001
... B145: 69 | C145: PCV | D145: PCV | E145: 20600 | F145: PCV-20600 | G145: Válvula Reductora de Presión | I145: Agua Contra Incendio (FP) | L145: Instrumentación | M145: 6340-FP-4"-C3-1133-N | N145: 4600027788-06340-201CA-00001
B146: 70 | C146: FCV | D146: FCV | E146: 92062A | F146: FCV-92062A | G146: Válvula Diluvio | I146: Agua Contra Incendio (FP) | L146: Instrumentación | M146: 6340-FP-3"-C3-1152-N | N146: 4600027788-06340-201CA-00004
B147: 71 | C147: FCV | D147: FCV | E147: 92062B | F147: FCV-92062B | G147: Válvula Diluvio | I147: Agua Contra Incendio (FP) | L147: Instrumentación | M147: 6340-FP-6"-C3-1153-N | N147: 4600027788-06340-201CA-00004
B148: 72 | C148: 4" | D148: VMP | E148: 920 | F148: 4"-VMP-920 | G148: Válvula de Mariposa | I148: Agua Contra Incendio (FP) | L148: Manual | M148: 6340-FP-4"-C3-0967-N | N148: 4600027788-06340-201CA-00004
B149: 73 | C149: PCV | D149: 20605 | F149: PCV-20605 | G149: Válvula Reductora de Presión | I149: Agua Contra Incendio (FP) | L149: Instrumentación | M149: 6340-FP-4"-C3-0967-N | N149: 4600027788-06340-201CA-00004
B150: 74 | C150: FCV | D150: 920605 | F150: FCV-920605 | G150: Válvula Diluvio | I150: Agua Contra Incendio (FP) | L150: Instrumentación | M150: 6340-FP-3"-C2-0968-N | N150: 4600027788-06340-201CA-00004
B151: 75 | C151: 4" | D151: VMP | F151: 4"-VMP-921 | G151: Válvula de Mariposa | I151: Agua Contra Incendio (FP) | L151: Manual | M151: 6340-FP-4"-C3-0972-N | N151: 4600027788-06340-201CA-00004
B152: 76 | C152: PCV | D152: 20614 | F152: PCV-20614 | G152: Válvula Reductora de Presión | I152: Agua Contra Incendio (FP) | L152: Instrumentación | M152: 6340-FP-4"-C3-0972-N | N152: 4600027788-06340-201CA-00004
B153: 77 | C153: 1.1/2" | D153: VVT | F153: 1.1/2"-VVT-1029 | G153: Válvula de Venteo | I153: Agua Contra Incendio (FP) | L153: Autónoma | M153: 6340-FP-4"-C3-0972-N | N153: 4600027788-06340-201CA-00004
B154: 78 | C154: 1.1/2" | D154: VVT | F154: 1.1/2"-VVT-1058 | G154: Válvula de Bola | I154: Agua Contra Incendio (FP) | L154: Manual | M154: 6340-FP-4"-C3-0972-N | N154: 4600027788-06340-201CA-00004
B155: 79 | C155: 1.1/2" | D155: VVT | F155: 1.1/2"-VVT-1059 | G155: Válvula de Bola | I155: Agua Contra Incendio (FP) | L155: Manual | M155: 6340-FP-4"-C3-0972-N | N155: 4600027788-06340-201CA-00004
B156: 80 | C156: 1.1/2" | D156: VVT | F156: 1.1/2"-VVT-1061 | G156: Válvula de Bola | I156: Agua Contra Incendio (FP) | L156: Manual | M156: 6340-FP-4"-C3-0974-N | N156: 4600027788-06340-201CA-00004
B157: 81 | C157: 1.1/2" | D157: VVT | F157: 1.1/2"-VVT-1063 | G157: Válvula de Bola | I157: Agua Contra Incendio (FP) | L157: Manual | M157: 6340-FP-4"-C3-0973-N | N157: 4600027788-06340-201CA-00004
B158: 82 | C158: PCV | D158: 20606 | F158: PCV-20606 | G158: Válvula Reductora de Presión | I158: Agua Contra Incendio (FP) | L158: Instrumentación | M158: 6340-FP-4"-C5-1136-N | N158: 4600027788-06340-201CA-00003
B159: 83 | C159: FCV | D159: 920623B | F159: FCV-920623B | G159: Válvula Diluvio | I159: Agua Contra Incendio (FP) | L159: Instrumentación | M159: 6360-FP-3"-C3-0973-N | N159: 4600027788-06340-201CA-00004
B160: 84 | C160: FCV | D160: 920606A | F160: FCV-920606A | G160: Válvula Diluvio | I160: Agua Contra Incendio (FP) | L160: Instrumentación | M160: 6360-FP-3"-C3-0974-N | N160: 4600027788-06340-201CA-00004
B161: 85 | C161: FCV | D161: 920607 | F161: FCV-920607 | G161: Válvula Diluvio | I161: Agua Contra Incendio (FP) | L161: Instrumentación | M161: 6340-FP-3"-C2-0976-N | N161: 4600027788-06340-201CA-00004
B162: 86 | C162: 1.1/2" | D162: VBB | F162: 1.1/2"-VBB-1072 | G162: Válvula de Bola | I162: Agua Contra Incendio (FP) | L162: Manual | M162: 6340-FP-2"-C3-1015-N | N162: 4600027788-06340-201CA-00004
B163: 87 | C163: 3" | D163: VMP | F163: 3"-VMP-923 | G163: Válvula de Mariposa | I163: Agua Contra Incendio (FP) | L163: Manual | M163: 6340-FP-3"-C3-0981-HC | N163: 4600027788-06340-201CA-00004
B164: 88 | C164: PCV | D164: 20608 | F164: PCV-20608 | G164: Válvula Reductora de Presión | I164: Agua Contra Incendio (FP) | L164: Instrumentación | M164: 6340-FP-3"-C3-0981-HC | N164: 4600027788-06340-201CA-00004
B165: 89 | C165: 1.1/2" | D165: VVT | F165: 1.1/2"-VVT-1027 | G165: Válvula de Venteo | I165: Agua Contra Incendio (FP) | L165: Autónoma | M165: 6340-FP-3"-C3-0981-HC | N165: 4600027788-06340-201CA-00004
B166: 90 | C166: 1.1/2" | D166: VBB | F166: 1.1/2"-VBB-1054 | G166: Válvula de Bola | I166: Agua Contra Incendio (FP) | L166: Manual | M166: 6340-FP-3"-C3-0981-HC | N166: 4600027788-06340-201CA-00004
B167: 91 | C167: 1.1/2" | D167: VBB | F167: 1.1/2"-VBB-1055 | G167: Válvula de Bola | I167: Agua Contra Incendio (FP) | L167: Manual | M167: 6340-FP-3"-C3-0981-HC | N167: 4600027788-06340-201CA-00004
B168: 92 | C168: 1.1/2" | D168: VBB | F168: 1.1/2"-VBB-1057 | G168: Válvula de Bola | I168: Agua Contra Incendio (FP) | L168: Manual | M168: 6340-FP-3"-C3-0983-N | N168: 4600027788-06340-201CA-00004
B169: 93 | C169: FCV | D169: 920951 | F169: FCV-920951 | G169: Válvula Diluvio | I169: Agua Contra Incendio (FP) | L169: Autónoma | M169: 6360-FP-3"-C3-0983-N | N169: 4600027788-06340-201CA-00004
B170: 94 | C170: 3" | D170: VMP | F170: 3"-VMP-924 | G170: Válvula de Mariposa | I170: Agua Contra Incendio (FP) | L170: Manual | M170: 6340-FP-3"-C5-0984-N | N170: 4600027788-06340-201CA-00004
...

Sheet Volumen_Obra
B2: 2.1 | C2: MANEJO RIPIOS
B3: 2.2 | C3: REGADIO LIXIVIACION SECUNDARIA
B4: 2.3 | C4: MANEJO DE SOLUCIONES PLS
B5: 2.4 | C5: CONDUCCION
B6: 2.5 | C6: SISTEMA CONTRA INCENDIO
B7: 2.6 | C7: RECEPCION Y SUMINISTRO ENERGIA ELECTRICA
H8: =SUBTOTAL(9,H10:H704) -> 19288.671
B9: Ítem | C9: AREA | D9: APORTES | E9: DESCRIPCION | F9: UNID | G9: CANT | H9: POM
B10: 2.1.1.1.1 | C10: MANEJO RIPIOS | D10: PPC | E10: Emplantillado G-10 | F10: m3 | G10: 17 | H10: =SUMIFS(Itemizado_Piping!$O$5:$O$93,Itemizado_Piping!$C$5:$C$93,Volumen_Obra!B10) -> 0
B11: 2.1.1.1.2 | C11: MANEJO RIPIOS | D11: PPC | E11: Hormigón Fundaciones, Muro y Radier G-25 | F11: m3 | G11: 140 | H11: =SUMIFS(Itemizado_Piping!$O$5:$O$93,Itemizado_Piping!$C$5:$C$93,Volumen_Obra!B11) -> 0
B12: 2.1.1.1.3 | C12: MANEJO RIPIOS | D12: PPC | E12: Acero de refuerzo A630-420H | F12: kg | G12: 8920 | H12: =SUMIFS(Itemizado_Piping!$O$5:$O$93,Itemizado_Piping!$C$5:$C$93,Volumen_Obra!B12) -> 0
B13: 2.1.1.1.4 | C13: MANEJO RIPIOS | D13: PPC | E13: Excavación estructural (incluye excavación malla a tierra) | F13: m3 | G13: 529 | H13: =SUMIFS(Itemizado_Piping!$O$5:$O$93,Itemizado_Piping!$C$5:$C$93,Volumen_Obra!B13) -> 0
B14: 2.1.1.1.5 | C14: MANEJO RIPIOS | D14: PPC | E14: Relleno estructural compactado (incluye relleno malla a tierra) | F14: m3 | G14: 417 | H14: =SUMIFS(Itemizado_Piping!$O$5:$O$93,Itemizado_Piping!$C$5:$C$93,Volumen_Obra!B14) -> 0
B15: 2.1.1.10.1 | C15: MANEJO RIPIOS | D15: PPC | E15: Suministro e Instalación Conductor desnudo blando, clase B, 19 hebras N° 2/0 AWG | F15: m | G15: 120 | H15: =SUMIFS(Itemizado_Piping!$O$5:$O$93,Itemizado_Piping!$C$5:$C$93,Volumen_Obra!B15) -> 0
B16: 2.1.1.10.2 | C16: MANEJO RIPIOS | D16: PPC | E16: Suministro e Instalación Conductor desnudo blando, clase B, 19 hebras N° 4/0 AWG | F16: m | G16: 560 | H16: =SUMIFS(Itemizado_Piping!$O$5:$O$93,Itemizado_Piping!$C$5:$C$93,Volumen_Obra!B16) -> 0
B17: 2.1.1.10.3 | C17: MANEJO RIPIOS | D17: PPC | E17: Suministro y Montaje de cámaras de registro | F17: uni | G17: 4 | H17: =SUMIFS(Itemizado_Piping!$O$5:$O$93,Itemizado_Piping!$C$5:$C$93,Volumen_Obra!B17) -> 0
B18: 2.1.1.10.4 | C18: MANEJO RIPIOS | D18: PPC | E18: Suministro y Montaje de GEL para mejoramiento de resistividad de suelo (Sacos de 14kilos) | F18: uni | G18: 280 | H18: =SUMIFS(Itemizado_Piping!$O$5:$O$93,Itemizado_Piping!$C$5:$C$93,Volumen_Obra!B18) -> 0
B19: 2.1.1.10.5 | C19: MANEJO RIPIOS | D19: PPC | E19: Suministro e Instalación Cables, canalizaciones y materiales menores | F19: gl | G19: 1 | H19: =SUMIFS(Itemizado_Piping!$O$5:$O$93,Itemizado_Piping!$C$5:$C$93,Volumen_Obra!B19) -> 0
B20: 2.1.1.10.6 | C20: MANEJO RIPIOS | D20: PPC | E20: Construcción Malla puesta a tierra: moldes soldadura termofusión, cámara de registro, etc. | F20: gl | G20: 1 | H20: =SUMIFS(Itemizado_Piping!$O$5:$O$93,Itemizado_Piping!$C$5:$C$93,Volumen_Obra!B20) -> 0
B21: 2.1.1.11.1 | C21: MANEJO RIPIOS | D21: PPD | E21: Montaje, conexionado de estación GPS repetidora 03622-ZT-1000 de acuerdo a puntos topográficos que se indicarán. incluye su infraestructura civil (para que termine en base de hormigón) de acuerdo a plano 4600020303-06700-221AT-00002. | F21: uni | G21: 1 | H21: =SUMIFS(Itemizado_Piping!$O$5:$O$93,Itemizado_Piping!$C$5:$C$93,Volumen_Obra!B21) -> 0
... B43: 2.1.1.2.6 | C43: MANEJO RIPIOS | D43: PPD | E43: Suministro y Montaje de Barandas de acceso para la Sala Eléctrica | F43: m | G43: 70 | H43: =SUMIFS(Itemizado_Piping!$O$5:$O$93,Itemizado_Piping!$C$5:$C$93,Volumen_Obra!B43) -> 0
B44: 2.1.1.3.1 | D44: PPD | E44: Montaje Sala Eléctrica prefabricada 27 x 6 x 3,5 m - 220-SEL-011 | F44: uni | G44: 1 | H44: =SUMIFS(Itemizado_Piping!$O$5:$O$93,Itemizado_Piping!$C$5:$C$93,Volumen_Obra!B44) -> 0
B45: 2.1.1.3.2 | D45: PPD | E45: Montaje Equipo Aire Acondicionado, Exterior | F45: uni | G45: 1 | H45: =SUMIFS(Itemizado_Piping!$O$5:$O$93,Itemizado_Piping!$C$5:$C$93,Volumen_Obra!B45) -> 0
B46: 2.1.1.3.3 | D46: PPD | E46: Montaje Ducto de Barras MT de 3000A | F46: uni | G46: 1 | H46: =SUMIFS(Itemizado_Piping!$O$5:$O$93,Itemizado_Piping!$C$5:$C$93,Volumen_Obra!B46) -> 0
B47: 2.1.1.3.4 | D47: PPD | E47: Montaje Sistema Sobrepresión, Exterior | F47: uni | G47: 1 | H47: =SUMIFS(Itemizado_Piping!$O$5:$O$93,Itemizado_Piping!$C$5:$C$93,Volumen_Obra!B47) -> 0
B48: 2.1.1.3.5 | D48: PPD | E48: Montaje Resistencia de Puesta a Tierra, Exterior | F48: uni | G48: 1 | H48: =SUMIFS(Itemizado_Piping!$O$5:$O$93,Itemizado_Piping!$C$5:$C$93,Volumen_Obra!B48) -> 0
B49: 2.1.1.3.6 | D49: PPD | E49: Montaje Transformador 10/13 MVA,KNAN KNAF 23/4,16 kV, Exterior | F49: uni | G49: 1 | H49: =SUMIFS(Itemizado_Piping!$O$5:$O$93,Itemizado_Piping!$C$5:$C$93,Volumen_Obra!B49) -> 0
B50: 2.1.1.3.7 | D50: PPD | E50: Montaje Transformador 300 KVA de 4,16/0,6 kV, Exterior | F50: uni | G50: 1 | H50: =SUMIFS(Itemizado_Piping!$O$5:$O$93,Itemizado_Piping!$C$5:$C$93,Volumen_Obra!B50) -> 0
B51: 2.1.1.3.8 | D51: PPD | E51: Montaje Transformador 150 KVA de 600/400-231 V, Exterior | F51: uni | G51: 1 | H51: =SUMIFS(Itemizado_Piping!$O$5:$O$93,Itemizado_Piping!$C$5:$C$93,Volumen_Obra!B51) -> 0
B52: 2.1.1.3.9 | D52: PPD | E52: Montaje Celda GIS a piso 23kV, y apoyo en puesta marcha | F52: uni | G52: 2 | H52: =SUMIFS(Itemizado_Piping!$O$5:$O$93,Itemizado_Piping!$C$5:$C$93,Volumen_Obra!B52) -> 0
B53: 2.1.1.4.1 | D53: PPC | E53: Construcción Cámara Eléctrica de hormigón 2000x2000x2400 mm con tapa | F53: un | G53: 8 | H53: =SUMIFS(Itemizado_Piping!$O$5:$O$93,Itemizado_Piping!$C$5:$C$93,Volumen_Obra!B53) -> 0
B54: 2.1.1.4.2 | D54: PPC | E54: Construcción Banco de Ductos reforzado para tránsito pesado de 1610x1100 mm | F54: m | G54: 93 | H54: =SUMIFS(Itemizado_Piping!$O$5:$O$93,Itemizado_Piping!$C$5:$C$93,Volumen_Obra!B54) -> 0
B55: 2.1.1.4.3 | D55: PPC | E55: Construcción Banco de Ductos reforzado para tránsito pesado de 600x600 mm | F55: m | G55: 252 | H55: =SUMIFS(Itemizado_Piping!$O$5:$O$93,Itemizado_Piping!$C$5:$C$93,Volumen_Obra!B55) -> 0
... B495: 2.6.1.2.5 | D495: PPC | E495: Construcción Cámara Eléctrica de hormigón 2000x2000x2400 mm | F495: un | G495: 4 | H495: =SUMIFS(Itemizado_Piping!$O$5:$O$93,Itemizado_Piping!$C$5:$C$93,Volumen_Obra!B495) -> 0
B496: 3.1.1 | E496: Bulldozer semi-U 9,4m3 (D8) | F496: HM | G496: 150 | H496: =SUMIFS(Itemizado_Piping!$O$5:$O$93,Itemizado_Piping!$C$5:$C$93,Volumen_Obra!B496) -> 0
B497: 3.1.10 | E497: Torre de iluminación | F497: HM | G497: 500 | H497: =SUMIFS(Itemizado_Piping!$O$5:$O$93,Itemizado_Piping!$C$5:$C$93,Volumen_Obra!B497) -> 0
B498: 3.1.11 | E498: Generador | F498: HM | G498: 800 | H498: =SUMIFS(Itemizado_Piping!$O$5:$O$93,Itemizado_Piping!$C$5:$C$93,Volumen_Obra!B498) -> 0
B499: 3.1.12 | E499: Camión Plano | F499: HM | G499: 500 | H499: =SUMIFS(Itemizado_Piping!$O$5:$O$93,Itemizado_Piping!$C$5:$C$93,Volumen_Obra!B499) -> 0
B500: 3.1.13 | E500: Grúa Horquilla | F500: HM | G500: 300 | H500: =SUMIFS(Itemizado_Piping!$O$5:$O$93,Itemizado_Piping!$C$5:$C$93,Volumen_Obra!B500) -> 0
B501: 3.1.14 | E501: Cuadrilla Distintas especialidades | F501: HH | G501: 5000 | H501: =SUMIFS(Itemizado_Piping!$O$5:$O$93,Itemizado_Piping!$C$5:$C$93,Volumen_Obra!B501) -> 0
B502: 3.1.2 | E502: Cargador frontal (2,6 m3) | F502: HM | G502: 500 | H502: =SUMIFS(Itemizado_Piping!$O$5:$O$93,Itemizado_Piping!$C$5:$C$93,Volumen_Obra!B502) -> 0
B503: 3.1.3 | E503: Camión Tolva 20 m3 | F503: HM | G503: 500 | H503: =SUMIFS(Itemizado_Piping!$O$5:$O$93,Itemizado_Piping!$C$5:$C$93,Volumen_Obra!B503) -> 0
B504: 3.1.4 | E504: Camión Aljibe 20 m3 | F504: HM | G504: 1000 | H504: =SUMIFS(Itemizado_Piping!$O$5:$O$93,Itemizado_Piping!$C$5:$C$93,Volumen_Obra!B504) -> 0
B505: 3.1.5 | E505: Motoniveladora (hoja 14") | F505: HM | G505: 500 | H505: =SUMIFS(Itemizado_Piping!$O$5:$O$93,Itemizado_Piping!$C$5:$C$93,Volumen_Obra!B505) -> 0
B506: 3.1.6 | E506: Rodillo Vibradores Autopropulsados 10 Ton | F506: HM | G506: 350 | H506: =SUMIFS(Itemizado_Piping!$O$5:$O$93,Itemizado_Piping!$C$5:$C$93,Volumen_Obra!B506) -> 0
B507: 3.1.7 | E507: Camión Cama Baja | F507: HM | G507: 500 | H507: =SUMIFS(Itemizado_Piping!$O$5:$O$93,Itemizado_Piping!$C$5:$C$93,Volumen_Obra!B507) -> 0
... B511: 4.2 | E511: Seguro Complementario de Salud | F511: gl | G511: 1 | H511: =SUMIFS(Itemizado_Piping!$O$5:$O$93,Itemizado_Piping!$C$5:$C$93,Volumen_Obra!B511) -> 0
B512: 2.1 | C512: MANEJO RIPIOS | E512: Manejo de Ripios | H512: =SUMIFS(Itemizado_Piping!$O$5:$O$93,Itemizado_Piping!$C$5:$C$93,Volumen_Obra!B512) -> 0
B513: 2.2 | C513: REGADIO LIXIVIACION SECUNDARIA | E513: Regadío Lixiviación Secundaria | H513: =SUMIFS(Itemizado_Piping!$O$5:$O$93,Itemizado_Piping!$C$5:$C$93,Volumen_Obra!B513) -> 0
B514: 2.2.2 | C514: LINEAS DE RIEGO | E514: Líneas de Riego | H514: =SUMIFS(Itemizado_Piping!$O$5:$O$93,Itemizado_Piping!$C$5:$C$93,Volumen_Obra!B514) -> 0
B515: 2.2.2.2 | C515: LINEAS DE RIEGO | E515: Piping | H515: =SUMIFS(Itemizado_Piping!$O$5:$O$93,Itemizado_Piping!$C$5:$C$93,Volumen_Obra!B515) -> 0
B516: 2.2.2.2.1 | C516: LINEAS DE RIEGO | D516: PPD | E516: Tie-In 3631-001 Cañería HDPE 1000 mm | F516: gl | G516: 1 | H516: =SUMIFS(Itemizado_Piping!$O$5:$O$93,Itemizado_Piping!$C$5:$C$93,Volumen_Obra!B516) -> 1
B517: 2.2.2.2.10 | C517: LINEAS DE RIEGO | D517: PPD | E517: Instalación Cañería titanio gr. 2 sch 10S soldada diámetro 6" | F517: m | G517: 16 | H517: =SUMIFS(Itemizado_Piping!$O$5:$O$93,Itemizado_Piping!$C$5:$C$93,Volumen_Obra!B517) -> 0
B518: 2.2.2.2.11 | C518: LINEAS DE RIEGO | D518: PPD | E518: Instalación Cañería titanio gr. 2 sch 10S soldada diámetro 12" | F518: m | G518: 5 | H518: =SUMIFS(Itemizado_Piping!$O$5:$O$93,Itemizado_Piping!$C$5:$C$93,Volumen_Obra!B518) -> 5
B519: 2.2.2.2.12 | C519: LINEAS DE RIEGO | D519: PPD | E519: Instalación Cañería titanio gr. 2 sch 10S soldada diámetro 16" | F519: m | G519: 13 | H519: =SUMIFS(Itemizado_Piping!$O$5:$O$93,Itemizado_Piping!$C$5:$C$93,Volumen_Obra!B519) -> 18
B520: 2.2.2.2.13 | C520: LINEAS DE RIEGO | D520: PPD | E520: Instalación Cañería titanio gr. 2 sch 10S soldada diámetro 24" | F520: m | G520: 13 | H520: =SUMIFS(Itemizado_Piping!$O$5:$O$93,Itemizado_Piping!$C$5:$C$93,Volumen_Obra!B520) -> 12
B521: 2.2.2.2.14 | C521: LINEAS DE RIEGO | D521: PPD | E521: Instalación Cañería titanio gr. 2 sch 10S soldada diámetro 28" | F521: m | G521: 3 | H521: =SUMIFS(Itemizado_Piping!$O$5:$O$93,Itemizado_Piping!$C$5:$C$93,Volumen_Obra!B521) -> 3.4
B522: 2.2.2.2.15 | C522: LINEAS DE RIEGO | D522: PPD | E522: Instalación Cañería titanio gr. 2 sch 10S soldada diámetro 30" | F522: m | G522: 15 | H522: =SUMIFS(Itemizado_Piping!$O$5:$O$93,Itemizado_Piping!$C$5:$C$93,Volumen_Obra!B522) -> 15.57
B523: 2.2.2.2.16 | C523: LINEAS DE RIEGO | D523: PPD | E523: Instalación Cañería titanio gr. 2 sch 10S soldada diámetro 36" | F523: m | G523: 6 | H523: =SUMIFS(Itemizado_Piping!$O$5:$O$93,Itemizado_Piping!$C$5:$C$93,Volumen_Obra!B523) -> 6
B524: 2.2.2.2.17 | C524: LINEAS DE RIEGO | D524: PPC | E524: Instalación Cañería HDPE PN16 H3 110 mm | F524: m | G524: 1 | H524: =SUMIFS(Itemizado_Piping!$O$5:$O$93,Itemizado_Piping!$C$5:$C$93,Volumen_Obra!B524) -> 13.149
B525: 2.2.2.2.18 | C525: LINEAS DE RIEGO | D525: PPC | E525: Instalación Cañería HDPE PN16 H1 710 mm | F525: m | G525: 1241 | H525: =SUMIFS(Itemizado_Piping!$O$5:$O$93,Itemizado_Piping!$C$5:$C$93,Volumen_Obra!B525) -> 184.75
B526: 2.2.2.2.19 | C526: LINEAS DE RIEGO | D526: PPC | E526: Instalación Cañería HDPE PN16 H3 900 mm | F526: m | G526: 1450 | H526: =SUMIFS(Itemizado_Piping!$O$5:$O$93,Itemizado_Piping!$C$5:$C$93,Volumen_Obra!B526) -> 1560
B527: 2.2.2.2.2 | C527: LINEAS DE RIEGO | D527: PPD | E527: Tie-In 3631-002 Cañería HDPE 710 mm | F527: gl | G527: 1 | H527: =SUMIFS(Itemizado_Piping!$O$5:$O$93,Itemizado_Piping!$C$5:$C$93,Volumen_Obra!B527) -> 1
... B553: 2.2.2.2.9 | C553: LINEAS DE RIEGO | D553: PPD | E553: Instalación Cañería titanio gr. 2 sch 10S soldada diámetro 4" | F553: m | G553: 4 | H553: =SUMIFS(Itemizado_Piping!$O$5:$O$93,Itemizado_Piping!$C$5:$C$93,Volumen_Obra!B553) -> 4
B554: 2.3 | C554: MANEJO DE SOLUCIONES PLS | E554: Manejo de Soluciones PLS (Piscinas, Canaletas y Pozos de Traspaso) | H554: =SUMIFS(Itemizado_Piping!$O$5:$O$93,Itemizado_Piping!$C$5:$C$93,Volumen_Obra!B554) -> 0
B555: 2.3.1 | C555: MANEJO DE SOLUCIONES PLS | E555: Sentina Piscina OBL (Refino) | H555: =SUMIFS(Itemizado_Piping!$O$5:$O$93,Itemizado_Piping!$C$5:$C$93,Volumen_Obra!B555) -> 0
B556: 2.3.2 | C556: Piscina de Emergencia | E556: Piscina de Emergencia | H556: =SUMIFS(Itemizado_Piping!$O$5:$O$93,Itemizado_Piping!$C$5:$C$93,Volumen_Obra!B556) -> 0
B557: 2.3.2.8 | C557: Piscina de Emergencia | E557: Cañerías | H557: =SUMIFS(Itemizado_Piping!$O$5:$O$93,Itemizado_Piping!$C$5:$C$93,Volumen_Obra!B557) -> 0
B558: 2.3.2.8.1 | C558: Piscina de Emergencia | D558: PPC | E558: Suministro e Instalación Cañería titanio gr. 2 sch 10S sin costura diámetro 2" | F558: m | G558: 1 | H558: =SUMIFS(Itemizado_Piping!$O$5:$O$93,Itemizado_Piping!$C$5:$C$93,Volumen_Obra!B558) -> 0
B559: 2.3.2.8.10 | C559: Piscina de Emergencia | D559: PPD | E559: Instalación Válvula bola 2" clase 150 titanio | F559: uni | G559: 8 | H559: =SUMIFS(Itemizado_Piping!$O$5:$O$93,Itemizado_Piping!$C$5:$C$93,Volumen_Obra!B559) -> 0
B560: 2.3.2.8.11 | C560: Piscina de Emergencia | D560: PPD | E560: Instalación Válvula bola 4" clase 150 titanio | F560: uni | G560: 2 | H560: =SUMIFS(Itemizado_Piping!$O$5:$O$93,Itemizado_Piping!$C$5:$C$93,Volumen_Obra!B560) -> 0
B561: 2.3.2.8.12 | C561: Piscina de Emergencia | D561: PPD | E561: Instalación Válvula mariposa 4" clase 150 titanio | F561: uni | G561: 1 | H561: =SUMIFS(Itemizado_Piping!$O$5:$O$93,Itemizado_Piping!$C$5:$C$93,Volumen_Obra!B561) -> 0
B562: 2.3.2.8.13 | C562: Piscina de Emergencia | D562: PPD | E562: Instalación Válvula mariposa 14" clase 150 titanio | F562: uni | G562: 4 | H562: =SUMIFS(Itemizado_Piping!$O$5:$O$93,Itemizado_Piping!$C$5:$C$93,Volumen_Obra!B562) -> 0
B563: 2.3.2.8.14 | C563: Piscina de Emergencia | D563: PPD | E563: Instalación Válvula check 14" clase 300 titanio | F563: uni | G563: 2 | H563: =SUMIFS(Itemizado_Piping!$O$5:$O$93,Itemizado_Piping!$C$5:$C$93,Volumen_Obra!B563) -> 0
B564: 2.3.2.8.15 | C564: Piscina de Emergencia | D564: PPD | E564: Instalación Válvula ventosa 4" titanio | F564: uni | G564: 2 | H564: =SUMIFS(Itemizado_Piping!$O$5:$O$93,Itemizado_Piping!$C$5:$C$93,Volumen_Obra!B564) -> 2
B565: 2.3.2.8.16 | C565: Piscina de Emergencia | D565: PPD | E565: Instalación Válvula mariposa 36" clase 150 titanio | F565: uni | G565: 2 | H565: =SUMIFS(Itemizado_Piping!$O$5:$O$93,Itemizado_Piping!$C$5:$C$93,Volumen_Obra!B565) -> 0
B566: 2.3.2.8.17 | C566: Piscina de Emergencia | D566: PPD | E566: Fitting | F566: gl | G566: 1 | H566: =SUMIFS(Itemizado_Piping!$O$5:$O$93,Itemizado_Piping!$C$5:$C$93,Volumen_Obra!B566) -> 1
B567: 2.3.2.8.2 | C567: Piscina de Emergencia | D567: PPD | E567: Instalación Cañería titanio gr. 2 sch 10S soldada diámetro 4" | F567: m | G567: 2 | H567: =SUMIFS(Itemizado_Piping!$O$5:$O$93,Itemizado_Piping!$C$5:$C$93,Volumen_Obra!B567) -> 0
B568: 2.3.2.8.3 | C568: Piscina de Emergencia | D568: PPD | E568: Instalación Cañería titanio gr. 2 sch 10S soldada diámetro 10" | F568: m | G568: 3 | H568: =SUMIFS(Itemizado_Piping!$O$5:$O$93,Itemizado_Piping!$C$5:$C$93,Volumen_Obra!B568) -> 0
B569: 2.3.2.8.4 | C569: Piscina de Emergencia | D569: PPD | E569: Instalación Cañería titanio gr. 2 sch 10S soldada diámetro 14" | F569: m | G569: 3 | H569: =SUMIFS(Itemizado_Piping!$O$5:$O$93,Itemizado_Piping!$C$5:$C$93,Volumen_Obra!B569) -> 2.55
... B574: 2.3.2.8.9 | C574: Piscina de Emergencia | D574: PPD | E574: Tie-In 3632-002 Cañería HDPE 800 mm | F574: gl | G574: 1 | H574: =SUMIFS(Itemizado_Piping!$O$5:$O$93,Itemizado_Piping!$C$5:$C$93,Volumen_Obra!B574) -> 0
B575: 2.5 | C575: Sistema Contra Incendio Completo | E575: Sistema Contra Incendio Completo | H575: =SUMIFS(Itemizado_Piping!$O$5:$O$93,Itemizado_Piping!$C$5:$C$93,Volumen_Obra!B575) -> 0
B576: 2.5.1 | C576: Sistema Contra Incendio Completo | E576: Suministro y montaje Sistemas de Detección, Alarma y Combate de incendio | H576: =SUMIFS(Itemizado_Piping!$O$5:$O$93,Itemizado_Piping!$C$5:$C$93,Volumen_Obra!B576) -> 0
B577: 2.5.1.2 | C577: Sistema Contra Incendio Completo | E577: Piping, Suministro e instalación | H577: =SUMIFS(Itemizado_Piping!$O$5:$O$93,Itemizado_Piping!$C$5:$C$93,Volumen_Obra!B577) -> 0
B578: 2.5.1.2.1 | C578: Sistema Contra Incendio Completo | D578: PPC | E578: Suministro e Instalación Válvula Tipo Diluvio de Diámetro 6" de Accionamiento Automático y Manual 6" clase 300 | F578: un | G578: 16 | H578: =SUMIFS(Itemizado_Piping!$O$5:$O$93,Itemizado_Piping!$C$5:$C$93,Volumen_Obra!B578) -> 0
B579: 2.5.1.2.10 | C579: Sistema Contra Incendio Completo | D579: PPC | E579: Suministro e Instalación Boquillas Abiertas de Accionamiento Automático/Manual. Material de cuerpo ASTM A-743, Coberturas Generales clase 300 | F579: un | G579: 144 | H579: =SUMIFS(Itemizado_Piping!$O$5:$O$93,Itemizado_Piping!$C$5:$C$93,Volumen_Obra!B579) -> 287
B580: 2.5.1.2.11 | C580: Sistema Contra Incendio Completo | D580: PPC | E580: Suministro e Instalación Boquillas Abiertas de Accionamiento Automático/Manual. Material de cuerpo ASTM A-743, Transformador clase 300 | F580: un | G580: 12 | H580: =SUMIFS(Itemizado_Piping!$O$5:$O$93,Itemizado_Piping!$C$5:$C$93,Volumen_Obra!B580) -> 72
B581: 2.5.1.2.12 | C581: Sistema Contra Incendio Completo | D581: PPC | E581: Suministro e Instalación Rociadores Automáticos (Bulbo), Material cuerpo de Bronce | F581: un | G581: 422 | H581: =SUMIFS(Itemizado_Piping!$O$5:$O$93,Itemizado_Piping!$C$5:$C$93,Volumen_Obra!B581) -> 136
B582: 2.5.1.2.13 | C582: Sistema Contra Incendio Completo | D582: PPD | E582: Instalación Tubería Acero ASTM A53 Gr.B Sch Std 14" | F582: m | G582: 2000 | H582: =SUMIFS(Itemizado_Piping!$O$5:$O$93,Itemizado_Piping!$C$5:$C$93,Volumen_Obra!B582) -> 2411.64
B583: 2.5.1.2.14 | C583: Sistema Contra Incendio Completo | D583: PPD | E583: Instalación Tubería Acero ASTM A53 Gr.B Sch Std 12" | F583: m | G583: 2250 | H583: =SUMIFS(Itemizado_Piping!$O$5:$O$93,Itemizado_Piping!$C$5:$C$93,Volumen_Obra!B583) -> 3072.993
B584: 2.5.1.2.15 | C584: Sistema Contra Incendio Completo | D584: PPD | E584: Instalación Tubería Acero ASTM A53 Gr.B Sch Std 6" | F584: m | G584: 1200 | H584: =SUMIFS(Itemizado_Piping!$O$5:$O$93,Itemizado_Piping!$C$5:$C$93,Volumen_Obra!B584) -> 587.085
B585: 2.5.1.2.16 | C585: Sistema Contra Incendio Completo | D585: PPD | E585: Instalación Tubería de HDPE PE 3608 14" | F585: m | G585: 1180 | H585: =SUMIFS(Itemizado_Piping!$O$5:$O$93,Itemizado_Piping!$C$5:$C$93,Volumen_Obra!B585) -> 0
B586: 2.5.1.2.17 | C586: Sistema Contra Incendio Completo | D586: PPD | E586: Instalación Tubería de HDPE PE 20 DE 8" | F586: m | G586: 3400 | H586: =SUMIFS(Itemizado_Piping!$O$5:$O$93,Itemizado_Piping!$C$5:$C$93,Volumen_Obra!B586) -> 3204
B587: 2.5.1.2.18 | C587: Sistema Contra Incendio Completo | D587: PPC | E587: Suministro e Instalación Fitting de Acero | F587: gl | G587: 1 | H587: =SUMIFS(Itemizado_Piping!$O$5:$O$93,Itemizado_Piping!$C$5:$C$93,Volumen_Obra!B587) -> 1
B588: 2.5.1.2.19 | C588: Sistema Contra Incendio Completo | D588: PPD | E588: Suministro e Instalación Fitting de HDPE | F588: gl | G588: 1 | H588: =SUMIFS(Itemizado_Piping!$O$5:$O$93,Itemizado_Piping!$C$5:$C$93,Volumen_Obra!B588) -> 1
B589: 2.5.1.2.2 | C589: Sistema Contra Incendio Completo | D589: PPC | E589: Suministro e Instalación Válvula OS&Y de tipo Vástago Ascendente, Diámetro 4" para Hidrantes. De accionamiento Manual 4" clase 150 | F589: un | G589: 80 | H589: =SUMIFS(Itemizado_Piping!$O$5:$O$93,Itemizado_Piping!$C$5:$C$93,Volumen_Obra!B589) -> 0
... B601: 2.5.1.2.9 | C601: Sistema Contra Incendio Completo | D601: PPC | E601: Suministro e Instalación Gabinete de Mangueras de Diámetro 1 1/2" de Accionamiento Manual 1,5" clase 150 | F601: un | G601: 18 | H601: =SUMIFS(Itemizado_Piping!$O$5:$O$93,Itemizado_Piping!$C$5:$C$93,Volumen_Obra!B601) -> 52
B602: 2.0 | E602: OBRAS CONSTRUCCIÓN (Serie de Precio Unitario c/ Utilidad) | H602: =SUMIFS(Itemizado_Piping!$O$5:$O$93,Itemizado_Piping!$C$5:$C$93,Volumen_Obra!B602) -> 0
B603: 2.1.1 | C603: MANEJO RIPIOS | E603: Sala Eléctrica Transporte de Ripios | H603: =SUMIFS(Itemizado_Piping!$O$5:$O$93,Itemizado_Piping!$C$5:$C$93,Volumen_Obra!B603) -> 0
B604: 2.1.1.1 | E604: OOCC Sala Eléctrica (incluye suministros) | H604: =SUMIFS(Itemizado_Piping!$O$5:$O$93,Itemizado_Piping!$C$5:$C$93,Volumen_Obra!B604) -> 0
...

Sheet POM Y AVANCE
C2: MONTO CONTRATO | O2: =O3+O9+O16 -> 12904186214 | P2: =P3+P9+P16 -> 1.9523797e+10 | Q2: =Q3+Q9+Q16 -> 2.6323838e+09 | R2: =R3+R9+R16 -> 4.6030447e+09 | S2: =S3+S9+S16 -> 1.4189319e+10 | T2: =T3+T9+T16 -> 5.3852731e+10 | W2: =W3+W9+W16 -> 12904186214 | X2: =X3+X9+X16 -> 1.9523797e+10 | Y2: =Y3+Y9+Y16 -> 2.6323838e+09 | Z2: =Z3+Z9+Z16 -> 4.6030447e+09 | AA2: =AA3+AA9+AA16 -> 1.298824e+10 | AB2: =AB3+AB9+AB16 -> 5.2651652e+10 | AE2: =AE3+AE9+AE16 -> 0 | AF2: =AF3+AF9+AF16 -> 0 | AG2: =AG3+AG9+AG16 -> 0 | AH2: =AH3+AH9+AH16 -> 0 | AI2: =AI3+AI9+AI16 -> 0 | AJ2: =AJ3+AJ9+AJ16 -> 0 | AQ2: =AQ3+AQ9+AQ16 -> 1.4000666e+09
C3: COSTO INDIRECTO | O3: =SUM(O4:O8) -> 305200000 | P3: =SUM(P4:P8) -> 0 | Q3: =SUM(Q4:Q8) -> 0 | R3: =SUM(R4:R8) -> 0 | S3: =SUM(S4:S8) -> 1.4189319e+10 | T3: =SUM(T4:T8) -> 1.4494519e+10 | W3: =SUM(W4:W8) -> 305200000 | X3: =SUM(X4:X8) -> 0 | Y3: =SUM(Y4:Y8) -> 0 | Z3: =SUM(Z4:Z8) -> 0 | AA3: =SUM(AA4:AA8) -> 1.298824e+10 | AB3: =SUM(AB4:AB8) -> 1.329344e+10 | AE3: =SUM(AE4:AE8) -> 0 | AF3: =SUM(AF4:AF8) -> 0 | AG3: =SUM(AG4:AG8) -> 0 | AH3: =SUM(AH4:AH8) -> 0 | AI3: =SUM(AI4:AI8) -> 0 | AJ3: =SUM(AJ4:AJ8) -> 0 | AQ3: =SUM(AQ4:AQ8) -> 5.8927538e+08
B4: 1.1 | C4: INSTALACION FAENA | O4: =SUM(O22:O24) -> 0 | P4: =SUM(P22:P24) -> 0 | Q4: =SUM(Q22:Q24) -> 0 | R4: =SUM(R22:R24) -> 0 | S4: =SUM(S22:S24) -> 1.043907e+09 | T4: =SUM(T22:T24) -> 1.043907e+09 | W4: =SUM(W22:W24) -> 0 | X4: =SUM(X22:X24) -> 0 | Y4: =SUM(Y22:Y24) -> 0 | Z4: =SUM(Z22:Z24) -> 0 | AA4: =SUM(AA22:AA24) -> 1.043907e+09 | AB4: =SUM(AB22:AB24) -> 1.043907e+09 | AE4: =SUM(AE22:AE24) -> 0 | AF4: =SUM(AF22:AF24) -> 0 | AG4: =SUM(AG22:AG24) -> 0 | AH4: =SUM(AH22:AH24) -> 0 | AI4: =SUM(AI22:AI24) -> 0 | AJ4: =SUM(AJ22:AJ24) -> 0 | AQ4: =SUM(AQ22:AQ24) -> 5.8927538e+08
B5: 1.2 | C5: MANTENCION DE CAMINO BICHOFITA | O5: =SUM(O26:O33) -> 305200000 | P5: =SUM(P26:P33) -> 0 | Q5: =SUM(Q26:Q33) -> 0 | R5: =SUM(R26:R33) -> 0 | S5: =SUM(S26:S33) -> 0 | T5: =SUM(T26:T33) -> 305200000 | W5: =SUM(W26:W33) -> 305200000 | X5: =SUM(X26:X33) -> 0 | Y5: =SUM(Y26:Y33) -> 0 | Z5: =SUM(Z26:Z33) -> 0 | AA5: =SUM(AA26:AA33) -> 0 | AB5: =SUM(AB26:AB33) -> 305200000 | AE5: =SUM(AE26:AE33) -> 0 | AF5: =SUM(AF26:AF33) -> 0 | AG5: =SUM(AG26:AG33) -> 0 | AH5: =SUM(AH26:AH33) -> 0 | AI5: =SUM(AI26:AI33) -> 0 | AJ5: =SUM(AJ26:AJ33) -> 0 | AQ5: =SUM(AQ26:AQ33) -> 0
B6: 1.3.1 | C6: GASTOS GENERALES | O6: =O35 -> 0 | P6: =P35 -> 0 | Q6: =Q35 -> 0 | R6: =R35 -> 0 | S6: =S35 -> 1.1780358e+10 | T6: =T35 -> 1.1780358e+10 | W6: =W35 -> 0 | X6: =X35 -> 0 | Y6: =Y35 -> 0 | Z6: =Z35 -> 0 | AA6: =AA35 -> 1.1780358e+10 | AB6: =AB35 -> 1.1780358e+10 | AE6: =AE35 -> 0 | AF6: =AF35 -> 0 | AG6: =AG35 -> 0 | AH6: =AH35 -> 0 | AI6: =AI35 -> 0 | AJ6: =AJ35 -> 0 | AQ6: =AQ35 -> 0
B7: 1.3.2 | C7: GASTOS A COSTO EFECTIVO | O7: =O36 -> 0 | P7: =P36 -> 0 | Q7: =Q36 -> 0 | R7: =R36 -> 0 | S7: =S36 -> 160000000 | T7: =T36 -> 160000000 | W7: =W36 -> 0 | X7: =X36 -> 0 | Y7: =Y36 -> 0 | Z7: =Z36 -> 0 | AA7: =AA36 -> 160000000 | AB7: =AB36 -> 160000000 | AE7: =AE36 -> 0 | AF7: =AF36 -> 0 | AG7: =AG36 -> 0 | AH7: =AH36 -> 0 | AI7: =AI36 -> 0 | AJ7: =AJ36 -> 0 | AQ7: =AQ36 -> 0
B8: 4.1 | C8: INCENTIVO TRIMESTRAL | O8: =O731 -> 0 | P8: =P731 -> 0 | Q8: =Q731 -> 0 | R8: =R731 -> 0 | S8: =S731 -> 1205054055 | T8: =T731 -> 1205054055 | W8: =W731 -> 0 | X8: =X731 -> 0 | Y8: =Y731 -> 0 | Z8: =Z731 -> 0 | AA8: =AA731 -> 3975016 | AB8: =AB731 -> 3975016 | AE8: =AE731 -> 0 | AF8: =AF731 -> 0 | AG8: =AG731 -> 0 | AH8: =AH731 -> 0 | AI8: =AI731 -> 0 | AJ8: =AJ731 -> 0 | AQ8: =AQ731 -> 0
C9: COSTO DIRECTO | O9: =SUM(O10:O15) -> 12123676364 | P9: =SUM(P10:P15) -> 1.9221375e+10 | Q9: =SUM(Q10:Q15) -> 2.6323838e+09 | R9: =SUM(R10:R15) -> 4.6030447e+09 | S9: =SUM(S10:S15) -> 0 | T9: =SUM(T10:T15) -> 3.858048e+10 | W9: =SUM(W10:W15) -> 12123676364 | X9: =SUM(X10:X15) -> 1.9221375e+10 | Y9: =SUM(Y10:Y15) -> 2.6323838e+09 | Z9: =SUM(Z10:Z15) -> 4.6030447e+09 | AA9: =SUM(AA10:AA15) -> 0 | AB9: =SUM(AB10:AB15) -> 3.858048e+10 | AE9: =SUM(AE10:AE15) -> 0 | AF9: =SUM(AF10:AF15) -> 0 | AG9: =SUM(AG10:AG15) -> 0 | AH9: =SUM(AH10:AH15) -> 0 | AI9: =SUM(AI10:AI15) -> 0 | AJ9: =SUM(AJ10:AJ15) -> 0 | AQ9: =SUM(AQ10:AQ15) -> 8.1079126e+08
B10: 2.1 | C10: MANEJO RIPIOS | O10: =SUM(O39:O205) -> 1751055083 | P10: =SUM(P39:P205) -> 2.9392104e+09 | Q10: =SUM(Q39:Q205) -> 3.9389245e+08 | R10: =SUM(R39:R205) -> 6.8876907e+08 | S10: =SUM(S39:S205) -> 0 | T10: =SUM(T39:T205) -> 5.772927e+09 | W10: =SUM(W39:W205) -> 1751055083 | X10: =SUM(X39:X205) -> 2.9392104e+09 | Y10: =SUM(Y39:Y205) -> 3.9389245e+08 | Z10: =SUM(Z39:Z205) -> 6.8876907e+08 | AA10: =SUM(AA39:AA205) -> 0 | AB10: =SUM(AB39:AB205) -> 5.772927e+09 | AE10: =SUM(AE39:AE205) -> 0 | AF10: =SUM(AF39:AF205) -> 0 | AG10: =SUM(AG39:AG205) -> 0 | AH10: =SUM(AH39:AH205) -> 0 | AI10: =SUM(AI39:AI205) -> 0 | AJ10: =SUM(AJ39:AJ205) -> 0 | AQ10: =SUM(AQ39:AQ205) -> 0
B11: 2.2 | C11: REGADIO LIXIVIACION SECUNDARIA | O11: =SUM(O206:O352) -> 192553210 | P11: =SUM(P206:P352) -> 3.7086517e+09 | Q11: =SUM(Q206:Q352) -> 3.2762647e+08 | R11: =SUM(R206:R352) -> 5.7289492e+08 | S11: =SUM(S206:S352) -> 0 | T11: =SUM(T206:T352) -> 4.8017263e+09 | W11: =SUM(W206:W352) -> 192553210 | X11: =SUM(X206:X352) -> 3.7086517e+09 | Y11: =SUM(Y206:Y352) -> 3.2762647e+08 | Z11: =SUM(Z206:Z352) -> 5.7289492e+08 | AA11: =SUM(AA206:AA352) -> 0 | AB11: =SUM(AB206:AB352) -> 4.8017263e+09 | AE11: =SUM(AE206:AE352) -> 0 | AF11: =SUM(AF206:AF352) -> 0 | AG11: =SUM(AG206:AG352) -> 0 | AH11: =SUM(AH206:AH352) -> 0 | AI11: =SUM(AI206:AI352) -> 0 | AJ11: =SUM(AJ206:AJ352) -> 0 | AQ11: =SUM(AQ206:AQ352) -> 2.4762178e+08
B12: 2.3 | C12: MANEJO DE SOLUCIONES PLS | O12: =SUM(O353:O513) -> 4603157049 | P12: =SUM(P353:P513) -> 2.5981418e+09 | Q12: =SUM(Q353:Q513) -> 6.0477115e+08 | R12: =SUM(R353:R513) -> 1.0575162e+09 | S12: =SUM(S353:S513) -> 0 | T12: =SUM(T353:T513) -> 8.8635863e+09 | W12: =SUM(W353:W513) -> 4603157049 | X12: =SUM(X353:X513) -> 2.5981418e+09 | Y12: =SUM(Y353:Y513) -> 6.0477115e+08 | Z12: =SUM(Z353:Z513) -> 1.0575162e+09 | AA12: =SUM(AA353:AA513) -> 0 | AB12: =SUM(AB353:AB513) -> 8.8635863e+09 | AE12: =SUM(AE353:AE513) -> 0 | AF12: =SUM(AF353:AF513) -> 0 | AG12: =SUM(AG353:AG513) -> 0 | AH12: =SUM(AH353:AH513) -> 0 | AI12: =SUM(AI353:AI513) -> 0 | AJ12: =SUM(AJ353:AJ513) -> 0 | AQ12: =SUM(AQ353:AQ513) -> 1.938665e+08
B13: 2.4 | C13: CONDUCCION | O13: =SUM(O514:O602) -> 4999459551 | P13: =SUM(P514:P602) -> 1.1536332e+09 | Q13: =SUM(Q514:Q602) -> 5.1674191e+08 | R13: =SUM(R514:R602) -> 9.0358637e+08 | S13: =SUM(S514:S602) -> 0 | T13: =SUM(T514:T602) -> 7.573421e+09 | W13: =SUM(W514:W602) -> 4999459551 | X13: =SUM(X514:X602) -> 1.1536332e+09 | Y13: =SUM(Y514:Y602) -> 5.1674191e+08 | Z13: =SUM(Z514:Z602) -> 9.0358637e+08 | AA13: =SUM(AA514:AA602) -> 0 | AB13: =SUM(AB514:AB602) -> 7.573421e+09 | AE13: =SUM(AE514:AE602) -> 0 | AF13: =SUM(AF514:AF602) -> 0 | AG13: =SUM(AG514:AG602) -> 0 | AH13: =SUM(AH514:AH602) -> 0 | AI13: =SUM(AI514:AI602) -> 0 | AJ13: =SUM(AJ514:AJ602) -> 0 | AQ13: =SUM(AQ514:AQ602) -> 0
B14: 2.5 | C14: SISTEMA CONTRA INCENDIO | O14: =SUM(O603:O703) -> 577451471 | P14: =SUM(P603:P703) -> 8.0797399e+09 | Q14: =SUM(Q603:Q703) -> 7.2703822e+08 | R14: =SUM(R603:R703) -> 1.2713152e+09 | S14: =SUM(S603:S703) -> 0 | T14: =SUM(T603:T703) -> 1.0655545e+10 | W14: =SUM(W603:W703) -> 577451471 | X14: =SUM(X603:X703) -> 8.0797399e+09 | Y14: =SUM(Y603:Y703) -> 7.2703822e+08 | Z14: =SUM(Z603:Z703) -> 1.2713152e+09 | AA14: =SUM(AA603:AA703) -> 0 | AB14: =SUM(AB603:AB703) -> 1.0655545e+10 | AE14: =SUM(AE603:AE703) -> 0 | AF14: =SUM(AF603:AF703) -> 0 | AG14: =SUM(AG603:AG703) -> 0 | AH14: =SUM(AH603:AH703) -> 0 | AI14: =SUM(AI603:AI703) -> 0 | AJ14: =SUM(AJ603:AJ703) -> 0 | AQ14: =SUM(AQ603:AQ703) -> 3.6930298e+08
B15: 2.6 | C15: RECEPCION Y SUMINISTRO ENERGIA ELECTRICA | O15: =SUM(O704:O713) -> 0 | P15: =SUM(P704:P713) -> 7.4199809e+08 | Q15: =SUM(Q704:Q713) -> 62313625 | R15: =SUM(R704:R713) -> 1.0896299e+08 | S15: =SUM(S704:S713) -> 0 | T15: =SUM(T704:T713) -> 9.132747e+08 | W15: =SUM(W704:W713) -> 0 | X15: =SUM(X704:X713) -> 7.4199809e+08 | Y15: =SUM(Y704:Y713) -> 62313625 | Z15: =SUM(Z704:Z713) -> 1.0896299e+08 | AA15: =SUM(AA704:AA713) -> 0 | AB15: =SUM(AB704:AB713) -> 9.132747e+08 | AE15: =SUM(AE704:AE713) -> 0 | AF15: =SUM(AF704:AF713) -> 0 | AG15: =SUM(AG704:AG713) -> 0 | AH15: =SUM(AH704:AH713) -> 0 | AI15: =SUM(AI704:AI713) -> 0 | AJ15: =SUM(AJ704:AJ713) -> 0 | AQ15: =SUM(AQ704:AQ713) -> 0
C16: USO RECURSOS | O16: =O17 -> 475309850 | P16: =P17 -> 302421800 | Q16: =Q17 -> 0 | R16: =R17 -> 0 | S16: =S17 -> 0 | T16: =T17 -> 777731650 | W16: =W17 -> 475309850 | X16: =X17 -> 302421800 | Y16: =Y17 -> 0 | Z16: =Z17 -> 0 | AA16: =AA17 -> 0 | AB16: =AB17 -> 777731650 | AE16: =AE17 -> 0 | AF16: =AF17 -> 0 | AG16: =AG17 -> 0 | AH16: =AH17 -> 0 | AI16: =AI17 -> 0 | AJ16: =AJ17 -> 0 | AQ16: =AQ17 -> 0
B17: 3.1 | C17: EQUIPOS | O17: =SUM(O714:O729) -> 475309850 | P17: =SUM(P714:P729) -> 302421800 | Q17: =SUM(Q714:Q729) -> 0 | R17: =SUM(R714:R729) -> 0 | S17: =SUM(S714:S729) -> 0 | T17: =SUM(T714:T729) -> 777731650 | W17: =SUM(W714:W729) -> 475309850 | X17: =SUM(X714:X729) -> 302421800 | Y17: =SUM(Y714:Y729) -> 0 | Z17: =SUM(Z714:Z729) -> 0 | AA17: =SUM(AA714:AA729) -> 0 | AB17: =SUM(AB714:AB729) -> 777731650 | AE17: =SUM(AE714:AE729) -> 0 | AF17: =SUM(AF714:AF729) -> 0 | AG17: =SUM(AG714:AG729) -> 0 | AH17: =SUM(AH714:AH729) -> 0 | AI17: =SUM(AI714:AI729) -> 0 | AJ17: =SUM(AJ714:AJ729) -> 0 | AQ17: =SUM(AQ714:AQ729) -> 0
F18: =SUBTOTAL(9,F20:F730) -> 0 | G18: =SUBTOTAL(9,G20:G730) -> 3174.474 | H18: =SUBTOTAL(9,H20:H730) -> 3174.474 | AL18: Forecast
A19: ITEM | B19: ESPECIALIDAD | C19: DESCRIPCION | D19: UNIDAD | E19: CANTIDAD | F19: HH EXCON | G19: HH EIMISA | H19: HH TOTAL | I19: APU EXCON | J19: APU EIMISA | K19: % UTILIDAD | L19: % MOI TERRENO | M19: GG + IND + IF | N19: APU | O19: EXCON $ | P19: EIMISA $ | Q19: UTILIDAD | R19: MOI TERRENO | S19: GG + IND + IF $ | T19: TOTAL $ | V19: CANTIDAD | W19: EXCON $ | X19: EIMISA $ | Y19: UTILIDAD | Z19: MOI TERRENO | AA19: GG + IND + IF $ | AB19: TOTAL $ | AD19: AVANCE ACUMULADO | AE19: EXCON $ | AF19: EIMISA $ | AG19: UTILIDAD | AH19: MOI TERRENO | AI19: GG + IND + IF $ | AJ19: TOTAL $ | AL19: POM | AM19: HH | AN19: $$$ | AP19: CANTIDAD | AQ19: TOTAL $
A20: 1.0 | C20: GENERAL (Suma Alzada)
A21: 1.1 | C21: Movilización, Instalación y Desmovilización de Faenas
A22: 1.1.1 | C22: Movilización e Instalación de Faena | D22: gl | E22: 1 | H22: =G22+F22 -> 0 | M22: 9.8212563e+08 | N22: =SUM(I22:M22) -> 9.8212563e+08 | O22: =$E22*I22 -> 0 | P22: =$E22*J22 -> 0 | Q22: =$E22*K22 -> 0 | R22: =$E22*L22 -> 0 | S22: =$E22*M22 -> 9.8212563e+08 | T22: =SUM(O22:S22) -> 9.8212563e+08 | V22: 1 | W22: =$V22*I22 -> 0 | X22: =$V22*J22 -> 0 | Y22: =$V22*K22 -> 0 | Z22: =$V22*L22 -> 0 | AA22: =$V22*M22 -> 9.8212563e+08 | AB22: =SUM(W22:AA22) -> 9.8212563e+08 | AE22: =$AD22*I22 -> 0 | AF22: =$AD22*J22 -> 0 | AG22: =$AD22*K22 -> 0 | AH22: =$AD22*L22 -> 0 | AI22: =$AD22*M22 -> 0 | AJ22: =SUM(AE22:AI22) -> 0 | AL22: =IFERROR(VLOOKUP($A22,Itemizado_Piping!C:Q,12,0),0) -> 0 | AM22: =IFERROR(VLOOKUP($A22,Itemizado_Piping!C:Q,13,0),0) -> 0 | AN22: =IFERROR(VLOOKUP($A22,Itemizado_Piping!C:Q,14,0),0) -> 0 | AP22: 0.6 | AQ22: =N22*AP22 -> 5.8927538e+08
A23: 1.1.2 | C23: Mantención mensual instalaciones (INLCUIDO) | D23: mes | E23: 15 | H23: =G23+F23 -> 0 | M23: 0 | N23: =SUM(I23:M23) -> 0 | O23: =$E23*I23 -> 0 | P23: =$E23*J23 -> 0 | Q23: =$E23*K23 -> 0 | R23: =$E23*L23 -> 0 | S23: =$E23*M23 -> 0 | T23: =SUM(O23:S23) -> 0 | V23: 15 | W23: =$V23*I23 -> 0 | X23: =$V23*J23 -> 0 | Y23: =$V23*K23 -> 0 | Z23: =$V23*L23 -> 0 | AA23: =$V23*M23 -> 0 | AB23: =SUM(W23:AA23) -> 0 | AE23: =$AD23*I23 -> 0 | AF23: =$AD23*J23 -> 0 | AG23: =$AD23*K23 -> 0 | AH23: =$AD23*L23 -> 0 | AI23: =$AD23*M23 -> 0 | AJ23: =SUM(AE23:AI23) -> 0 | AL23: =IFERROR(VLOOKUP($A23,Itemizado_Piping!C:Q,12,0),0) -> 0 | AM23: =IFERROR(VLOOKUP($A23,Itemizado_Piping!C:Q,13,0),0) -> 0 | AN23: =IFERROR(VLOOKUP($A23,Itemizado_Piping!C:Q,14,0),0) -> 0 | AQ23: =N23*AP23 -> 0
A24: 1.1.3 | C24: Levantamiento final de instalaciones y desmovilización | D24: gl | E24: 1 | H24: =G24+F24 -> 0 | M24: 61781357 | N24: =SUM(I24:M24) -> 61781357 | O24: =$E24*I24 -> 0 | P24: =$E24*J24 -> 0 | Q24: =$E24*K24 -> 0 | R24: =$E24*L24 -> 0 | S24: =$E24*M24 -> 61781357 | T24: =SUM(O24:S24) -> 61781357 | V24: 1 | W24: =$V24*I24 -> 0 | X24: =$V24*J24 -> 0 | Y24: =$V24*K24 -> 0 | Z24: =$V24*L24 -> 0 | AA24: =$V24*M24 -> 61781357 | AB24: =SUM(W24:AA24) -> 61781357 | AE24: =$AD24*I24 -> 0 | AF24: =$AD24*J24 -> 0 | AG24: =$AD24*K24 -> 0 | AH24: =$AD24*L24 -> 0 | AI24: =$AD24*M24 -> 0 | AJ24: =SUM(AE24:AI24) -> 0 | AL24: =IFERROR(VLOOKUP($A24,Itemizado_Piping!C:Q,12,0),0) -> 0 | AM24: =IFERROR(VLOOKUP($A24,Itemizado_Piping!C:Q,13,0),0) -> 0 | AN24: =IFERROR(VLOOKUP($A24,Itemizado_Piping!C:Q,14,0),0) -> 0 | AQ24: =N24*AP24 -> 0
A25: 1.2 | C25: Mantención de caminos con Bichofita
A26: 1.2.1 | C26: Motoniveladora | D26: hm | E26: 405 | F26: 742 | H26: =G26+F26 -> 742 | I26: 115198 | N26: =SUM(I26:M26) -> 115198 | O26: =$E26*I26 -> 46655190 | P26: =$E26*J26 -> 0 | Q26: =$E26*K26 -> 0 | R26: =$E26*L26 -> 0 | S26: =$E26*M26 -> 0 | T26: =SUM(O26:S26) -> 46655190 | V26: 405 | W26: =$V26*I26 -> 46655190 | X26: =$V26*J26 -> 0 | Y26: =$V26*K26 -> 0 | Z26: =$V26*L26 -> 0 | AA26: =$V26*M26 -> 0 | AB26: =SUM(W26:AA26) -> 46655190 | AE26: =$AD26*I26 -> 0 | AF26: =$AD26*J26 -> 0 | AG26: =$AD26*K26 -> 0 | AH26: =$AD26*L26 -> 0 | AI26: =$AD26*M26 -> 0 | AJ26: =SUM(AE26:AI26) -> 0 | AL26: =IFERROR(VLOOKUP($A26,Itemizado_Piping!C:Q,12,0),0) -> 0 | AM26: =IFERROR(VLOOKUP($A26,Itemizado_Piping!C:Q,13,0),0) -> 0 | AN26: =IFERROR(VLOOKUP($A26,Itemizado_Piping!C:Q,14,0),0) -> 0 | AQ26: =N26*AP26 -> 0
A27: 1.2.2 | C27: Rodillo 10 T | D27: hm | E27: 405 | F27: 742 | H27: =G27+F27 -> 742 | I27: 74321 | N27: =SUM(I27:M27) -> 74321 | O27: =$E27*I27 -> 30100005 | P27: =$E27*J27 -> 0 | Q27: =$E27*K27 -> 0 | R27: =$E27*L27 -> 0 | S27: =$E27*M27 -> 0 | T27: =SUM(O27:S27) -> 30100005 | V27: 405 | W27: =$V27*I27 -> 30100005 | X27: =$V27*J27 -> 0 | Y27: =$V27*K27 -> 0 | Z27: =$V27*L27 -> 0 | AA27: =$V27*M27 -> 0 | AB27: =SUM(W27:AA27) -> 30100005 | AE27: =$AD27*I27 -> 0 | AF27: =$AD27*J27 -> 0 | AG27: =$AD27*K27 -> 0 | AH27: =$AD27*L27 -> 0 | AI27: =$AD27*M27 -> 0 | AJ27: =SUM(AE27:AI27) -> 0 | AL27: =IFERROR(VLOOKUP($A27,Itemizado_Piping!C:Q,12,0),0) -> 0 | AM27: =IFERROR(VLOOKUP($A27,Itemizado_Piping!C:Q,13,0),0) -> 0 | AN27: =IFERROR(VLOOKUP($A27,Itemizado_Piping!C:Q,14,0),0) -> 0 | AQ27: =N27*AP27 -> 0
A28: 1.2.3 | C28: Camion aljibe 25 m3 | D28: hm | E28: 405 | F28: 742 | H28: =G28+F28 -> 742 | I28: 87401 | N28: =SUM(I28:M28) -> 87401 | O28: =$E28*I28 -> 35397405 | P28: =$E28*J28 -> 0 | Q28: =$E28*K28 -> 0 | R28: =$E28*L28 -> 0 | S28: =$E28*M28 -> 0 | T28: =SUM(O28:S28) -> 35397405 | V28: 405 | W28: =$V28*I28 -> 35397405 | X28: =$V28*J28 -> 0 | Y28: =$V28*K28 -> 0 | Z28: =$V28*L28 -> 0 | AA28: =$V28*M28 -> 0 | AB28: =SUM(W28:AA28) -> 35397405 | AE28: =$AD28*I28 -> 0 | AF28: =$AD28*J28 -> 0 | AG28: =$AD28*K28 -> 0 | AH28: =$AD28*L28 -> 0 | AI28: =$AD28*M28 -> 0 | AJ28: =SUM(AE28:AI28) -> 0 | AL28: =IFERROR(VLOOKUP($A28,Itemizado_Piping!C:Q,12,0),0) -> 0 | AM28: =IFERROR(VLOOKUP($A28,Itemizado_Piping!C:Q,13,0),0) -> 0 | AN28: =IFERROR(VLOOKUP($A28,Itemizado_Piping!C:Q,14,0),0) -> 0 | AQ28: =N28*AP28 -> 0
A29: 1.2.4 | C29: Camion tolva | D29: hm | E29: 225 | F29: 412 | H29: =G29+F29 -> 412 | I29: 91523 | N29: =SUM(I29:M29) -> 91523 | O29: =$E29*I29 -> 20592675 | P29: =$E29*J29 -> 0 | Q29: =$E29*K29 -> 0 | R29: =$E29*L29 -> 0 | S29: =$E29*M29 -> 0 | T29: =SUM(O29:S29) -> 20592675 | V29: 225 | W29: =$V29*I29 -> 20592675 | X29: =$V29*J29 -> 0 | Y29: =$V29*K29 -> 0 | Z29: =$V29*L29 -> 0 | AA29: =$V29*M29 -> 0 | AB29: =SUM(W29:AA29) -> 20592675 | AE29: =$AD29*I29 -> 0 | AF29: =$AD29*J29 -> 0 | AG29: =$AD29*K29 -> 0 | AH29: =$AD29*L29 -> 0 | AI29: =$AD29*M29 -> 0 | AJ29: =SUM(AE29:AI29) -> 0 | AL29: =IFERROR(VLOOKUP($A29,Itemizado_Piping!C:Q,12,0),0) -> 0 | AM29: =IFERROR(VLOOKUP($A29,Itemizado_Piping!C:Q,13,0),0) -> 0 | AN29: =IFERROR(VLOOKUP($A29,Itemizado_Piping!C:Q,14,0),0) -> 0 | AQ29: =N29*AP29 -> 0
A30: 1.2.5 | C30: Cargador | D30: hm | E30: 225 | F30: 412 | H30: =G30+F30 -> 412 | I30: 105865 | N30: =SUM(I30:M30) -> 105865 | O30: =$E30*I30 -> 23819625 | P30: =$E30*J30 -> 0 | Q30: =$E30*K30 -> 0 | R30: =$E30*L30 -> 0 | S30: =$E30*M30 -> 0 | T30: =SUM(O30:S30) -> 23819625 | V30: 225 | W30: =$V30*I30 -> 23819625 | X30: =$V30*J30 -> 0 | Y30: =$V30*K30 -> 0 | Z30: =$V30*L30 -> 0 | AA30: =$V30*M30 -> 0 | AB30: =SUM(W30:AA30) -> 23819625 | AE30: =$AD30*I30 -> 0 | AF30: =$AD30*J30 -> 0 | AG30: =$AD30*K30 -> 0 | AH30: =$AD30*L30 -> 0 | AI30: =$AD30*M30 -> 0 | AJ30: =SUM(AE30:AI30) -> 0 | AL30: =IFERROR(VLOOKUP($A30,Itemizado_Piping!C:Q,12,0),0) -> 0 | AM30: =IFERROR(VLOOKUP($A30,Itemizado_Piping!C:Q,13,0),0) -> 0 | AN30: =IFERROR(VLOOKUP($A30,Itemizado_Piping!C:Q,14,0),0) -> 0 | AQ30: =N30*AP30 -> 0
A31: 1.2.6 | C31: Bischofita | D31: kg | E31: 1688000 | H31: =G31+F31 -> 0 | I31: 74 | N31: =SUM(I31:M31) -> 74 | O31: =$E31*I31 -> 124912000 | P31: =$E31*J31 -> 0 | Q31: =$E31*K31 -> 0 | R31: =$E31*L31 -> 0 | S31: =$E31*M31 -> 0 | T31: =SUM(O31:S31) -> 124912000 | V31: 1688000 | W31: =$V31*I31 -> 124912000 | X31: =$V31*J31 -> 0 | Y31: =$V31*K31 -> 0 | Z31: =$V31*L31 -> 0 | AA31: =$V31*M31 -> 0 | AB31: =SUM(W31:AA31) -> 124912000 | AE31: =$AD31*I31 -> 0 | AF31: =$AD31*J31 -> 0 | AG31: =$AD31*K31 -> 0 | AH31: =$AD31*L31 -> 0 | AI31: =$AD31*M31 -> 0 | AJ31: =SUM(AE31:AI31) -> 0 | AL31: =IFERROR(VLOOKUP($A31,Itemizado_Piping!C:Q,12,0),0) -> 0 | AM31: =IFERROR(VLOOKUP($A31,Itemizado_Piping!C:Q,13,0),0) -> 0 | AN31: =IFERROR(VLOOKUP($A31,Itemizado_Piping!C:Q,14,0),0) -> 0 | AQ31: =N31*AP31 -> 0
A32: 1.2.7 | C32: Supervisor | D32: hd | E32: 45 | F32: 495 | H32: =G32+F32 -> 495 | I32: 248746 | N32: =SUM(I32:M32) -> 248746 | O32: =$E32*I32 -> 11193570 | P32: =$E32*J32 -> 0 | Q32: =$E32*K32 -> 0 | R32: =$E32*L32 -> 0 | S32: =$E32*M32 -> 0 | T32: =SUM(O32:S32) -> 11193570 | V32: 45 | W32: =$V32*I32 -> 11193570 | X32: =$V32*J32 -> 0 | Y32: =$V32*K32 -> 0 | Z32: =$V32*L32 -> 0 | AA32: =$V32*M32 -> 0 | AB32: =SUM(W32:AA32) -> 11193570 | AE32: =$AD32*I32 -> 0 | AF32: =$AD32*J32 -> 0 | AG32: =$AD32*K32 -> 0 | AH32: =$AD32*L32 -> 0 | AI32: =$AD32*M32 -> 0 | AJ32: =SUM(AE32:AI32) -> 0 | AL32: =IFERROR(VLOOKUP($A32,Itemizado_Piping!C:Q,12,0),0) -> 0 | AM32: =IFERROR(VLOOKUP($A32,Itemizado_Piping!C:Q,13,0),0) -> 0 | AN32: =IFERROR(VLOOKUP($A32,Itemizado_Piping!C:Q,14,0),0) -> 0 | AQ32: =N32*AP32 -> 0
A33: 1.2.8 | C33: Señaleros | D33: hd | E33: 90 | F33: 990 | H33: =G33+F33 -> 990 | I33: 139217 | N33: =SUM(I33:M33) -> 139217 | O33: =$E33*I33 -> 12529530 | P33: =$E33*J33 -> 0 | Q33: =$E33*K33 -> 0 | R33: =$E33*L33 -> 0 | S33: =$E33*M33 -> 0 | T33: =SUM(O33:S33) -> 12529530 | V33: 90 | W33: =$V33*I33 -> 12529530 | X33: =$V33*J33 -> 0 | Y33: =$V33*K33 -> 0 | Z33: =$V33*L33 -> 0 | AA33: =$V33*M33 -> 0 | AB33: =SUM(W33:AA33) -> 12529530 | AE33: =$AD33*I33 -> 0 | AF33: =$AD33*J33 -> 0 | AG33: =$AD33*K33 -> 0 | AH33: =$AD33*L33 -> 0 | AI33: =$AD33*M33 -> 0 | AJ33: =SUM(AE33:AI33) -> 0 | AL33: =IFERROR(VLOOKUP($A33,Itemizado_Piping!C:Q,12,0),0) -> 0 | AM33: =IFERROR(VLOOKUP($A33,Itemizado_Piping!C:Q,13,0),0) -> 0 | AN33: =IFERROR(VLOOKUP($A33,Itemizado_Piping!C:Q,14,0),0) -> 0 | AQ33: =N33*AP33 -> 0
A34: 1.3 | C34: Generales
A35: 1.3.1 | C35: Gastos Generales (ECO-08) | D35: gl | E35: 1 | H35: =G35+F35 -> 0 | M35: 1.1780358e+10 | N35: =SUM(I35:M35) -> 1.1780358e+10 | O35: =$E35*I35 -> 0 | P35: =$E35*J35 -> 0 | Q35: =$E35*K35 -> 0 | R35: =$E35*L35 -> 0 | S35: =$E35*M35 -> 1.1780358e+10 | T35: =SUM(O35:S35) -> 1.1780358e+10 | V35: 1 | W35: =$V35*I35 -> 0 | X35: =$V35*J35 -> 0 | Y35: =$V35*K35 -> 0 | Z35: =$V35*L35 -> 0 | AA35: =$V35*M35 -> 1.1780358e+10 | AB35: =SUM(W35:AA35) -> 1.1780358e+10 | AE35: =$AD35*I35 -> 0 | AF35: =$AD35*J35 -> 0 | AG35: =$AD35*K35 -> 0 | AH35: =$AD35*L35 -> 0 | AI35: =$AD35*M35 -> 0 | AJ35: =SUM(AE35:AI35) -> 0 | AL35: =IFERROR(VLOOKUP($A35,Itemizado_Piping!C:Q,12,0),0) -> 0 | AM35: =IFERROR(VLOOKUP($A35,Itemizado_Piping!C:Q,13,0),0) -> 0 | AN35: =IFERROR(VLOOKUP($A35,Itemizado_Piping!C:Q,14,0),0) -> 0 | AQ35: =N35*AP35 -> 0
A36: 1.3.2 | C36: Gastos a Costo Efectivo (incluye gestión de compras | D36: gl | E36: 1 | H36: =G36+F36 -> 0 | M36: 160000000 | N36: =SUM(I36:M36) -> 160000000 | O36: =$E36*I36 -> 0 | P36: =$E36*J36 -> 0 | Q36: =$E36*K36 -> 0 | R36: =$E36*L36 -> 0 | S36: =$E36*M36 -> 160000000 | T36: =SUM(O36:S36) -> 160000000 | V36: 1 | W36: =$V36*I36 -> 0 | X36: =$V36*J36 -> 0 | Y36: =$V36*K36 -> 0 | Z36: =$V36*L36 -> 0 | AA36: =$V36*M36 -> 160000000 | AB36: =SUM(W36:AA36) -> 160000000 | AE36: =$AD36*I36 -> 0 | AF36: =$AD36*J36 -> 0 | AG36: =$AD36*K36 -> 0 | AH36: =$AD36*L36 -> 0 | AI36: =$AD36*M36 -> 0 | AJ36: =SUM(AE36:AI36) -> 0 | AL36: =IFERROR(VLOOKUP($A36,Itemizado_Piping!C:Q,12,0),0) -> 0 | AM36: =IFERROR(VLOOKUP($A36,Itemizado_Piping!C:Q,13,0),0) -> 0 | AN36: =IFERROR(VLOOKUP($A36,Itemizado_Piping!C:Q,14,0),0) -> 0 | AQ36: =N36*AP36 -> 0
A37: 1.3.3 | C37: UTILIDAD (Incluida en Precios Unitarios) | D37: gl | E37: 1 | H37: =G37+F37 -> 0 | N37: =SUM(I37:M37) -> 0 | O37: =$E37*I37 -> 0 | P37: =$E37*J37 -> 0 | Q37: =$E37*K37 -> 0 | R37: =$E37*L37 -> 0 | S37: =$E37*M37 -> 0 | T37: =SUM(O37:S37) -> 0 | V37: 1 | W37: =$V37*I37 -> 0 | X37: =$V37*J37 -> 0 | Y37: =$V37*K37 -> 0 | Z37: =$V37*L37 -> 0 | AA37: =$V37*M37 -> 0 | AB37: =SUM(W37:AA37) -> 0 | AE37: =$AD37*I37 -> 0 | AF37: =$AD37*J37 -> 0 | AG37: =$AD37*K37 -> 0 | AH37: =$AD37*L37 -> 0 | AI37: =$AD37*M37 -> 0 | AJ37: =SUM(AE37:AI37) -> 0 | AL37: =IFERROR(VLOOKUP($A37,Itemizado_Piping!C:Q,12,0),0) -> 0 | AM37: =IFERROR(VLOOKUP($A37,Itemizado_Piping!C:Q,13,0),0) -> 0 | AN37: =IFERROR(VLOOKUP($A37,Itemizado_Piping!C:Q,14,0),0) -> 0 | AQ37: =N37*AP37 -> 0
A38: 2.0 | C38: OBRAS CONSTRUCCIÓN (Serie de Precio Unitario c/ Utilidad)
A39: 2.1 | C39: Manejo de Ripios
A40: 2.1.1 | C40: Sala Eléctrica Transporte de Ripios
A41: 2.1.1.1 | C41: OOCC Sala Eléctrica (incluye suministros)
A42: 2.1.1.1.1 | C42: Emplantillado G-10 | D42: m3 | E42: 17 | G42: 76.5 | H42: =G42+F42 -> 76.5 | J42: 268814.89 | K42: 22575.301 | L42: 39475.672 | N42: =SUM(I42:M42) -> 330865.86 | O42: =$E42*I42 -> 0 | P42: =$E42*J42 -> 4569853.1 | Q42: =$E42*K42 -> 383780.12 | R42: =$E42*L42 -> 671086.43 | S42: =$E42*M42 -> 0 | T42: =SUM(O42:S42) -> 5624719.7 | V42: 17 | W42: =$V42*I42 -> 0 | X42: =$V42*J42 -> 4569853.1 | Y42: =$V42*K42 -> 383780.12 | Z42: =$V42*L42 -> 671086.43 | AA42: =$V42*M42 -> 0 | AB42: =SUM(W42:AA42) -> 5624719.7 | AE42: =$AD42*I42 -> 0 | AF42: =$AD42*J42 -> 0 | AG42: =$AD42*K42 -> 0 | AH42: =$AD42*L42 -> 0 | AI42: =$AD42*M42 -> 0 | AJ42: =SUM(AE42:AI42) -> 0 | AL42: =IFERROR(VLOOKUP($A42,Itemizado_Piping!C:Q,12,0),0) -> 0 | AM42: =IFERROR(VLOOKUP($A42,Itemizado_Piping!C:Q,13,0),0) -> 0 | AN42: =IFERROR(VLOOKUP($A42,Itemizado_Piping!C:Q,14,0),0) -> 0 | AQ42: =N42*AP42 -> 0
A43: 2.1.1.1.2 | C43: Hormigón Fundaciones, Muro y Radier G-25 | D43: m3 | E43: 140 | G43: 3421.04 | H43: =G43+F43 -> 3421.04 | J43: 965831.54 | K43: 81111.349 | L43: 141833.1 | N43: =SUM(I43:M43) -> 1188776 | O43: =$E43*I43 -> 0 | P43: =$E43*J43 -> 1.3521641e+08 | Q43: =$E43*K43 -> 11355589 | R43: =$E43*L43 -> 19856634 | S43: =$E43*M43 -> 0 | T43: =SUM(O43:S43) -> 1.6642864e+08 | V43: 140 | W43: =$V43*I43 -> 0 | X43: =$V43*J43 -> 1.3521641e+08 | Y43: =$V43*K43 -> 11355589 | Z43: =$V43*L43 -> 19856634 | AA43: =$V43*M43 -> 0 | AB43: =SUM(W43:AA43) -> 1.6642864e+08 | AE43: =$AD43*I43 -> 0 | AF43: =$AD43*J43 -> 0 | AG43: =$AD43*K43 -> 0 | AH43: =$AD43*L43 -> 0 | AI43: =$AD43*M43 -> 0 | AJ43: =SUM(AE43:AI43) -> 0 | AL43: =IFERROR(VLOOKUP($A43,Itemizado_Piping!C:Q,12,0),0) -> 0 | AM43: =IFERROR(VLOOKUP($A43,Itemizado_Piping!C:Q,13,0),0) -> 0 | AN43: =IFERROR(VLOOKUP($A43,Itemizado_Piping!C:Q,14,0),0) -> 0 | AQ43: =N43*AP43 -> 0
A44: 2.1.1.1.3 | C44: Acero de refuerzo A630-420H | D44: kg | E44: 8920 | G44: 624.4 | H44: =G44+F44 -> 624.4 | J44: 2987.235 | K44: 250.87051 | L44: 438.67774 | N44: =SUM(I44:M44) -> 3676.7833 | O44: =$E44*I44 -> 0 | P44: =$E44*J44 -> 26646136 | Q44: =$E44*K44 -> 2237765 | R44: =$E44*L44 -> 3913005.5 | S44: =$E44*M44 -> 0 | T44: =SUM(O44:S44) -> 32796907 | V44: 8920 | W44: =$V44*I44 -> 0 | X44: =$V44*J44 -> 26646136 | Y44: =$V44*K44 -> 2237765 | Z44: =$V44*L44 -> 3913005.5 | AA44: =$V44*M44 -> 0 | AB44: =SUM(W44:AA44) -> 32796907 | AE44: =$AD44*I44 -> 0 | AF44: =$AD44*J44 -> 0 | AG44: =$AD44*K44 -> 0 | AH44: =$AD44*L44 -> 0 | AI44: =$AD44*M44 -> 0 | AJ44: =SUM(AE44:AI44) -> 0 | AL44: =IFERROR(VLOOKUP($A44,Itemizado_Piping!C:Q,12,0),0) -> 0 | AM44: =IFERROR(VLOOKUP($A44,Itemizado_Piping!C:Q,13,0),0) -> 0 | AN44: =IFERROR(VLOOKUP($A44,Itemizado_Piping!C:Q,14,0),0) -> 0 | AQ44: =N44*AP44 -> 0
A45: 2.1.1.1.4 | C45: Excavación estructural (incluye excavación malla a tierra) | D45: m3 | E45: 529 | F45: 95 | H45: =G45+F45 -> 95 | I45: 8205 | K45: 689.06282 | L45: 1204.9105 | N45: =SUM(I45:M45) -> 10098.973 | O45: =$E45*I45 -> 4340445 | P45: =$E45*J45 -> 0 | Q45: =$E45*K45 -> 364514.23 | R45: =$E45*L45 -> 637397.67 | S45: =$E45*M45 -> 0 | T45: =SUM(O45:S45) -> 5342356.9 | V45: 529 | W45: =$V45*I45 -> 4340445 | X45: =$V45*J45 -> 0 | Y45: =$V45*K45 -> 364514.23 | Z45: =$V45*L45 -> 637397.67 | AA45: =$V45*M45 -> 0 | AB45: =SUM(W45:AA45) -> 5342356.9 | AE45: =$AD45*I45 -> 0 | AF45: =$AD45*J45 -> 0 | AG45: =$AD45*K45 -> 0 | AH45: =$AD45*L45 -> 0 | AI45: =$AD45*M45 -> 0 | AJ45: =SUM(AE45:AI45) -> 0 | AL45: =IFERROR(VLOOKUP($A45,Itemizado_Piping!C:Q,12,0),0) -> 0 | AM45: =IFERROR(VLOOKUP($A45,Itemizado_Piping!C:Q,13,0),0) -> 0 | AN45: =IFERROR(VLOOKUP($A45,Itemizado_Piping!C:Q,14,0),0) -> 0 | AQ45: =N45*AP45 -> 0
A46: 2.1.1.1.5 | C46: Relleno estructural compactado (incluye relleno malla a tierra) | D46: m3 | E46: 417 | F46: 699 | H46: =G46+F46 -> 699 | I46: 44980 | K46: 3777.4583 | L46: 6605.3474 | N46: =SUM(I46:M46) -> 55362.806 | O46: =$E46*I46 -> 18756660 | P46: =$E46*J46 -> 0 | Q46: =$E46*K46 -> 1575200.1 | R46: =$E46*L46 -> 2754429.9 | S46: =$E46*M46 -> 0 | T46: =SUM(O46:S46) -> 23086290 | V46: 417 | W46: =$V46*I46 -> 18756660 | X46: =$V46*J46 -> 0 | Y46: =$V46*K46 -> 1575200.1 | Z46: =$V46*L46 -> 2754429.9 | AA46: =$V46*M46 -> 0 | AB46: =SUM(W46:AA46) -> 23086290 | AE46: =$AD46*I46 -> 0 | AF46: =$AD46*J46 -> 0 | AG46: =$AD46*K46 -> 0 | AH46: =$AD46*L46 -> 0 | AI46: =$AD46*M46 -> 0 | AJ46: =SUM(AE46:AI46) -> 0 | AL46: =IFERROR(VLOOKUP($A46,Itemizado_Piping!C:Q,12,0),0) -> 0 | AM46: =IFERROR(VLOOKUP($A46,Itemizado_Piping!C:Q,13,0),0) -> 0 | AN46: =IFERROR(VLOOKUP($A46,Itemizado_Piping!C:Q,14,0),0) -> 0 | AQ46: =N46*AP46 -> 0
A47: 2.1.1.10 | C47: Malla Puesta a Tierra
A48: 2.1.1.10.1 | C48: Suministro e Instalación Conductor desnudo blando, clase B, 19 hebras N° 2/0 AWG | D48: m | E48: 120 | G48: 43.2 | H48: =G48+F48 -> 43.2 | J48: 15440.88 | K48: 1296.7381 | L48: 2267.505 | N48: =SUM(I48:M48) -> 19005.123 | O48: =$E48*I48 -> 0 | P48: =$E48*J48 -> 1852905.6 | Q48: =$E48*K48 -> 155608.57 | R48: =$E48*L48 -> 272100.6 | S48: =$E48*M48 -> 0 | T48: =SUM(O48:S48) -> 2280614.8 | V48: 120 | W48: =$V48*I48 -> 0 | X48: =$V48*J48 -> 1852905.6 | Y48: =$V48*K48 -> 155608.57 | Z48: =$V48*L48 -> 272100.6 | AA48: =$V48*M48 -> 0 | AB48: =SUM(W48:AA48) -> 2280614.8 | AE48: =$AD48*I48 -> 0 | AF48: =$AD48*J48 -> 0 | AG48: =$AD48*K48 -> 0 | AH48: =$AD48*L48 -> 0 | AI48: =$AD48*M48 -> 0 | AJ48: =SUM(AE48:AI48) -> 0 | AL48: =IFERROR(VLOOKUP($A48,Itemizado_Piping!C:Q,12,0),0) -> 0 | AM48: =IFERROR(VLOOKUP($A48,Itemizado_Piping!C:Q,13,0),0) -> 0 | AN48: =IFERROR(VLOOKUP($A48,Itemizado_Piping!C:Q,14,0),0) -> 0 | AQ48: =N48*AP48 -> 0
A49: 2.1.1.10.2 | C49: Suministro e Instalación Conductor desnudo blando, clase B, 19 hebras N° 4/0 AWG | D49: m | E49: 560 | G49: 257.6 | H49: =G49+F49 -> 257.6 | J49: 21216.72 | K49: 1781.798 | L49: 3115.6916 | N49: =SUM(I49:M49) -> 26114.21 | O49: =$E49*I49 -> 0 | P49: =$E49*J49 -> 11881363 | Q49: =$E49*K49 -> 997806.9 | R49: =$E49*L49 -> 1744787.3 | S49: =$E49*M49 -> 0 | T49: =SUM(O49:S49) -> 14623957 | V49: 560 | W49: =$V49*I49 -> 0 | X49: =$V49*J49 -> 11881363 | Y49: =$V49*K49 -> 997806.9 | Z49: =$V49*L49 -> 1744787.3 | AA49: =$V49*M49 -> 0 | AB49: =SUM(W49:AA49) -> 14623957 | AE49: =$AD49*I49 -> 0 | AF49: =$AD49*J49 -> 0 | AG49: =$AD49*K49 -> 0 | AH49: =$AD49*L49 -> 0 | AI49: =$AD49*M49 -> 0 | AJ49: =SUM(AE49:AI49) -> 0 | AL49: =IFERROR(VLOOKUP($A49,Itemizado_Piping!C:Q,12,0),0) -> 0 | AM49: =IFERROR(VLOOKUP($A49,Itemizado_Piping!C:Q,13,0),0) -> 0 | AN49: =IFERROR(VLOOKUP($A49,Itemizado_Piping!C:Q,14,0),0) -> 0 | AQ49: =N49*AP49 -> 0
A50: 2.1.1.10.3 | C50: Suministro y Montaje de cámaras de registro | D50: uni | E50: 4 | G50: 24 | H50: =G50+F50 -> 24 | J50: 172652 | K50: 14499.46 | L50: 25354.078 | N50: =SUM(I50:M50) -> 212505.54 | O50: =$E50*I50 -> 0 | P50: =$E50*J50 -> 690608 | Q50: =$E50*K50 -> 57997.842 | R50: =$E50*L50 -> 101416.31 | S50: =$E50*M50 -> 0 | T50: =SUM(O50:S50) -> 850022.15 | V50: 4 | W50: =$V50*I50 -> 0 | X50: =$V50*J50 -> 690608 | Y50: =$V50*K50 -> 57997.842 | Z50: =$V50*L50 -> 101416.31 | AA50: =$V50*M50 -> 0 | AB50: =SUM(W50:AA50) -> 850022.15 | AE50: =$AD50*I50 -> 0 | AF50: =$AD50*J50 -> 0 | AG50: =$AD50*K50 -> 0 | AH50: =$AD50*L50 -> 0 | AI50: =$AD50*M50 -> 0 | AJ50: =SUM(AE50:AI50) -> 0 | AL50: =IFERROR(VLOOKUP($A50,Itemizado_Piping!C:Q,12,0),0) -> 0 | AM50: =IFERROR(VLOOKUP($A50,Itemizado_Piping!C:Q,13,0),0) -> 0 | AN50: =IFERROR(VLOOKUP($A50,Itemizado_Piping!C:Q,14,0),0) -> 0 | AQ50: =N50*AP50 -> 0
A51: 2.1.1.10.4 | C51: Suministro y Montaje de GEL para mejoramiento de resistividad de suelo (Sacos de 14kilos) | D51: uni | E51: 280 | G51: 840 | H51: =G51+F51 -> 840 | J51: 106627 | K51: 8954.6253 | L51: 15658.256 | N51: =SUM(I51:M51) -> 131239.88 | O51: =$E51*I51 -> 0 | P51: =$E51*J51 -> 29855560 | Q51: =$E51*K51 -> 2507295.1 | R51: =$E51*L51 -> 4384311.8 | S51: =$E51*M51 -> 0 | T51: =SUM(O51:S51) -> 36747167 | V51: 280 | W51: =$V51*I51 -> 0 | X51: =$V51*J51 -> 29855560 | Y51: =$V51*K51 -> 2507295.1 | Z51: =$V51*L51 -> 4384311.8 | AA51: =$V51*M51 -> 0 | AB51: =SUM(W51:AA51) -> 36747167 | AE51: =$AD51*I51 -> 0 | AF51: =$AD51*J51 -> 0 | AG51: =$AD51*K51 -> 0 | AH51: =$AD51*L51 -> 0 | AI51: =$AD51*M51 -> 0 | AJ51: =SUM(AE51:AI51) -> 0 | AL51: =IFERROR(VLOOKUP($A51,Itemizado_Piping!C:Q,12,0),0) -> 0 | AM51: =IFERROR(VLOOKUP($A51,Itemizado_Piping!C:Q,13,0),0) -> 0 | AN51: =IFERROR(VLOOKUP($A51,Itemizado_Piping!C:Q,14,0),0) -> 0 | AQ51: =N51*AP51 -> 0
A52: 2.1.1.10.5 | C52: Suministro e Instalación Cables, canalizaciones y materiales menores | D52: gl | E52: 1 | G52: 324.8 | H52: =G52+F52 -> 324.8 | J52: 9576058.7 | K52: 804205.48 | L52: 1406251.5 | N52: =SUM(I52:M52) -> 11786516 | O52: =$E52*I52 -> 0 | P52: =$E52*J52 -> 9576058.7 | Q52: =$E52*K52 -> 804205.48 | R52: =$E52*L52 -> 1406251.5 | S52: =$E52*M52 -> 0 | T52: =SUM(O52:S52) -> 11786516 | V52: 1 | W52: =$V52*I52 -> 0 | X52: =$V52*J52 -> 9576058.7 | Y52: =$V52*K52 -> 804205.48 | Z52: =$V52*L52 -> 1406251.5 | AA52: =$V52*M52 -> 0 | AB52: =SUM(W52:AA52) -> 11786516 | AE52: =$AD52*I52 -> 0 | AF52: =$AD52*J52 -> 0 | AG52: =$AD52*K52 -> 0 | AH52: =$AD52*L52 -> 0 | AI52: =$AD52*M52 -> 0 | AJ52: =SUM(AE52:AI52) -> 0 | AL52: =IFERROR(VLOOKUP($A52,Itemizado_Piping!C:Q,12,0),0) -> 0 | AM52: =IFERROR(VLOOKUP($A52,Itemizado_Piping!C:Q,13,0),0) -> 0 | AN52: =IFERROR(VLOOKUP($A52,Itemizado_Piping!C:Q,14,0),0) -> 0 | AQ52: =N52*AP52 -> 0
A53: 2.1.1.10.6 | C53: Construcción Malla puesta a tierra: moldes soldadura termofusión, cámara de registro, etc. | D53: gl | E53: 1 | G53: 328.3 | H53: =G53+F53 -> 328.3 | J53: 11416994 | K53: 958808.75 | L53: 1676594.2 | N53: =SUM(I53:M53) -> 14052397 | O53: =$E53*I53 -> 0 | P53: =$E53*J53 -> 11416994 | Q53: =$E53*K53 -> 958808.75 | R53: =$E53*L53 -> 1676594.2 | S53: =$E53*M53 -> 0 | T53: =SUM(O53:S53) -> 14052397 | V53: 1 | W53: =$V53*I53 -> 0 | X53: =$V53*J53 -> 11416994 | Y53: =$V53*K53 -> 958808.75 | Z53: =$V53*L53 -> 1676594.2 | AA53: =$V53*M53 -> 0 | AB53: =SUM(W53:AA53) -> 14052397 | AE53: =$AD53*I53 -> 0 | AF53: =$AD53*J53 -> 0 | AG53: =$AD53*K53 -> 0 | AH53: =$AD53*L53 -> 0 | AI53: =$AD53*M53 -> 0 | AJ53: =SUM(AE53:AI53) -> 0 | AL53: =IFERROR(VLOOKUP($A53,Itemizado_Piping!C:Q,12,0),0) -> 0 | AM53: =IFERROR(VLOOKUP($A53,Itemizado_Piping!C:Q,13,0),0) -> 0 | AN53: =IFERROR(VLOOKUP($A53,Itemizado_Piping!C:Q,14,0),0) -> 0 | AQ53: =N53*AP53 -> 0
A54: 2.1.1.11 | C54: Montaje de Gabinetes
A55: 2.1.1.11.1 | C55: Montaje, conexionado de estación GPS repetidora 03622-ZT-1000 de acuerdo a puntos topográficos que se indicarán. incluye su infraestructura civil (para que termine en base de hormigón) de acuerdo a plano 4600020303-06700-221AT-00002. | D55: uni | E55: 1 | G55: 46.866 | H55: =G55+F55 -> 46.866 | J55: 1620607.6 | K55: 136100 | L55: 237987.47 | N55: =SUM(I55:M55) -> 1994695.1 | O55: =$E55*I55 -> 0 | P55: =$E55*J55 -> 1620607.6 | Q55: =$E55*K55 -> 136100 | R55: =$E55*L55 -> 237987.47 | S55: =$E55*M55 -> 0 | T55: =SUM(O55:S55) -> 1994695.1 | V55: 1 | W55: =$V55*I55 -> 0 | X55: =$V55*J55 -> 1620607.6 | Y55: =$V55*K55 -> 136100 | Z55: =$V55*L55 -> 237987.47 | AA55: =$V55*M55 -> 0 | AB55: =SUM(W55:AA55) -> 1994695.1 | AE55: =$AD55*I55 -> 0 | AF55: =$AD55*J55 -> 0 | AG55: =$AD55*K55 -> 0 | AH55: =$AD55*L55 -> 0 | AI55: =$AD55*M55 -> 0 | AJ55: =SUM(AE55:AI55) -> 0 | AL55: =IFERROR(VLOOKUP($A55,Itemizado_Piping!C:Q,12,0),0) -> 0 | AM55: =IFERROR(VLOOKUP($A55,Itemizado_Piping!C:Q,13,0),0) -> 0 | AN55: =IFERROR(VLOOKUP($A55,Itemizado_Piping!C:Q,14,0),0) -> 0 | AQ55: =N55*AP55 -> 0
A56: 2.1.1.11.2 | C56: Suministro, Montaje, conexionado de cámara cctv 3622-NT-031 interior sala 220-SEL-011 incluye cable y accesorios necesarios, puesta en marcha, pruebas y protocolos correspondientes de acuerdo a plano 4600020303-06700-222AT-00001 y 4600020303-06700-HDDAT-00008 | D56: uni | E56: 1 | G56: 37 | H56: =G56+F56 -> 37 | J56: 4918214 | K56: 413035.76 | L56: 722243.49 | N56: =SUM(I56:M56) -> 6053493.2 | O56: =$E56*I56 -> 0 | P56: =$E56*J56 -> 4918214 | Q56: =$E56*K56 -> 413035.76 | R56: =$E56*L56 -> 722243.49 | S56: =$E56*M56 -> 0 | T56: =SUM(O56:S56) -> 6053493.2 | V56: 1 | W56: =$V56*I56 -> 0 | X56: =$V56*J56 -> 4918214 | Y56: =$V56*K56 -> 413035.76 | Z56: =$V56*L56 -> 722243.49 | AA56: =$V56*M56 -> 0 | AB56: =SUM(W56:AA56) -> 6053493.2 | AE56: =$AD56*I56 -> 0 | AF56: =$AD56*J56 -> 0 | AG56: =$AD56*K56 -> 0 | AH56: =$AD56*L56 -> 0 | AI56: =$AD56*M56 -> 0 | AJ56: =SUM(AE56:AI56) -> 0 | AL56: =IFERROR(VLOOKUP($A56,Itemizado_Piping!C:Q,12,0),0) -> 0 | AM56: =IFERROR(VLOOKUP($A56,Itemizado_Piping!C:Q,13,0),0) -> 0 | AN56: =IFERROR(VLOOKUP($A56,Itemizado_Piping!C:Q,14,0),0) -> 0 | AQ56: =N56*AP56 -> 0
A57: 2.1.1.11.3 | C57: Suministro, Montaje, conexionado de Tablero de instrumentación 220-TDI-011 @ 013 incluye todo lo interior de acuerdo a plano 4600020303-06700-202AT-00001 | D57: uni | E57: 3 | G57: 210 | H57: =G57+F57 -> 210 | J57: 3475074 | K57: 291839.64 | L57: 510317.27 | N57: =SUM(I57:M57) -> 4277230.9 | O57: =$E57*I57 -> 0 | P57: =$E57*J57 -> 10425222 | Q57: =$E57*K57 -> 875518.93 | R57: =$E57*L57 -> 1530951.8 | S57: =$E57*M57 -> 0 | T57: =SUM(O57:S57) -> 12831693 | V57: 3 | W57: =$V57*I57 -> 0 | X57: =$V57*J57 -> 10425222 | Y57: =$V57*K57 -> 875518.93 | Z57: =$V57*L57 -> 1530951.8 | AA57: =$V57*M57 -> 0 | AB57: =SUM(W57:AA57) -> 12831693 | AE57: =$AD57*I57 -> 0 | AF57: =$AD57*J57 -> 0 | AG57: =$AD57*K57 -> 0 | AH57: =$AD57*L57 -> 0 | AI57: =$AD57*M57 -> 0 | AJ57: =SUM(AE57:AI57) -> 0 | AL57: =IFERROR(VLOOKUP($A57,Itemizado_Piping!C:Q,12,0),0) -> 0 | AM57: =IFERROR(VLOOKUP($A57,Itemizado_Piping!C:Q,13,0),0) -> 0 | AN57: =IFERROR(VLOOKUP($A57,Itemizado_Piping!C:Q,14,0),0) -> 0 | AQ57: =N57*AP57 -> 0
A58: 2.1.1.11.4 | C58: Suministro, Montaje, conexionado de Gabinete de comunicaciones 6340-COM-911 en Sala LP3 existente , incluye todo lo interior de acuerdo a plano 4600020303-06700-220AT-00001 y 4600020303-06700-HDDAT-00005 | D58: uni | E58: 1 | G58: 55 | H58: =G58+F58 -> 55 | J58: 1462174 | K58: 122794.6 | L58: 214721.37 | N58: =SUM(I58:M58) -> 1799690 | O58: =$E58*I58 -> 0 | P58: =$E58*J58 -> 1462174 | Q58: =$E58*K58 -> 122794.6 | R58: =$E58*L58 -> 214721.37 | S58: =$E58*M58 -> 0 | T58: =SUM(O58:S58) -> 1799690 | V58: 1 | W58: =$V58*I58 -> 0 | X58: =$V58*J58 -> 1462174 | Y58: =$V58*K58 -> 122794.6 | Z58: =$V58*L58 -> 214721.37 | AA58: =$V58*M58 -> 0 | AB58: =SUM(W58:AA58) -> 1799690 | AE58: =$AD58*I58 -> 0 | AF58: =$AD58*J58 -> 0 | AG58: =$AD58*K58 -> 0 | AH58: =$AD58*L58 -> 0 | AI58: =$AD58*M58 -> 0 | AJ58: =SUM(AE58:AI58) -> 0 | AL58: =IFERROR(VLOOKUP($A58,Itemizado_Piping!C:Q,12,0),0) -> 0 | AM58: =IFERROR(VLOOKUP($A58,Itemizado_Piping!C:Q,13,0),0) -> 0 | AN58: =IFERROR(VLOOKUP($A58,Itemizado_Piping!C:Q,14,0),0) -> 0 | AQ58: =N58*AP58 -> 0
A59: 2.1.1.11.5 | C59: Suministro, Montaje, conexionado, licencias, protocolos de prueba de cámaras que se configuran en los servidores existentes, puesta en marcha, pruebas y protocolos correspondientes. | D59: uni | E59: 27 | G59: 162 | H59: =G59+F59 -> 162 | J59: 388060 | K59: 32589.606 | L59: 56986.908 | N59: =SUM(I59:M59) -> 477636.51 | O59: =$E59*I59 -> 0 | P59: =$E59*J59 -> 10477620 | Q59: =$E59*K59 -> 879919.36 | R59: =$E59*L59 -> 1538646.5 | S59: =$E59*M59 -> 0 | T59: =SUM(O59:S59) -> 12896186 | V59: 27 | W59: =$V59*I59 -> 0 | X59: =$V59*J59 -> 10477620 | Y59: =$V59*K59 -> 879919.36 | Z59: =$V59*L59 -> 1538646.5 | AA59: =$V59*M59 -> 0 | AB59: =SUM(W59:AA59) -> 12896186 | AE59: =$AD59*I59 -> 0 | AF59: =$AD59*J59 -> 0 | AG59: =$AD59*K59 -> 0 | AH59: =$AD59*L59 -> 0 | AI59: =$AD59*M59 -> 0 | AJ59: =SUM(AE59:AI59) -> 0 | AL59: =IFERROR(VLOOKUP($A59,Itemizado_Piping!C:Q,12,0),0) -> 0 | AM59: =IFERROR(VLOOKUP($A59,Itemizado_Piping!C:Q,13,0),0) -> 0 | AN59: =IFERROR(VLOOKUP($A59,Itemizado_Piping!C:Q,14,0),0) -> 0 | AQ59: =N59*AP59 -> 0
A60: 2.1.1.11.6 | C60: Suministro, Montaje, conexionado de Servidor Storage 6700-STG-001 en Sala de Datos VTAP existente , incluye todo lo interior de acuerdo a plano 4600020303-06700-222AT-00001 y 4600020303-06700-HDDAT-00011 | D60: uni | E60: 1 | G60: 30 | H60: =G60+F60 -> 30 | J60: 17512580 | K60: 1470721.2 | L60: 2571735.8 | N60: =SUM(I60:M60) -> 21555037 | O60: =$E60*I60 -> 0 | P60: =$E60*J60 -> 17512580 | Q60: =$E60*K60 -> 1470721.2 | R60: =$E60*L60 -> 2571735.8 | S60: =$E60*M60 -> 0 | T60: =SUM(O60:S60) -> 21555037 | V60: 1 | W60: =$V60*I60 -> 0 | X60: =$V60*J60 -> 17512580 | Y60: =$V60*K60 -> 1470721.2 | Z60: =$V60*L60 -> 2571735.8 | AA60: =$V60*M60 -> 0 | AB60: =SUM(W60:AA60) -> 21555037 | AE60: =$AD60*I60 -> 0 | AF60: =$AD60*J60 -> 0 | AG60: =$AD60*K60 -> 0 | AH60: =$AD60*L60 -> 0 | AI60: =$AD60*M60 -> 0 | AJ60: =SUM(AE60:AI60) -> 0 | AL60: =IFERROR(VLOOKUP($A60,Itemizado_Piping!C:Q,12,0),0) -> 0 | AM60: =IFERROR(VLOOKUP($A60,Itemizado_Piping!C:Q,13,0),0) -> 0 | AN60: =IFERROR(VLOOKUP($A60,Itemizado_Piping!C:Q,14,0),0) -> 0 | AQ60: =N60*AP60 -> 0
A61: 2.1.1.11.7 | C61: Suministro, tendido, empalme (fusionado), protocolos de prueba, colocación de pictail en cada pelo, de fibra óptica 48 FO SM ADSS ,varios tramos, considerar referencia 4600020303-06700-CUBCO-00001 y 4600020303-06700-LSTII-00011, usar lo necesario para tender de acuerdo a norma y lugar que se coloca. | D61: m | E61: 6850 | G61: 3082.5 | H61: =G61+F61 -> 3082.5 | J61: 18403.4 | K61: 1545.533 | L61: 2702.5534 | N61: =SUM(I61:M61) -> 22651.486 | O61: =$E61*I61 -> 0 | P61: =$E61*J61 -> 1.2606329e+08 | Q61: =$E61*K61 -> 10586901 | R61: =$E61*L61 -> 18512491 | S61: =$E61*M61 -> 0 | T61: =SUM(O61:S61) -> 1.5516268e+08 | V61: 6850 | W61: =$V61*I61 -> 0 | X61: =$V61*J61 -> 1.2606329e+08 | Y61: =$V61*K61 -> 10586901 | Z61: =$V61*L61 -> 18512491 | AA61: =$V61*M61 -> 0 | AB61: =SUM(W61:AA61) -> 1.5516268e+08 | AE61: =$AD61*I61 -> 0 | AF61: =$AD61*J61 -> 0 | AG61: =$AD61*K61 -> 0 | AH61: =$AD61*L61 -> 0 | AI61: =$AD61*M61 -> 0 | AJ61: =SUM(AE61:AI61) -> 0 | AL61: =IFERROR(VLOOKUP($A61,Itemizado_Piping!C:Q,12,0),0) -> 0 | AM61: =IFERROR(VLOOKUP($A61,Itemizado_Piping!C:Q,13,0),0) -> 0 | AN61: =IFERROR(VLOOKUP($A61,Itemizado_Piping!C:Q,14,0),0) -> 0 | AQ61: =N61*AP61 -> 0
A62: 2.1.1.11.8 | C62: Suministro, tendido, empalme (fusionado), protocolos de prueba, colocación de pictail en cada pelo, de fibra óptica 24 FO SM ADSS ,varios tramos, considerar referencia 4600020303-06700-CUBCO-00001 y 4600020303-06700-LSTII-00011, usar lo necesario para tender de acuerdo a norma y lugar que se coloca. | D62: m | E62: 11000 | G62: 4312 | H62: =G62+F62 -> 4312 | J62: 14856.111 | K62: 1247.6287 | L62: 2181.6313 | N62: =SUM(I62:M62) -> 18285.371 | O62: =$E62*I62 -> 0 | P62: =$E62*J62 -> 163417221 | Q62: =$E62*K62 -> 13723916 | R62: =$E62*L62 -> 23997944 | S62: =$E62*M62 -> 0 | T62: =SUM(O62:S62) -> 2.0113908e+08 | V62: 11000 | W62: =$V62*I62 -> 0 | X62: =$V62*J62 -> 163417221 | Y62: =$V62*K62 -> 13723916 | Z62: =$V62*L62 -> 23997944 | AA62: =$V62*M62 -> 0 | AB62: =SUM(W62:AA62) -> 2.0113908e+08 | AE62: =$AD62*I62 -> 0 | AF62: =$AD62*J62 -> 0 | AG62: =$AD62*K62 -> 0 | AH62: =$AD62*L62 -> 0 | AI62: =$AD62*M62 -> 0 | AJ62: =SUM(AE62:AI62) -> 0 | AL62: =IFERROR(VLOOKUP($A62,Itemizado_Piping!C:Q,12,0),0) -> 0 | AM62: =IFERROR(VLOOKUP($A62,Itemizado_Piping!C:Q,13,0),0) -> 0 | AN62: =IFERROR(VLOOKUP($A62,Itemizado_Piping!C:Q,14,0),0) -> 0 | AQ62: =N62*AP62 -> 0
A63: 2.1.1.11.9 | C63: Suministro, tendido, conexionado,de cables de instrumentación, control, y fuerza de 120VAC o 220 VAC para alimentación de equipos o tableros, varios lugares | D63: m | E63: 10000 | G63: 2314 | H63: =G63+F63 -> 2314 | J63: 7724.467 | K63: 648.70725 | L63: 1134.3439 | N63: =SUM(I63:M63) -> 9507.5181 | O63: =$E63*I63 -> 0 | P63: =$E63*J63 -> 77244670 | Q63: =$E63*K63 -> 6487072.5 | R63: =$E63*L63 -> 11343439 | S63: =$E63*M63 -> 0 | T63: =SUM(O63:S63) -> 95075181 | V63: 10000 | W63: =$V63*I63 -> 0 | X63: =$V63*J63 -> 77244670 | Y63: =$V63*K63 -> 6487072.5 | Z63: =$V63*L63 -> 11343439 | AA63: =$V63*M63 -> 0 | AB63: =SUM(W63:AA63) -> 95075181 | AE63: =$AD63*I63 -> 0 | AF63: =$AD63*J63 -> 0 | AG63: =$AD63*K63 -> 0 | AH63: =$AD63*L63 -> 0 | AI63: =$AD63*M63 -> 0 | AJ63: =SUM(AE63:AI63) -> 0 | AL63: =IFERROR(VLOOKUP($A63,Itemizado_Piping!C:Q,12,0),0) -> 0 | AM63: =IFERROR(VLOOKUP($A63,Itemizado_Piping!C:Q,13,0),0) -> 0 | AN63: =IFERROR(VLOOKUP($A63,Itemizado_Piping!C:Q,14,0),0) -> 0 | AQ63: =N63*AP63 -> 0
A64: 2.1.1.11.10 | C64: Suministro, Montaje, conexionado de dos switches de comunicación en Sala de Datos VTAP existente , incluye todo lo interior de acuerdo a plano 4600020303-06700-222AT-00001 | D64: uni | E64: 2 | G64: 110 | H64: =G64+F64 -> 110 | J64: 13670254 | K64: 1148039.5 | L64: 2007487.2 | N64: =SUM(I64:M64) -> 16825781 | O64: =$E64*I64 -> 0 | P64: =$E64*J64 -> 27340508 | Q64: =$E64*K64 -> 2296078.9 | R64: =$E64*L64 -> 4014974.5 | S64: =$E64*M64 -> 0 | T64: =SUM(O64:S64) -> 33651561 | V64: 2 | W64: =$V64*I64 -> 0 | X64: =$V64*J64 -> 27340508 | Y64: =$V64*K64 -> 2296078.9 | Z64: =$V64*L64 -> 4014974.5 | AA64: =$V64*M64 -> 0 | AB64: =SUM(W64:AA64) -> 33651561 | AE64: =$AD64*I64 -> 0 | AF64: =$AD64*J64 -> 0 | AG64: =$AD64*K64 -> 0 | AH64: =$AD64*L64 -> 0 | AI64: =$AD64*M64 -> 0 | AJ64: =SUM(AE64:AI64) -> 0 | AL64: =IFERROR(VLOOKUP($A64,Itemizado_Piping!C:Q,12,0),0) -> 0 | AM64: =IFERROR(VLOOKUP($A64,Itemizado_Piping!C:Q,13,0),0) -> 0 | AN64: =IFERROR(VLOOKUP($A64,Itemizado_Piping!C:Q,14,0),0) -> 0 | AQ64: =N64*AP64 -> 0
A65: 2.1.1.11.11 | C65: Suministro, Montaje, conexionado, licencias, protocolos de prueba de estaciones de monitoreo (solo salas CO2), incluye todo lo interior de acuerdo a plano 4600020303-06700-222AT-00001 | D65: uni | E65: 1 | G65: 10 | H65: =G65+F65 -> 10 | J65: 9267980 | K65: 778332.77 | L65: 1361009.9 | N65: =SUM(I65:M65) -> 11407323 | O65: =$E65*I65 -> 0 | P65: =$E65*J65 -> 9267980 | Q65: =$E65*K65 -> 778332.77 | R65: =$E65*L65 -> 1361009.9 | S65: =$E65*M65 -> 0 | T65: =SUM(O65:S65) -> 11407323 | V65: 1 | W65: =$V65*I65 -> 0 | X65: =$V65*J65 -> 9267980 | Y65: =$V65*K65 -> 778332.77 | Z65: =$V65*L65 -> 1361009.9 | AA65: =$V65*M65 -> 0 | AB65: =SUM(W65:AA65) -> 11407323 | AE65: =$AD65*I65 -> 0 | AF65: =$AD65*J65 -> 0 | AG65: =$AD65*K65 -> 0 | AH65: =$AD65*L65 -> 0 | AI65: =$AD65*M65 -> 0 | AJ65: =SUM(AE65:AI65) -> 0 | AL65: =IFERROR(VLOOKUP($A65,Itemizado_Piping!C:Q,12,0),0) -> 0 | AM65: =IFERROR(VLOOKUP($A65,Itemizado_Piping!C:Q,13,0),0) -> 0 | AN65: =IFERROR(VLOOKUP($A65,Itemizado_Piping!C:Q,14,0),0) -> 0 | AQ65: =N65*AP65 -> 0
A66: 2.1.1.13 | C66: Cambio Trazado Línea 23 kV EXISTENTE por BANCO DUCTO
A67: 2.1.1.13.1 | C67: Tie-IN Desenergización y Energización Línea 23 kV Existente | D67: gl | E67: 1 | G67: 40 | H67: =G67+F67 -> 40 | J67: 9881680 | K67: 829871.82 | L67: 1451132.3 | N67: =SUM(I67:M67) -> 12162684 | O67: =$E67*I67 -> 0 | P67: =$E67*J67 -> 9881680 | Q67: =$E67*K67 -> 829871.82 | R67: =$E67*L67 -> 1451132.3 | S67: =$E67*M67 -> 0 | T67: =SUM(O67:S67) -> 12162684 | V67: 1 | W67: =$V67*I67 -> 0 | X67: =$V67*J67 -> 9881680 | Y67: =$V67*K67 -> 829871.82 | Z67: =$V67*L67 -> 1451132.3 | AA67: =$V67*M67 -> 0 | AB67: =SUM(W67:AA67) -> 12162684 | AE67: =$AD67*I67 -> 0 | AF67: =$AD67*J67 -> 0 | AG67: =$AD67*K67 -> 0 | AH67: =$AD67*L67 -> 0 | AI67: =$AD67*M67 -> 0 | AJ67: =SUM(AE67:AI67) -> 0 | AL67: =IFERROR(VLOOKUP($A67,Itemizado_Piping!C:Q,12,0),0) -> 0 | AM67: =IFERROR(VLOOKUP($A67,Itemizado_Piping!C:Q,13,0),0) -> 0 | AN67: =IFERROR(VLOOKUP($A67,Itemizado_Piping!C:Q,14,0),0) -> 0 | AQ67: =N67*AP67 -> 0
A68: 2.1.1.13.2 | C68: Retiro y Desarme Postes de 18 metros (1 portal y 4 postes de suspensión, etc) | D68: gl | E68: 1 | H68: =G68+F68 -> 0 | J68: 18475000 | K68: 1551546.1 | L68: 2713067.9 | N68: =SUM(I68:M68) -> 22739614 | O68: =$E68*I68 -> 0 | P68: =$E68*J68 -> 18475000 | Q68: =$E68*K68 -> 1551546.1 | R68: =$E68*L68 -> 2713067.9 | S68: =$E68*M68 -> 0 | T68: =SUM(O68:S68) -> 22739614 | V68: 1 | W68: =$V68*I68 -> 0 | X68: =$V68*J68 -> 18475000 | Y68: =$V68*K68 -> 1551546.1 | Z68: =$V68*L68 -> 2713067.9 | AA68: =$V68*M68 -> 0 | AB68: =SUM(W68:AA68) -> 22739614 | AE68: =$AD68*I68 -> 0 | AF68: =$AD68*J68 -> 0 | AG68: =$AD68*K68 -> 0 | AH68: =$AD68*L68 -> 0 | AI68: =$AD68*M68 -> 0 | AJ68: =SUM(AE68:AI68) -> 0 | AL68: =IFERROR(VLOOKUP($A68,Itemizado_Piping!C:Q,12,0),0) -> 0 | AM68: =IFERROR(VLOOKUP($A68,Itemizado_Piping!C:Q,13,0),0) -> 0 | AN68: =IFERROR(VLOOKUP($A68,Itemizado_Piping!C:Q,14,0),0) -> 0 | AQ68: =N68*AP68 -> 0
A69: 2.1.1.13.3 | C69: Suministro y Montaje Poste Remate (incluye ferreteria P. Remate y Suspensión) | D69: uni | E69: 2 | H69: =G69+F69 -> 0 | J69: 19995000 | K69: 1679197 | L69: 2936281 | N69: =SUM(I69:M69) -> 24610478 | O69: =$E69*I69 -> 0 | P69: =$E69*J69 -> 39990000 | Q69: =$E69*K69 -> 3358393.9 | R69: =$E69*L69 -> 5872562.1 | S69: =$E69*M69 -> 0 | T69: =SUM(O69:S69) -> 49220956 | V69: 2 | W69: =$V69*I69 -> 0 | X69: =$V69*J69 -> 39990000 | Y69: =$V69*K69 -> 3358393.9 | Z69: =$V69*L69 -> 5872562.1 | AA69: =$V69*M69 -> 0 | AB69: =SUM(W69:AA69) -> 49220956 | AE69: =$AD69*I69 -> 0 | AF69: =$AD69*J69 -> 0 | AG69: =$AD69*K69 -> 0 | AH69: =$AD69*L69 -> 0 | AI69: =$AD69*M69 -> 0 | AJ69: =SUM(AE69:AI69) -> 0 | AL69: =IFERROR(VLOOKUP($A69,Itemizado_Piping!C:Q,12,0),0) -> 0 | AM69: =IFERROR(VLOOKUP($A69,Itemizado_Piping!C:Q,13,0),0) -> 0 | AN69: =IFERROR(VLOOKUP($A69,Itemizado_Piping!C:Q,14,0),0) -> 0 | AQ69: =N69*AP69 -> 0
A70: 2.1.1.13.4 | C70: Construcción Banco de Ductos reforzado para tránsito pesado de 600x500 mm | D70: m | E70: 250 | G70: 4356.325 | H70: =G70+F70 -> 4356.325 | J70: 815385.82 | K70: 68476.789 | L70: 119740.03 | N70: =SUM(I70:M70) -> 1003602.6 | O70: =$E70*I70 -> 0 | P70: =$E70*J70 -> 203846455 | Q70: =$E70*K70 -> 17119197 | R70: =$E70*L70 -> 29935008 | S70: =$E70*M70 -> 0 | T70: =SUM(O70:S70) -> 2.5090066e+08 | V70: 250 | W70: =$V70*I70 -> 0 | X70: =$V70*J70 -> 203846455 | Y70: =$V70*K70 -> 17119197 | Z70: =$V70*L70 -> 29935008 | AA70: =$V70*M70 -> 0 | AB70: =SUM(W70:AA70) -> 2.5090066e+08 | AE70: =$AD70*I70 -> 0 | AF70: =$AD70*J70 -> 0 | AG70: =$AD70*K70 -> 0 | AH70: =$AD70*L70 -> 0 | AI70: =$AD70*M70 -> 0 | AJ70: =SUM(AE70:AI70) -> 0 | AL70: =IFERROR(VLOOKUP($A70,Itemizado_Piping!C:Q,12,0),0) -> 0 | AM70: =IFERROR(VLOOKUP($A70,Itemizado_Piping!C:Q,13,0),0) -> 0 | AN70: =IFERROR(VLOOKUP($A70,Itemizado_Piping!C:Q,14,0),0) -> 0 | AQ70: =N70*AP70 -> 0
A71: 2.1.1.13.5 | C71: Suministro y Montaje de conduit PVC 4" SCh-80 | D71: m | E71: 240 | G71: 408 | H71: =G71+F71 -> 408 | J71: 54215.158 | K71: 4553.0347 | L71: 7961.5374 | N71: =SUM(I71:M71) -> 66729.73 | O71: =$E71*I71 -> 0 | P71: =$E71*J71 -> 13011638 | Q71: =$E71*K71 -> 1092728.3 | R71: =$E71*L71 -> 1910769 | S71: =$E71*M71 -> 0 | T71: =SUM(O71:S71) -> 16015135 | V71: 240 | W71: =$V71*I71 -> 0 | X71: =$V71*J71 -> 13011638 | Y71: =$V71*K71 -> 1092728.3 | Z71: =$V71*L71 -> 1910769 | AA71: =$V71*M71 -> 0 | AB71: =SUM(W71:AA71) -> 16015135 | AE71: =$AD71*I71 -> 0 | AF71: =$AD71*J71 -> 0 | AG71: =$AD71*K71 -> 0 | AH71: =$AD71*L71 -> 0 | AI71: =$AD71*M71 -> 0 | AJ71: =SUM(AE71:AI71) -> 0 | AL71: =IFERROR(VLOOKUP($A71,Itemizado_Piping!C:Q,12,0),0) -> 0 | AM71: =IFERROR(VLOOKUP($A71,Itemizado_Piping!C:Q,13,0),0) -> 0 | AN71: =IFERROR(VLOOKUP($A71,Itemizado_Piping!C:Q,14,0),0) -> 0 | AQ71: =N71*AP71 -> 0
A72: 2.1.1.13.6 | C72: Suministro y Montaje de conduit PVC 2" SCh-80 | D72: m | E72: 240 | G72: 432 | H72: =G72+F72 -> 432 | J72: 48083.04 | K72: 4038.0542 | L72: 7061.0312 | N72: =SUM(I72:M72) -> 59182.125 | O72: =$E72*I72 -> 0 | P72: =$E72*J72 -> 11539930 | Q72: =$E72*K72 -> 969133.01 | R72: =$E72*L72 -> 1694647.5 | S72: =$E72*M72 -> 0 | T72: =SUM(O72:S72) -> 14203710 | V72: 240 | W72: =$V72*I72 -> 0 | X72: =$V72*J72 -> 11539930 | Y72: =$V72*K72 -> 969133.01 | Z72: =$V72*L72 -> 1694647.5 | AA72: =$V72*M72 -> 0 | AB72: =SUM(W72:AA72) -> 14203710 | AE72: =$AD72*I72 -> 0 | AF72: =$AD72*J72 -> 0 | AG72: =$AD72*K72 -> 0 | AH72: =$AD72*L72 -> 0 | AI72: =$AD72*M72 -> 0 | AJ72: =SUM(AE72:AI72) -> 0 | AL72: =IFERROR(VLOOKUP($A72,Itemizado_Piping!C:Q,12,0),0) -> 0 | AM72: =IFERROR(VLOOKUP($A72,Itemizado_Piping!C:Q,13,0),0) -> 0 | AN72: =IFERROR(VLOOKUP($A72,Itemizado_Piping!C:Q,14,0),0) -> 0 | AQ72: =N72*AP72 -> 0
A73: 2.1.1.2 | C73: Estructuras Metálicas
A74: 2.1.1.2.1 | C74: Suministro y Montaje Cerco | D74: m | E74: 82 | G74: 237.554 | H74: =G74+F74 -> 237.554 | J74: 114509.76 | K74: 9616.6275 | L74: 16815.846 | N74: =SUM(I74:M74) -> 140942.24 | O74: =$E74*I74 -> 0 | P74: =$E74*J74 -> 9389800.6 | Q74: =$E74*K74 -> 788563.45 | R74: =$E74*L74 -> 1378899.4 | S74: =$E74*M74 -> 0 | T74: =SUM(O74:S74) -> 11557263 | V74: 82 | W74: =$V74*I74 -> 0 | X74: =$V74*J74 -> 9389800.6 | Y74: =$V74*K74 -> 788563.45 | Z74: =$V74*L74 -> 1378899.4 | AA74: =$V74*M74 -> 0 | AB74: =SUM(W74:AA74) -> 11557263 | AE74: =$AD74*I74 -> 0 | AF74: =$AD74*J74 -> 0 | AG74: =$AD74*K74 -> 0 | AH74: =$AD74*L74 -> 0 | AI74: =$AD74*M74 -> 0 | AJ74: =SUM(AE74:AI74) -> 0 | AL74: =IFERROR(VLOOKUP($A74,Itemizado_Piping!C:Q,12,0),0) -> 0 | AM74: =IFERROR(VLOOKUP($A74,Itemizado_Piping!C:Q,13,0),0) -> 0 | AN74: =IFERROR(VLOOKUP($A74,Itemizado_Piping!C:Q,14,0),0) -> 0 | AQ74: =N74*AP74 -> 0
A75: 2.1.1.2.2 | C75: Suministro y Montaje Portones | D75: uni | E75: 4 | G75: 750 | H75: =G75+F75 -> 750 | J75: 6567725.2 | K75: 551563.1 | L75: 964475.46 | N75: =SUM(I75:M75) -> 8083763.7 | O75: =$E75*I75 -> 0 | P75: =$E75*J75 -> 26270901 | Q75: =$E75*K75 -> 2206252.4 | R75: =$E75*L75 -> 3857901.9 | S75: =$E75*M75 -> 0 | T75: =SUM(O75:S75) -> 32335055 | V75: 4 | W75: =$V75*I75 -> 0 | X75: =$V75*J75 -> 26270901 | Y75: =$V75*K75 -> 2206252.4 | Z75: =$V75*L75 -> 3857901.9 | AA75: =$V75*M75 -> 0 | AB75: =SUM(W75:AA75) -> 32335055 | AE75: =$AD75*I75 -> 0 | AF75: =$AD75*J75 -> 0 | AG75: =$AD75*K75 -> 0 | AH75: =$AD75*L75 -> 0 | AI75: =$AD75*M75 -> 0 | AJ75: =SUM(AE75:AI75) -> 0 | AL75: =IFERROR(VLOOKUP($A75,Itemizado_Piping!C:Q,12,0),0) -> 0 | AM75: =IFERROR(VLOOKUP($A75,Itemizado_Piping!C:Q,13,0),0) -> 0 | AN75: =IFERROR(VLOOKUP($A75,Itemizado_Piping!C:Q,14,0),0) -> 0 | AQ75: =N75*AP75 -> 0
A76: 2.1.1.2.3 | C76: Suministro y Montaje Parrilla de Piso ARS 6 | D76: m2 | E76: 13 | G76: 39.819 | H76: =G76+F76 -> 39.819 | J76: 110481.45 | K76: 9278.3256 | L76: 16224.286 | N76: =SUM(I76:M76) -> 135984.07 | O76: =$E76*I76 -> 0 | P76: =$E76*J76 -> 1436258.9 | Q76: =$E76*K76 -> 120618.23 | R76: =$E76*L76 -> 210915.72 | S76: =$E76*M76 -> 0 | T76: =SUM(O76:S76) -> 1767792.9 | V76: 13 | W76: =$V76*I76 -> 0 | X76: =$V76*J76 -> 1436258.9 | Y76: =$V76*K76 -> 120618.23 | Z76: =$V76*L76 -> 210915.72 | AA76: =$V76*M76 -> 0 | AB76: =SUM(W76:AA76) -> 1767792.9 | AE76: =$AD76*I76 -> 0 | AF76: =$AD76*J76 -> 0 | AG76: =$AD76*K76 -> 0 | AH76: =$AD76*L76 -> 0 | AI76: =$AD76*M76 -> 0 | AJ76: =SUM(AE76:AI76) -> 0 | AL76: =IFERROR(VLOOKUP($A76,Itemizado_Piping!C:Q,12,0),0) -> 0 | AM76: =IFERROR(VLOOKUP($A76,Itemizado_Piping!C:Q,13,0),0) -> 0 | AN76: =IFERROR(VLOOKUP($A76,Itemizado_Piping!C:Q,14,0),0) -> 0 | AQ76: =N76*AP76 -> 0
A77: 2.1.1.2.4 | C77: Suministro y Montaje Estructura Metálica Liviana 0 a 30 Kg/m | D77: kg | E77: 1044 | G77: 130.5 | H77: =G77+F77 -> 130.5 | J77: 4388.659 | K77: 368.56328 | L77: 644.47793 | N77: =SUM(I77:M77) -> 5401.7002 | O77: =$E77*I77 -> 0 | P77: =$E77*J77 -> 4581760 | Q77: =$E77*K77 -> 384780.07 | R77: =$E77*L77 -> 672834.96 | S77: =$E77*M77 -> 0 | T77: =SUM(O77:S77) -> 5639375 | V77: 1044 | W77: =$V77*I77 -> 0 | X77: =$V77*J77 -> 4581760 | Y77: =$V77*K77 -> 384780.07 | Z77: =$V77*L77 -> 672834.96 | AA77: =$V77*M77 -> 0 | AB77: =SUM(W77:AA77) -> 5639375 | AE77: =$AD77*I77 -> 0 | AF77: =$AD77*J77 -> 0 | AG77: =$AD77*K77 -> 0 | AH77: =$AD77*L77 -> 0 | AI77: =$AD77*M77 -> 0 | AJ77: =SUM(AE77:AI77) -> 0 | AL77: =IFERROR(VLOOKUP($A77,Itemizado_Piping!C:Q,12,0),0) -> 0 | AM77: =IFERROR(VLOOKUP($A77,Itemizado_Piping!C:Q,13,0),0) -> 0 | AN77: =IFERROR(VLOOKUP($A77,Itemizado_Piping!C:Q,14,0),0) -> 0 | AQ77: =N77*AP77 -> 0
A78: 2.1.1.2.5 | C78: Suministro y Montaje Estructura Metálica Mediana 30 a 60 kg/m | D78: kg | E78: 651 | G78: 69.006 | H78: =G78+F78 -> 69.006 | J78: 3723.124 | K78: 312.67109 | L78: 546.74361 | N78: =SUM(I78:M78) -> 4582.5387 | O78: =$E78*I78 -> 0 | P78: =$E78*J78 -> 2423753.7 | Q78: =$E78*K78 -> 203548.88 | R78: =$E78*L78 -> 355930.09 | S78: =$E78*M78 -> 0 | T78: =SUM(O78:S78) -> 2983232.7 | V78: 651 | W78: =$V78*I78 -> 0 | X78: =$V78*J78 -> 2423753.7 | Y78: =$V78*K78 -> 203548.88 | Z78: =$V78*L78 -> 355930.09 | AA78: =$V78*M78 -> 0 | AB78: =SUM(W78:AA78) -> 2983232.7 | AE78: =$AD78*I78 -> 0 | AF78: =$AD78*J78 -> 0 | AG78: =$AD78*K78 -> 0 | AH78: =$AD78*L78 -> 0 | AI78: =$AD78*M78 -> 0 | AJ78: =SUM(AE78:AI78) -> 0 | AL78: =IFERROR(VLOOKUP($A78,Itemizado_Piping!C:Q,12,0),0) -> 0 | AM78: =IFERROR(VLOOKUP($A78,Itemizado_Piping!C:Q,13,0),0) -> 0 | AN78: =IFERROR(VLOOKUP($A78,Itemizado_Piping!C:Q,14,0),0) -> 0 | AQ78: =N78*AP78 -> 0
A79: 2.1.1.2.6 | C79: Suministro y Montaje de Barandas de acceso para la Sala Eléctrica | D79: m | E79: 70 | G79: 238 | H79: =G79+F79 -> 238 | J79: 118759.6 | K79: 9973.5312 | L79: 17439.938 | N79: =SUM(I79:M79) -> 146173.07 | O79: =$E79*I79 -> 0 | P79: =$E79*J79 -> 8313171.9 | Q79: =$E79*K79 -> 698147.19 | R79: =$E79*L79 -> 1220795.7 | S79: =$E79*M79 -> 0 | T79: =SUM(O79:S79) -> 10232115 | V79: 70 | W79: =$V79*I79 -> 0 | X79: =$V79*J79 -> 8313171.9 | Y79: =$V79*K79 -> 698147.19 | Z79: =$V79*L79 -> 1220795.7 | AA79: =$V79*M79 -> 0 | AB79: =SUM(W79:AA79) -> 10232115 | AE79: =$AD79*I79 -> 0 | AF79: =$AD79*J79 -> 0 | AG79: =$AD79*K79 -> 0 | AH79: =$AD79*L79 -> 0 | AI79: =$AD79*M79 -> 0 | AJ79: =SUM(AE79:AI79) -> 0 | AL79: =IFERROR(VLOOKUP($A79,Itemizado_Piping!C:Q,12,0),0) -> 0 | AM79: =IFERROR(VLOOKUP($A79,Itemizado_Piping!C:Q,13,0),0) -> 0 | AN79: =IFERROR(VLOOKUP($A79,Itemizado_Piping!C:Q,14,0),0) -> 0 | AQ79: =N79*AP79 -> 0
A80: 2.1.1.3 | C80: Equipos Eléctricos
A81: 2.1.1.3.1 | C81: Montaje Sala Eléctrica prefabricada 27 x 6 x 3,5 m - 220-SEL-011 | D81: uni | E81: 1 | G81: 1402 | H81: =G81+F81 -> 1402 | J81: 40651144 | K81: 3413917.3 | L81: 5969651.6 | N81: =SUM(I81:M81) -> 50034713 | O81: =$E81*I81 -> 0 | P81: =$E81*J81 -> 40651144 | Q81: =$E81*K81 -> 3413917.3 | R81: =$E81*L81 -> 5969651.6 | S81: =$E81*M81 -> 0 | T81: =SUM(O81:S81) -> 50034713 | V81: 1 | W81: =$V81*I81 -> 0 | X81: =$V81*J81 -> 40651144 | Y81: =$V81*K81 -> 3413917.3 | Z81: =$V81*L81 -> 5969651.6 | AA81: =$V81*M81 -> 0 | AB81: =SUM(W81:AA81) -> 50034713 | AE81: =$AD81*I81 -> 0 | AF81: =$AD81*J81 -> 0 | AG81: =$AD81*K81 -> 0 | AH81: =$AD81*L81 -> 0 | AI81: =$AD81*M81 -> 0 | AJ81: =SUM(AE81:AI81) -> 0 | AL81: =IFERROR(VLOOKUP($A81,Itemizado_Piping!C:Q,12,0),0) -> 0 | AM81: =IFERROR(VLOOKUP($A81,Itemizado_Piping!C:Q,13,0),0) -> 0 | AN81: =IFERROR(VLOOKUP($A81,Itemizado_Piping!C:Q,14,0),0) -> 0 | AQ81: =N81*AP81 -> 0
A82: 2.1.1.3.2 | C82: Montaje Equipo Aire Acondicionado, Exterior | D82: uni | E82: 1 | G82: 120 | H82: =G82+F82 -> 120 | J82: 3113088 | K82: 261439.75 | L82: 457159.35 | N82: =SUM(I82:M82) -> 3831687.1 | O82: =$E82*I82 -> 0 | P82: =$E82*J82 -> 3113088 | Q82: =$E82*K82 -> 261439.75 | R82: =$E82*L82 -> 457159.35 | S82: =$E82*M82 -> 0 | T82: =SUM(O82:S82) -> 3831687.1 | V82: 1 | W82: =$V82*I82 -> 0 | X82: =$V82*J82 -> 3113088 | Y82: =$V82*K82 -> 261439.75 | Z82: =$V82*L82 -> 457159.35 | AA82: =$V82*M82 -> 0 | AB82: =SUM(W82:AA82) -> 3831687.1 | AE82: =$AD82*I82 -> 0 | AF82: =$AD82*J82 -> 0 | AG82: =$AD82*K82 -> 0 | AH82: =$AD82*L82 -> 0 | AI82: =$AD82*M82 -> 0 | AJ82: =SUM(AE82:AI82) -> 0 | AL82: =IFERROR(VLOOKUP($A82,Itemizado_Piping!C:Q,12,0),0) -> 0 | AM82: =IFERROR(VLOOKUP($A82,Itemizado_Piping!C:Q,13,0),0) -> 0 | AN82: =IFERROR(VLOOKUP($A82,Itemizado_Piping!C:Q,14,0),0) -> 0 | AQ82: =N82*AP82 -> 0
A83: 2.1.1.3.3 | C83: Montaje Ducto de Barras MT de 3000A | D83: uni | E83: 1 | G83: 130 | H83: =G83+F83 -> 130 | J83: 3498374 | K83: 293796.4 | L83: 513738.9 | N83: =SUM(I83:M83) -> 4305909.3 | O83: =$E83*I83 -> 0 | P83: =$E83*J83 -> 3498374 | Q83: =$E83*K83 -> 293796.4 | R83: =$E83*L83 -> 513738.9 | S83: =$E83*M83 -> 0 | T83: =SUM(O83:S83) -> 4305909.3 | V83: 1 | W83: =$V83*I83 -> 0 | X83: =$V83*J83 -> 3498374 | Y83: =$V83*K83 -> 293796.4 | Z83: =$V83*L83 -> 513738.9 | AA83: =$V83*M83 -> 0 | AB83: =SUM(W83:AA83) -> 4305909.3 | AE83: =$AD83*I83 -> 0 | AF83: =$AD83*J83 -> 0 | AG83: =$AD83*K83 -> 0 | AH83: =$AD83*L83 -> 0 | AI83: =$AD83*M83 -> 0 | AJ83: =SUM(AE83:AI83) -> 0 | AL83: =IFERROR(VLOOKUP($A83,Itemizado_Piping!C:Q,12,0),0) -> 0 | AM83: =IFERROR(VLOOKUP($A83,Itemizado_Piping!C:Q,13,0),0) -> 0 | AN83: =IFERROR(VLOOKUP($A83,Itemizado_Piping!C:Q,14,0),0) -> 0 | AQ83: =N83*AP83 -> 0
A84: 2.1.1.3.4 | C84: Montaje Sistema Sobrepresión, Exterior | D84: uni | E84: 1 | G84: 35 | H84: =G84+F84 -> 35 | J84: 912408 | K84: 76624.793 | L84: 133987.81 | N84: =SUM(I84:M84) -> 1123020.6 | O84: =$E84*I84 -> 0 | P84: =$E84*J84 -> 912408 | Q84: =$E84*K84 -> 76624.793 | R84: =$E84*L84 -> 133987.81 | S84: =$E84*M84 -> 0 | T84: =SUM(O84:S84) -> 1123020.6 | V84: 1 | W84: =$V84*I84 -> 0 | X84: =$V84*J84 -> 912408 | Y84: =$V84*K84 -> 76624.793 | Z84: =$V84*L84 -> 133987.81 | AA84: =$V84*M84 -> 0 | AB84: =SUM(W84:AA84) -> 1123020.6 | AE84: =$AD84*I84 -> 0 | AF84: =$AD84*J84 -> 0 | AG84: =$AD84*K84 -> 0 | AH84: =$AD84*L84 -> 0 | AI84: =$AD84*M84 -> 0 | AJ84: =SUM(AE84:AI84) -> 0 | AL84: =IFERROR(VLOOKUP($A84,Itemizado_Piping!C:Q,12,0),0) -> 0 | AM84: =IFERROR(VLOOKUP($A84,Itemizado_Piping!C:Q,13,0),0) -> 0 | AN84: =IFERROR(VLOOKUP($A84,Itemizado_Piping!C:Q,14,0),0) -> 0 | AQ84: =N84*AP84 -> 0
A85: 2.1.1.3.5 | C85: Montaje Resistencia de Puesta a Tierra, Exterior | D85: uni | E85: 1 | G85: 62 | H85: =G85+F85 -> 62 | J85: 1552204 | K85: 130355.4 | L85: 227942.34 | N85: =SUM(I85:M85) -> 1910501.7 | O85: =$E85*I85 -> 0 | P85: =$E85*J85 -> 1552204 | Q85: =$E85*K85 -> 130355.4 | R85: =$E85*L85 -> 227942.34 | S85: =$E85*M85 -> 0 | T85: =SUM(O85:S85) -> 1910501.7 | V85: 1 | W85: =$V85*I85 -> 0 | X85: =$V85*J85 -> 1552204 | Y85: =$V85*K85 -> 130355.4 | Z85: =$V85*L85 -> 227942.34 | AA85: =$V85*M85 -> 0 | AB85: =SUM(W85:AA85) -> 1910501.7 | AE85: =$AD85*I85 -> 0 | AF85: =$AD85*J85 -> 0 | AG85: =$AD85*K85 -> 0 | AH85: =$AD85*L85 -> 0 | AI85: =$AD85*M85 -> 0 | AJ85: =SUM(AE85:AI85) -> 0 | AL85: =IFERROR(VLOOKUP($A85,Itemizado_Piping!C:Q,12,0),0) -> 0 | AM85: =IFERROR(VLOOKUP($A85,Itemizado_Piping!C:Q,13,0),0) -> 0 | AN85: =IFERROR(VLOOKUP($A85,Itemizado_Piping!C:Q,14,0),0) -> 0 | AQ85: =N85*AP85 -> 0
A86: 2.1.1.3.6 | C86: Montaje Transformador 10/13 MVA,KNAN KNAF 23/4,16 kV, Exterior | D86: uni | E86: 1 | G86: 380 | H86: =G86+F86 -> 380 | J86: 17837228 | K86: 1497985.4 | L86: 2619410.6 | N86: =SUM(I86:M86) -> 21954624 | O86: =$E86*I86 -> 0 | P86: =$E86*J86 -> 17837228 | Q86: =$E86*K86 -> 1497985.4 | R86: =$E86*L86 -> 2619410.6 | S86: =$E86*M86 -> 0 | T86: =SUM(O86:S86) -> 21954624 | V86: 1 | W86: =$V86*I86 -> 0 | X86: =$V86*J86 -> 17837228 | Y86: =$V86*K86 -> 1497985.4 | Z86: =$V86*L86 -> 2619410.6 | AA86: =$V86*M86 -> 0 | AB86: =SUM(W86:AA86) -> 21954624 | AE86: =$AD86*I86 -> 0 | AF86: =$AD86*J86 -> 0 | AG86: =$AD86*K86 -> 0 | AH86: =$AD86*L86 -> 0 | AI86: =$AD86*M86 -> 0 | AJ86: =SUM(AE86:AI86) -> 0 | AL86: =IFERROR(VLOOKUP($A86,Itemizado_Piping!C:Q,12,0),0) -> 0 | AM86: =IFERROR(VLOOKUP($A86,Itemizado_Piping!C:Q,13,0),0) -> 0 | AN86: =IFERROR(VLOOKUP($A86,Itemizado_Piping!C:Q,14,0),0) -> 0 | AQ86: =N86*AP86 -> 0
A87: 2.1.1.3.7 | C87: Montaje Transformador 300 KVA de 4,16/0,6 kV, Exterior | D87: uni | E87: 1 | G87: 120 | H87: =G87+F87 -> 120 | J87: 7303228 | K87: 613331.24 | L87: 1072484.6 | N87: =SUM(I87:M87) -> 8989043.9 | O87: =$E87*I87 -> 0 | P87: =$E87*J87 -> 7303228 | Q87: =$E87*K87 -> 613331.24 | R87: =$E87*L87 -> 1072484.6 | S87: =$E87*M87 -> 0 | T87: =SUM(O87:S87) -> 8989043.9 | V87: 1 | W87: =$V87*I87 -> 0 | X87: =$V87*J87 -> 7303228 | Y87: =$V87*K87 -> 613331.24 | Z87: =$V87*L87 -> 1072484.6 | AA87: =$V87*M87 -> 0 | AB87: =SUM(W87:AA87) -> 8989043.9 | AE87: =$AD87*I87 -> 0 | AF87: =$AD87*J87 -> 0 | AG87: =$AD87*K87 -> 0 | AH87: =$AD87*L87 -> 0 | AI87: =$AD87*M87 -> 0 | AJ87: =SUM(AE87:AI87) -> 0 | AL87: =IFERROR(VLOOKUP($A87,Itemizado_Piping!C:Q,12,0),0) -> 0 | AM87: =IFERROR(VLOOKUP($A87,Itemizado_Piping!C:Q,13,0),0) -> 0 | AN87: =IFERROR(VLOOKUP($A87,Itemizado_Piping!C:Q,14,0),0) -> 0 | AQ87: =N87*AP87 -> 0
A88: 2.1.1.3.8 | C88: Montaje Transformador 150 KVA de 600/400-231 V, Exterior | D88: uni | E88: 1 | G88: 80 | H88: =G88+F88 -> 80 | J88: 1998460 | K88: 167832.36 | L88: 293475.38 | N88: =SUM(I88:M88) -> 2459767.7 | O88: =$E88*I88 -> 0 | P88: =$E88*J88 -> 1998460 | Q88: =$E88*K88 -> 167832.36 | R88: =$E88*L88 -> 293475.38 | S88: =$E88*M88 -> 0 | T88: =SUM(O88:S88) -> 2459767.7 | V88: 1 | W88: =$V88*I88 -> 0 | X88: =$V88*J88 -> 1998460 | Y88: =$V88*K88 -> 167832.36 | Z88: =$V88*L88 -> 293475.38 | AA88: =$V88*M88 -> 0 | AB88: =SUM(W88:AA88) -> 2459767.7 | AE88: =$AD88*I88 -> 0 | AF88: =$AD88*J88 -> 0 | AG88: =$AD88*K88 -> 0 | AH88: =$AD88*L88 -> 0 | AI88: =$AD88*M88 -> 0 | AJ88: =SUM(AE88:AI88) -> 0 | AL88: =IFERROR(VLOOKUP($A88,Itemizado_Piping!C:Q,12,0),0) -> 0 | AM88: =IFERROR(VLOOKUP($A88,Itemizado_Piping!C:Q,13,0),0) -> 0 | AN88: =IFERROR(VLOOKUP($A88,Itemizado_Piping!C:Q,14,0),0) -> 0 | AQ88: =N88*AP88 -> 0
A89: 2.1.1.3.9 | C89: Montaje Celda GIS a piso 23kV, y apoyo en puesta marcha | D89: uni | E89: 2 | G89: 140 | H89: =G89+F89 -> 140 | J89: 4871904 | K89: 409146.6 | L89: 715442.83 | N89: =SUM(I89:M89) -> 5996493.4 | O89: =$E89*I89 -> 0 | P89: =$E89*J89 -> 9743808 | Q89: =$E89*K89 -> 818293.21 | R89: =$E89*L89 -> 1430885.7 | S89: =$E89*M89 -> 0 | T89: =SUM(O89:S89) -> 11992987 | V89: 2 | W89: =$V89*I89 -> 0 | X89: =$V89*J89 -> 9743808 | Y89: =$V89*K89 -> 818293.21 | Z89: =$V89*L89 -> 1430885.7 | AA89: =$V89*M89 -> 0 | AB89: =SUM(W89:AA89) -> 11992987 | AE89: =$AD89*I89 -> 0 | AF89: =$AD89*J89 -> 0 | AG89: =$AD89*K89 -> 0 | AH89: =$AD89*L89 -> 0 | AI89: =$AD89*M89 -> 0 | AJ89: =SUM(AE89:AI89) -> 0 | AL89: =IFERROR(VLOOKUP($A89,Itemizado_Piping!C:Q,12,0),0) -> 0 | AM89: =IFERROR(VLOOKUP($A89,Itemizado_Piping!C:Q,13,0),0) -> 0 | AN89: =IFERROR(VLOOKUP($A89,Itemizado_Piping!C:Q,14,0),0) -> 0 | AQ89: =N89*AP89 -> 0
A90: 2.1.1.4 | C90: Banco de ductos servicio pesado
A91: 2.1.1.4.1 | C91: Construcción Cámara Eléctrica de hormigón 2000x2000x2400 mm con tapa | D91: un | E91: 8 | G91: 1060.701 | H91: =G91+F91 -> 1060.701 | J91: 6463960.8 | K91: 542848.87 | L91: 949237.58 | N91: =SUM(I91:M91) -> 7956047.3 | O91: =$E91*I91 -> 0 | P91: =$E91*J91 -> 51711686 | Q91: =$E91*K91 -> 4342790.9 | R91: =$E91*L91 -> 7593900.7 | S91: =$E91*M91 -> 0 | T91: =SUM(O91:S91) -> 63648378 | V91: 8 | W91: =$V91*I91 -> 0 | X91: =$V91*J91 -> 51711686 | Y91: =$V91*K91 -> 4342790.9 | Z91: =$V91*L91 -> 7593900.7 | AA91: =$V91*M91 -> 0 | AB91: =SUM(W91:AA91) -> 63648378 | AE91: =$AD91*I91 -> 0 | AF91: =$AD91*J91 -> 0 | AG91: =$AD91*K91 -> 0 | AH91: =$AD91*L91 -> 0 | AI91: =$AD91*M91 -> 0 | AJ91: =SUM(AE91:AI91) -> 0 | AL91: =IFERROR(VLOOKUP($A91,Itemizado_Piping!C:Q,12,0),0) -> 0 | AM91: =IFERROR(VLOOKUP($A91,Itemizado_Piping!C:Q,13,0),0) -> 0 | AN91: =IFERROR(VLOOKUP($A91,Itemizado_Piping!C:Q,14,0),0) -> 0 | AQ91: =N91*AP91 -> 0
A92: 2.1.1.4.2 | C92: Construcción Banco de Ductos reforzado para tránsito pesado de 1610x1100 mm | D92: m | E92: 93 | G92: 4241.414 | H92: =G92+F92 -> 4241.414 | J92: 2051054.1 | K92: 172249.25 | L92: 301198.86 | N92: =SUM(I92:M92) -> 2524502.2 | O92: =$E92*I92 -> 0 | P92: =$E92*J92 -> 1.9074803e+08 | Q92: =$E92*K92 -> 16019180 | R92: =$E92*L92 -> 28011494 | S92: =$E92*M92 -> 0 | T92: =SUM(O92:S92) -> 2.347787e+08 | V92: 93 | W92: =$V92*I92 -> 0 | X92: =$V92*J92 -> 1.9074803e+08 | Y92: =$V92*K92 -> 16019180 | Z92: =$V92*L92 -> 28011494 | AA92: =$V92*M92 -> 0 | AB92: =SUM(W92:AA92) -> 2.347787e+08 | AE92: =$AD92*I92 -> 0 | AF92: =$AD92*J92 -> 0 | AG92: =$AD92*K92 -> 0 | AH92: =$AD92*L92 -> 0 | AI92: =$AD92*M92 -> 0 | AJ92: =SUM(AE92:AI92) -> 0 | AL92: =IFERROR(VLOOKUP($A92,Itemizado_Piping!C:Q,12,0),0) -> 0 | AM92: =IFERROR(VLOOKUP($A92,Itemizado_Piping!C:Q,13,0),0) -> 0 | AN92: =IFERROR(VLOOKUP($A92,Itemizado_Piping!C:Q,14,0),0) -> 0 | AQ92: =N92*AP92 -> 0
A93: 2.1.1.4.3 | C93: Construcción Banco de Ductos reforzado para tránsito pesado de 600x600 mm | D93: m | E93: 252 | G93: 4871.689 | H93: =G93+F93 -> 4871.689 | J93: 929296.86 | K93: 78043.131 | L93: 136467.95 | N93: =SUM(I93:M93) -> 1143807.9 | O93: =$E93*I93 -> 0 | P93: =$E93*J93 -> 2.3418281e+08 | Q93: =$E93*K93 -> 19666869 | R93: =$E93*L93 -> 34389924 | S93: =$E93*M93 -> 0 | T93: =SUM(O93:S93) -> 2.882396e+08 | V93: 252 | W93: =$V93*I93 -> 0 | X93: =$V93*J93 -> 2.3418281e+08 | Y93: =$V93*K93 -> 19666869 | Z93: =$V93*L93 -> 34389924 | AA93: =$V93*M93 -> 0 | AB93: =SUM(W93:AA93) -> 2.882396e+08 | AE93: =$AD93*I93 -> 0 | AF93: =$AD93*J93 -> 0 | AG93: =$AD93*K93 -> 0 | AH93: =$AD93*L93 -> 0 | AI93: =$AD93*M93 -> 0 | AJ93: =SUM(AE93:AI93) -> 0 | AL93: =IFERROR(VLOOKUP($A93,Itemizado_Piping!C:Q,12,0),0) -> 0 | AM93: =IFERROR(VLOOKUP($A93,Itemizado_Piping!C:Q,13,0),0) -> 0 | AN93: =IFERROR(VLOOKUP($A93,Itemizado_Piping!C:Q,14,0),0) -> 0 | AQ93: =N93*AP93 -> 0
A94: 2.1.1.4.4 | C94: Suministro y Montaje cable desnudo Cu de 4/0 | D94: m | E94: 700 | G94: 322 | H94: =G94+F94 -> 322 | J94: 21216.72 | K94: 1781.798 | L94: 3115.6916 | N94: =SUM(I94:M94) -> 26114.21 | O94: =$E94*I94 -> 0 | P94: =$E94*J94 -> 14851704 | Q94: =$E94*K94 -> 1247258.6 | R94: =$E94*L94 -> 2180984.1 | S94: =$E94*M94 -> 0 | T94: =SUM(O94:S94) -> 18279947 | V94: 700 | W94: =$V94*I94 -> 0 | X94: =$V94*J94 -> 14851704 | Y94: =$V94*K94 -> 1247258.6 | Z94: =$V94*L94 -> 2180984.1 | AA94: =$V94*M94 -> 0 | AB94: =SUM(W94:AA94) -> 18279947 | AE94: =$AD94*I94 -> 0 | AF94: =$AD94*J94 -> 0 | AG94: =$AD94*K94 -> 0 | AH94: =$AD94*L94 -> 0 | AI94: =$AD94*M94 -> 0 | AJ94: =SUM(AE94:AI94) -> 0 | AL94: =IFERROR(VLOOKUP($A94,Itemizado_Piping!C:Q,12,0),0) -> 0 | AM94: =IFERROR(VLOOKUP($A94,Itemizado_Piping!C:Q,13,0),0) -> 0 | AN94: =IFERROR(VLOOKUP($A94,Itemizado_Piping!C:Q,14,0),0) -> 0 | AQ94: =N94*AP94 -> 0
A95: 2.1.1.4.5 | C95: Suministro y Montaje de conduit PVC 2" SCH-80 | D95: m | E95: 210 | G95: 378 | H95: =G95+F95 -> 378 | J95: 48083.04 | K95: 4038.0542 | L95: 7061.0312 | N95: =SUM(I95:M95) -> 59182.125 | O95: =$E95*I95 -> 0 | P95: =$E95*J95 -> 10097438 | Q95: =$E95*K95 -> 847991.39 | R95: =$E95*L95 -> 1482816.5 | S95: =$E95*M95 -> 0 | T95: =SUM(O95:S95) -> 12428246 | V95: 210 | W95: =$V95*I95 -> 0 | X95: =$V95*J95 -> 10097438 | Y95: =$V95*K95 -> 847991.39 | Z95: =$V95*L95 -> 1482816.5 | AA95: =$V95*M95 -> 0 | AB95: =SUM(W95:AA95) -> 12428246 | AE95: =$AD95*I95 -> 0 | AF95: =$AD95*J95 -> 0 | AG95: =$AD95*K95 -> 0 | AH95: =$AD95*L95 -> 0 | AI95: =$AD95*M95 -> 0 | AJ95: =SUM(AE95:AI95) -> 0 | AL95: =IFERROR(VLOOKUP($A95,Itemizado_Piping!C:Q,12,0),0) -> 0 | AM95: =IFERROR(VLOOKUP($A95,Itemizado_Piping!C:Q,13,0),0) -> 0 | AN95: =IFERROR(VLOOKUP($A95,Itemizado_Piping!C:Q,14,0),0) -> 0 | AQ95: =N95*AP95 -> 0
A96: 2.1.1.4.6 | C96: Suministro y Montaje de conduit PVC 4" SCH-80 | D96: m | E96: 1537 | G96: 2612.9 | H96: =G96+F96 -> 2612.9 | J96: 54215.158 | K96: 4553.0347 | L96: 7961.5374 | N96: =SUM(I96:M96) -> 66729.73 | O96: =$E96*I96 -> 0 | P96: =$E96*J96 -> 83328698 | Q96: =$E96*K96 -> 6998014.3 | R96: =$E96*L96 -> 12236883 | S96: =$E96*M96 -> 0 | T96: =SUM(O96:S96) -> 1.025636e+08 | V96: 1537 | W96: =$V96*I96 -> 0 | X96: =$V96*J96 -> 83328698 | Y96: =$V96*K96 -> 6998014.3 | Z96: =$V96*L96 -> 12236883 | AA96: =$V96*M96 -> 0 | AB96: =SUM(W96:AA96) -> 1.025636e+08 | AE96: =$AD96*I96 -> 0 | AF96: =$AD96*J96 -> 0 | AG96: =$AD96*K96 -> 0 | AH96: =$AD96*L96 -> 0 | AI96: =$AD96*M96 -> 0 | AJ96: =SUM(AE96:AI96) -> 0 | AL96: =IFERROR(VLOOKUP($A96,Itemizado_Piping!C:Q,12,0),0) -> 0 | AM96: =IFERROR(VLOOKUP($A96,Itemizado_Piping!C:Q,13,0),0) -> 0 | AN96: =IFERROR(VLOOKUP($A96,Itemizado_Piping!C:Q,14,0),0) -> 0 | AQ96: =N96*AP96 -> 0
A97: 2.1.1.4.7 | C97: Suministro y Montaje de conduit PVC 6" SCH-81 | D97: m | E97: 2130 | G97: 4473 | H97: =G97+F97 -> 4473 | J97: 77647.32 | K97: 6520.8874 | L97: 11402.568 | N97: =SUM(I97:M97) -> 95570.776 | O97: =$E97*I97 -> 0 | P97: =$E97*J97 -> 1.6538879e+08 | Q97: =$E97*K97 -> 13889490 | R97: =$E97*L97 -> 24287470 | S97: =$E97*M97 -> 0 | T97: =SUM(O97:S97) -> 2.0356575e+08 | V97: 2130 | W97: =$V97*I97 -> 0 | X97: =$V97*J97 -> 1.6538879e+08 | Y97: =$V97*K97 -> 13889490 | Z97: =$V97*L97 -> 24287470 | AA97: =$V97*M97 -> 0 | AB97: =SUM(W97:AA97) -> 2.0356575e+08 | AE97: =$AD97*I97 -> 0 | AF97: =$AD97*J97 -> 0 | AG97: =$AD97*K97 -> 0 | AH97: =$AD97*L97 -> 0 | AI97: =$AD97*M97 -> 0 | AJ97: =SUM(AE97:AI97) -> 0 | AL97: =IFERROR(VLOOKUP($A97,Itemizado_Piping!C:Q,12,0),0) -> 0 | AM97: =IFERROR(VLOOKUP($A97,Itemizado_Piping!C:Q,13,0),0) -> 0 | AN97: =IFERROR(VLOOKUP($A97,Itemizado_Piping!C:Q,14,0),0) -> 0 | AQ97: =N97*AP97 -> 0
A98: 2.1.1.5 | C98: Luminarias
A99: 2.1.1.5.1 | C99: Suministro y Montaje, F1: COOLON LED Lighting HT66-NWT-NOP-RPS HT66 LED Luminaria 320 W y Poste de 9 metros | D99: uni | E99: 5 | G99: 140 | H99: =G99+F99 -> 140 | J99: 1346826 | K99: 113107.58 | L99: 197782.43 | N99: =SUM(I99:M99) -> 1657716 | O99: =$E99*I99 -> 0 | P99: =$E99*J99 -> 6734130 | Q99: =$E99*K99 -> 565537.91 | R99: =$E99*L99 -> 988912.14 | S99: =$E99*M99 -> 0 | T99: =SUM(O99:S99) -> 8288580.1 | V99: 5 | W99: =$V99*I99 -> 0 | X99: =$V99*J99 -> 6734130 | Y99: =$V99*K99 -> 565537.91 | Z99: =$V99*L99 -> 988912.14 | AA99: =$V99*M99 -> 0 | AB99: =SUM(W99:AA99) -> 8288580.1 | AE99: =$AD99*I99 -> 0 | AF99: =$AD99*J99 -> 0 | AG99: =$AD99*K99 -> 0 | AH99: =$AD99*L99 -> 0 | AI99: =$AD99*M99 -> 0 | AJ99: =SUM(AE99:AI99) -> 0 | AL99: =IFERROR(VLOOKUP($A99,Itemizado_Piping!C:Q,12,0),0) -> 0 | AM99: =IFERROR(VLOOKUP($A99,Itemizado_Piping!C:Q,13,0),0) -> 0 | AN99: =IFERROR(VLOOKUP($A99,Itemizado_Piping!C:Q,14,0),0) -> 0 | AQ99: =N99*AP99 -> 0
A100: 2.1.1.5.2 | C100: Suministro y Montaje, F3: Holophane PLED2 05L 4K AS UN NA G L5H PETROLUX 2 LED WET LOCATION | D100: uni | E100: 4 | G100: 80 | H100: =G100+F100 -> 80 | J100: 1288800 | K100: 108234.51 | L100: 189261.27 | N100: =SUM(I100:M100) -> 1586295.8 | O100: =$E100*I100 -> 0 | P100: =$E100*J100 -> 5155200 | Q100: =$E100*K100 -> 432938.04 | R100: =$E100*L100 -> 757045.06 | S100: =$E100*M100 -> 0 | T100: =SUM(O100:S100) -> 6345183.1 | V100: 4 | W100: =$V100*I100 -> 0 | X100: =$V100*J100 -> 5155200 | Y100: =$V100*K100 -> 432938.04 | Z100: =$V100*L100 -> 757045.06 | AA100: =$V100*M100 -> 0 | AB100: =SUM(W100:AA100) -> 6345183.1 | AE100: =$AD100*I100 -> 0 | AF100: =$AD100*J100 -> 0 | AG100: =$AD100*K100 -> 0 | AH100: =$AD100*L100 -> 0 | AI100: =$AD100*M100 -> 0 | AJ100: =SUM(AE100:AI100) -> 0 | AL100: =IFERROR(VLOOKUP($A100,Itemizado_Piping!C:Q,12,0),0) -> 0 | AM100: =IFERROR(VLOOKUP($A100,Itemizado_Piping!C:Q,13,0),0) -> 0 | AN100: =IFERROR(VLOOKUP($A100,Itemizado_Piping!C:Q,14,0),0) -> 0 | AQ100: =N100*AP100 -> 0
A101: 2.1.1.5.3 | C101: Suministro y Montaje, F3: Holophane PLED2 05L 4K AS UN NA G L5H PETROLUX 2 LED WET LOCATION y poste de 2.5 metros | D101: uni | E101: 2 | G101: 56 | H101: =G101+F101 -> 56 | J101: 1515536 | K101: 127275.99 | L101: 222557.62 | N101: =SUM(I101:M101) -> 1865369.6 | O101: =$E101*I101 -> 0 | P101: =$E101*J101 -> 3031072 | Q101: =$E101*K101 -> 254551.98 | R101: =$E101*L101 -> 445115.24 | S101: =$E101*M101 -> 0 | T101: =SUM(O101:S101) -> 3730739.2 | V101: 2 | W101: =$V101*I101 -> 0 | X101: =$V101*J101 -> 3031072 | Y101: =$V101*K101 -> 254551.98 | Z101: =$V101*L101 -> 445115.24 | AA101: =$V101*M101 -> 0 | AB101: =SUM(W101:AA101) -> 3730739.2 | AE101: =$AD101*I101 -> 0 | AF101: =$AD101*J101 -> 0 | AG101: =$AD101*K101 -> 0 | AH101: =$AD101*L101 -> 0 | AI101: =$AD101*M101 -> 0 | AJ101: =SUM(AE101:AI101) -> 0 | AL101: =IFERROR(VLOOKUP($A101,Itemizado_Piping!C:Q,12,0),0) -> 0 | AM101: =IFERROR(VLOOKUP($A101,Itemizado_Piping!C:Q,13,0),0) -> 0 | AN101: =IFERROR(VLOOKUP($A101,Itemizado_Piping!C:Q,14,0),0) -> 0 | AQ101: =N101*AP101 -> 0
...

Sheet Itemizado_Piping
C2: Aproximado | D2: M | E2: =+SUMIFS(H5:H93,G5:G93,$D$2) -> 20784 | O2: FORECAST | S2: Avance FISICO Ponderado | W2: HH | Y2: Estado de Pago
H3: =SUBTOTAL(9,H5:H99) -> 24883 | J3: =+SUBTOTAL(9,J5:J93) -> 1.0517591e+10 | L3: =+SUBTOTAL(9,L5:L93) -> 152326.71 | O3: =SUBTOTAL(9,O5:O93) -> 19288.671 | P3: =SUBTOTAL(9,P5:P93) -> 141883.51 | Q3: =SUBTOTAL(9,Q5:Q93) -> 8.8948955e+09 | S3: =SUBTOTAL(9,S5:S93) -> 6349.206 | T3: =SUBTOTAL(9,T5:T93) -> 0 | U3: =SUBTOTAL(9,U5:U93) -> 6349.206 | W3: =SUM(W8:W99) -> 0 | Y3: =SUM(Y8:Y93) -> 5148.3261 | Z3: =SUM(Z8:Z93) -> 1271.8 | AA3: =SUM(AA8:AA93) -> 6420.126 | AB3: =SUM(AB8:AB93) -> 2.3333368e+09 | AC3: =SUM(AC8:AC93) -> 6.1692476e+08 | AD3: =SUM(AD8:AD93) -> 2.9502616e+09
B4: N° | C4: ITEM | D4: Area | E4: APORTE | F4: DESCRIPCIÓN | G4: UNI | H4: CANT. | I4: Precio Unitario | J4: Precio Total | K4: HH Unitaria | L4: HH Total | M4: Rendimiento | O4: POM | P4: HH | Q4: $$$ | S4: Avance Ponderado Anterior | T4: Avance Ponderado Presente | U4: Avance Ponderado Acumulado | W4: HH ponderado Actual | Y4: EDP Anterior | Z4: EDP Presente | AA4: EDP Acumulado | AB4: EDP Anterior $ | AC4: EDP Presente $ | AD4: EDP Acumulado $
B5: 1 | C5: 2.2 | D5: =VLOOKUP(C5,Volumen_Obra!B:C,2,0) -> REGADIO LIXIVIACION SECUNDARIA | F5: Regadío Lixiviación Secundaria
B6: 2 | C6: 2.2.2 | D6: =VLOOKUP(C6,Volumen_Obra!B:C,2,0) -> LINEAS DE RIEGO | F6: Líneas de Riego
B7: 3 | C7: 2.2.2.2 | D7: =VLOOKUP(C7,Volumen_Obra!B:C,2,0) -> LINEAS DE RIEGO | F7: Piping
B8: 4 | C8: 2.2.2.2.1 | D8: =VLOOKUP(C8,Volumen_Obra!B:C,2,0) -> LINEAS DE RIEGO | E8: PPD | F8: Tie-In 3631-001 Cañería HDPE 1000 mm | G8: gl | H8: 1 | I8: 18678629 | J8: =+H8*I8 -> 18678629 | K8: =375.44+30.036 -> 405.476 | L8: =+H8*K8 -> 405.476 | M8: =+K8/H8 -> 405.476 | O8: =SUMIFS('TIE-IN_IMP'!$G$7:$G$13,'TIE-IN_IMP'!$C$7:$C$13,Itemizado_Piping!C8) -> 1 | P8: =IFERROR(O8*K8,0) -> 405.476 | Q8: =IFERROR(O8*I8,0) -> 18678629 | S8: 0 | T8: =+U8-S8 -> 0 | U8: =SUMIFS('TIE-IN_IMP'!$P$7:$P$13,'TIE-IN_IMP'!$C$7:$C$13,Itemizado_Piping!C8) -> 0 | W8: =+T8*K8 -> 0 | Y8: 0 | Z8: =AA8-Y8 -> 0 | AA8: =SUMIFS('TIE-IN_IMP'!$Y$7:$Y$13,'TIE-IN_IMP'!$C$7:$C$13,Itemizado_Piping!C8) -> 0 | AB8: 0 | AC8: =Z8*I8 -> 0 | AD8: =AA8*I8 -> 0
B9: 5 | C9: 2.2.2.2.2 | D9: =VLOOKUP(C9,Volumen_Obra!B:C,2,0) -> LINEAS DE RIEGO | E9: PPD | F9: Tie-In 3631-002 Cañería HDPE 710 mm | G9: gl | H9: 1 | I9: 10900118 | J9: =I9*H9 -> 10900118 | K9: =219.092+17.528 -> 236.62 | L9: =+H9*K9 -> 236.62 | M9: =+K9/H9 -> 236.62 | O9: =SUMIFS('TIE-IN_IMP'!$G$7:$G$13,'TIE-IN_IMP'!$C$7:$C$13,Itemizado_Piping!C9) -> 1 | P9: =IFERROR(O9*K9,0) -> 236.62 | Q9: =IFERROR(O9*I9,0) -> 10900118 | S9: 0 | T9: =+U9-S9 -> 0 | U9: =SUMIFS('TIE-IN_IMP'!$P$7:$P$13,'TIE-IN_IMP'!$C$7:$C$13,Itemizado_Piping!C9) -> 0 | W9: =+T9*K9 -> 0 | Y9: 0 | Z9: =AA9-Y9 -> 0 | AA9: =SUMIFS('TIE-IN_IMP'!$Y$7:$Y$13,'TIE-IN_IMP'!$C$7:$C$13,Itemizado_Piping!C9) -> 0 | AB9: 0 | AC9: =Z9*I9 -> 0 | AD9: =AA9*I9 -> 0
B10: 6 | C10: 2.2.2.2.3 | D10: =VLOOKUP(C10,Volumen_Obra!B:C,2,0) -> LINEAS DE RIEGO | E10: PPD | F10: Tie-In 3631-003 Cañería HDPE 1000 mm | G10: gl | H10: 1 | I10: 8779189.5 | J10: =I10*H10 -> 8779189.5 | K10: 94 | L10: =+H10*K10 -> 94 | M10: =+K10/H10 -> 94 | O10: =SUMIFS('TIE-IN_IMP'!$G$7:$G$13,'TIE-IN_IMP'!$C$7:$C$13,Itemizado_Piping!C10) -> 1 | P10: =IFERROR(O10*K10,0) -> 94 | Q10: =IFERROR(O10*I10,0) -> 8779189.5 | S10: 0 | T10: =+U10-S10 -> 0 | U10: =SUMIFS('TIE-IN_IMP'!$P$7:$P$13,'TIE-IN_IMP'!$C$7:$C$13,Itemizado_Piping!C10) -> 0 | W10: =+T10*K10 -> 0 | Y10: 0 | Z10: =AA10-Y10 -> 0 | AA10: =SUMIFS('TIE-IN_IMP'!$Y$7:$Y$13,'TIE-IN_IMP'!$C$7:$C$13,Itemizado_Piping!C10) -> 0 | AB10: 0 | AC10: =Z10*I10 -> 0 | AD10: =AA10*I10 -> 0
B11: 7 | C11: 2.2.2.2.4 | D11: =VLOOKUP(C11,Volumen_Obra!B:C,2,0) -> LINEAS DE RIEGO | E11: PPD | F11: Tie-In 3631-004 Cañería HDPE 900 mm | G11: gl | H11: 1 | I11: 5525601.1 | J11: =I11*H11 -> 5525601.1 | K11: =111.064+8.886 -> 119.95 | L11: =+H11*K11 -> 119.95 | M11: =+K11/H11 -> 119.95 | O11: =SUMIFS('TIE-IN_IMP'!$G$7:$G$13,'TIE-IN_IMP'!$C$7:$C$13,Itemizado_Piping!C11) -> 1 | P11: =IFERROR(O11*K11,0) -> 119.95 | Q11: =IFERROR(O11*I11,0) -> 5525601.1 | S11: 0 | T11: =+U11-S11 -> 0 | U11: =SUMIFS('TIE-IN_IMP'!$P$7:$P$13,'TIE-IN_IMP'!$C$7:$C$13,Itemizado_Piping!C11) -> 0 | W11: =+T11*K11 -> 0 | Y11: 0 | Z11: =AA11-Y11 -> 0 | AA11: =SUMIFS('TIE-IN_IMP'!$Y$7:$Y$13,'TIE-IN_IMP'!$C$7:$C$13,Itemizado_Piping!C11) -> 0 | AB11: 0 | AC11: =Z11*I11 -> 0 | AD11: =AA11*I11 -> 0
B12: 8 | C12: 2.2.2.2.5 | D12: =VLOOKUP(C12,Volumen_Obra!B:C,2,0) -> LINEAS DE RIEGO | E12: PPD | F12: Tie-In 3631-005 Cañería HDPE 900 mm | G12: gl | H12: 1 | I12: 5585302.6 | J12: =I12*H12 -> 5585302.6 | K12: =112.264+8.982 -> 121.246 | L12: =+H12*K12 -> 121.246 | M12: =+K12/H12 -> 121.246 | O12: =SUMIFS('TIE-IN_IMP'!$G$7:$G$13,'TIE-IN_IMP'!$C$7:$C$13,Itemizado_Piping!C12) -> 1 | P12: =IFERROR(O12*K12,0) -> 121.246 | Q12: =IFERROR(O12*I12,0) -> 5585302.6 | S12: 0 | T12: =+U12-S12 -> 0 | U12: =SUMIFS('TIE-IN_IMP'!$P$7:$P$13,'TIE-IN_IMP'!$C$7:$C$13,Itemizado_Piping!C12) -> 0 | W12: =+T12*K12 -> 0 | Y12: 0 | Z12: =AA12-Y12 -> 0 | AA12: =SUMIFS('TIE-IN_IMP'!$Y$7:$Y$13,'TIE-IN_IMP'!$C$7:$C$13,Itemizado_Piping!C12) -> 0 | AB12: 0 | AC12: =Z12*I12 -> 0 | AD12: =AA12*I12 -> 0
B13: 9 | C13: 2.2.2.2.6 | D13: =VLOOKUP(C13,Volumen_Obra!B:C,2,0) -> LINEAS DE RIEGO | E13: PPD | F13: Tie-In 3631-006 Cañería HDPE 710 mm | G13: gl | H13: 1 | I13: 3407125.9 | J13: =I13*H13 -> 3407125.9 | K13: =68.483+5.479 -> 73.962 | L13: =+H13*K13 -> 73.962 | M13: =+K13/H13 -> 73.962 | O13: =SUMIFS('TIE-IN_IMP'!$G$7:$G$13,'TIE-IN_IMP'!$C$7:$C$13,Itemizado_Piping!C13) -> 1 | P13: =IFERROR(O13*K13,0) -> 73.962 | Q13: =IFERROR(O13*I13,0) -> 3407125.9 | S13: 0 | T13: =+U13-S13 -> 0 | U13: =SUMIFS('TIE-IN_IMP'!$P$7:$P$13,'TIE-IN_IMP'!$C$7:$C$13,Itemizado_Piping!C13) -> 0 | W13: =+T13*K13 -> 0 | Y13: 0 | Z13: =AA13-Y13 -> 0 | AA13: =SUMIFS('TIE-IN_IMP'!$Y$7:$Y$13,'TIE-IN_IMP'!$C$7:$C$13,Itemizado_Piping!C13) -> 0 | AB13: 0 | AC13: =Z13*I13 -> 0 | AD13: =AA13*I13 -> 0
B14: 10 | C14: 2.2.2.2.7 | D14: =VLOOKUP(C14,Volumen_Obra!B:C,2,0) -> LINEAS DE RIEGO | E14: PPD | F14: Tie-In 3631-007 Cañería HDPE 630 mm | G14: gl | H14: 1 | I14: 17690199 | J14: =I14*H14 -> 17690199 | K14: =355.573+28.446 -> 384.019 | L14: =+H14*K14 -> 384.019 | M14: =+K14/H14 -> 384.019 | O14: =SUMIFS('TIE-IN_IMP'!$G$7:$G$13,'TIE-IN_IMP'!$C$7:$C$13,Itemizado_Piping!C14) -> 1 | P14: =IFERROR(O14*K14,0) -> 384.019 | Q14: =IFERROR(O14*I14,0) -> 17690199 | S14: 0 | T14: =+U14-S14 -> 0 | U14: =SUMIFS('TIE-IN_IMP'!$P$7:$P$13,'TIE-IN_IMP'!$C$7:$C$13,Itemizado_Piping!C14) -> 0 | W14: =+T14*K14 -> 0 | Y14: 0 | Z14: =AA14-Y14 -> 0 | AA14: =SUMIFS('TIE-IN_IMP'!$Y$7:$Y$13,'TIE-IN_IMP'!$C$7:$C$13,Itemizado_Piping!C14) -> 0 | AB14: 0 | AC14: =Z14*I14 -> 0 | AD14: =AA14*I14 -> 0
B15: 11 | C15: 2.2.2.2.8 | D15: =VLOOKUP(C15,Volumen_Obra!B:C,2,0) -> LINEAS DE RIEGO | E15: PPD | F15: Sumnistro e Instalación Cañería titanio gr. 2 sch 10S sin costura diámetro 2" | G15: m | H15: 8 | I15: 754456.31 | J15: =I15*H15 -> 6035650.5 | K15: =29.264+0.164+2.342 -> 31.77 | L15: =+H15*K15 -> 254.16 | M15: =+K15/H15 -> 3.97125 | O15: =+SUMIFS(Cubicacion_IMP!$AD$6:$AD$50,Cubicacion_IMP!$C$6:$C$50,Itemizado_Piping!C15) -> 9 | P15: =IFERROR(O15*K15,0) -> 285.93 | Q15: =IFERROR(O15*I15,0) -> 6790106.8 | S15: 0 | T15: =+U15-S15 -> 0 | U15: =SUMIFS(Cubicacion_IMP!$AO$6:$AO$50,Cubicacion_IMP!$C$6:$C$50,Itemizado_Piping!C15) -> 0 | W15: =+T15*K15 -> 0 | Y15: 0 | Z15: =AA15-Y15 -> 0 | AA15: =SUMIFS(Cubicacion_IMP!$BB$6:$BB$50,Cubicacion_IMP!$C$6:$C$50,Itemizado_Piping!C15) -> 0 | AB15: 0 | AC15: =Z15*I15 -> 0 | AD15: =AA15*I15 -> 0
B16: 12 | C16: 2.2.2.2.9 | D16: =VLOOKUP(C16,Volumen_Obra!B:C,2,0) -> LINEAS DE RIEGO | E16: PPC | F16: Instalación Cañería titanio gr. 2 sch 10S soldada diámetro 4" | G16: m | H16: 4 | I16: 133192.16 | J16: =I16*H16 -> 532768.66 | K16: =35.283+0.483+2.823 -> 38.589 | L16: =+H16*K16 -> 154.356 | M16: =+K16/H16 -> 9.64725 | O16: =+SUMIFS(Cubicacion_IMP!$AD$6:$AD$50,Cubicacion_IMP!$C$6:$C$50,Itemizado_Piping!C16) -> 4 | P16: =IFERROR(O16*K16,0) -> 154.356 | Q16: =IFERROR(O16*I16,0) -> 532768.66 | S16: 0 | T16: =+U16-S16 -> 0 | U16: =SUMIFS(Cubicacion_IMP!$AO$6:$AO$50,Cubicacion_IMP!$C$6:$C$50,Itemizado_Piping!C16) -> 0 | W16: =+T16*K16 -> 0 | Y16: 0 | Z16: =AA16-Y16 -> 0 | AA16: =SUMIFS(Cubicacion_IMP!$BB$6:$BB$50,Cubicacion_IMP!$C$6:$C$50,Itemizado_Piping!C16) -> 0 | AB16: 0 | AC16: =Z16*I16 -> 0 | AD16: =AA16*I16 -> 0
B17: 13 | C17: 2.2.2.2.10 | D17: =VLOOKUP(C17,Volumen_Obra!B:C,2,0) -> LINEAS DE RIEGO | E17: PPC | F17: Instalación Cañería titanio gr. 2 sch 10S soldada diámetro 6" | G17: m | H17: 16 | I17: 162255.11 | J17: =I17*H17 -> 2596081.8 | K17: =6.248+0.623+0.5 -> 7.371 | L17: =+H17*K17 -> 117.936 | M17: =+K17/H17 -> 0.4606875 | O17: =+SUMIFS(Cubicacion_IMP!$AD$6:$AD$50,Cubicacion_IMP!$C$6:$C$50,Itemizado_Piping!C17) -> 0 | P17: =IFERROR(O17*K17,0) -> 0 | Q17: =IFERROR(O17*I17,0) -> 0 | S17: 0 | T17: =+U17-S17 -> 0 | U17: =SUMIFS(Cubicacion_IMP!$AO$6:$AO$50,Cubicacion_IMP!$C$6:$C$50,Itemizado_Piping!C17) -> 0 | W17: =+T17*K17 -> 0 | Y17: 0 | Z17: =AA17-Y17 -> 0 | AA17: =SUMIFS(Cubicacion_IMP!$BB$6:$BB$50,Cubicacion_IMP!$C$6:$C$50,Itemizado_Piping!C17) -> 0 | AB17: 0 | AC17: =Z17*I17 -> 0 | AD17: =AA17*I17 -> 0
